Workbook

Sheet 10-10-2023
B1: FECHA | C1: 45209
A2: No | B2: Servicio | C2: Docidentidad | D2: Usuario | E2: Nombre | F2: Dosis | G2: Medidadosis | H2: Frecuencia | I2: Unidadfrecuencia | J2: Tto Empirico | K2: Tto Dirigido | L2: cultivo | M2: Suspender | N2: Cambiar | R2: Observacionesorden | S2: Codigo Diagnostico | T2: Diagnostico | U2: Dosis | V2: Peso(kg) | W2: ITU | X2: ITB | Y2: NEUMONIA | Z2: MENINGITIS | AA2: Dosis recetada
N3: Escalar | O3: Desescalar | P3: RXN adversa | Q3: Por dosis
A4: 1 | B4: 601-4 | C4: 1023664134 | D4: ERICK OROZCO GOMEZ | E4: AMPIcilina (Sal Sodica) x 1000 mg Polvo para Inyeccion | F4: 400 | G4: MG | H4: 6 | I4: H | S4: J22X | T4: INFECCION AGUDA NO ESPECIFICADA DE LAS VIAS RESPIRATORIAS INFERIORES | U4: =+V4*(W4+X4+Y4+Z4) -> 3145.5 | V4: 6.99 | W4: =IFERROR(VLOOKUP(VLOOKUP(E4,'Dosis Mx'!$R$1:$X$19,1,FALSE),'Dosis Mx'!$R$1:$X$19,6,FALSE),0) -> 0 | X4: =IFERROR(VLOOKUP(VLOOKUP(E4,'Dosis Mx'!$R$20:$X$36,1,FALSE),'Dosis Mx'!$R$20:$X$36,6,FALSE),0) -> 0 | Y4: =IFERROR(VLOOKUP(VLOOKUP(E4,'Dosis Mx'!$R$37:$X$54,1,FALSE),'Dosis Mx'!$R$37:$X$54,6,FALSE),0) -> 200 | Z4: =IFERROR(VLOOKUP(VLOOKUP(E4,'Dosis Mx'!$R$55:$X$78,1,FALSE),'Dosis Mx'!$R$55:$X$78,6,FALSE),0) -> 250 | AA4: =+F4*(24/H4) -> 1600 | AB4: 5
A5: 2 | B5: 602-2 | C5: 1025776579 | D5: JULIETA GONZALEZ CADAVID | E5: AMPIcilina 500 mg Polvo para Inyeccion | F5: 500 | G5: MG | H5: 6 | I5: H | S5: J189 | T5: NEUMONIA, NO ESPECIFICADA | U5: =+V5*(W5+X5+Y5+Z5) -> 3226.5 | V5: 7.17 | W5: =IFERROR(VLOOKUP(VLOOKUP(E5,'Dosis Mx'!$R$1:$X$19,1,FALSE),'Dosis Mx'!$R$1:$X$19,6,FALSE),0) -> 0 | X5: =IFERROR(VLOOKUP(VLOOKUP(E5,'Dosis Mx'!$R$20:$X$36,1,FALSE),'Dosis Mx'!$R$20:$X$36,6,FALSE),0) -> 0 | Y5: =IFERROR(VLOOKUP(VLOOKUP(E5,'Dosis Mx'!$R$37:$X$54,1,FALSE),'Dosis Mx'!$R$37:$X$54,6,FALSE),0) -> 200 | Z5: =IFERROR(VLOOKUP(VLOOKUP(E5,'Dosis Mx'!$R$55:$X$78,1,FALSE),'Dosis Mx'!$R$55:$X$78,6,FALSE),0) -> 250 | AA5: =+F5*(24/H5) -> 2000 | AB5: 6
A6: 3 | B6: 602-3 | C6: 1021948405 | D6: ÁLAN SAMUEL VALLEJO GARCIA | E6: AMPIcilina (Sal Sodica) x 1000 mg Polvo para Inyeccion | F6: 750 | G6: MG | H6: 6 | I6: H | S6: J46X | T6: ESTADO ASMATICO | U6: =+V6*(W6+X6+Y6+Z6) -> 4140 | V6: 9.2 | W6: =IFERROR(VLOOKUP(VLOOKUP(E6,'Dosis Mx'!$R$1:$X$19,1,FALSE),'Dosis Mx'!$R$1:$X$19,6,FALSE),0) -> 0 | X6: =IFERROR(VLOOKUP(VLOOKUP(E6,'Dosis Mx'!$R$20:$X$36,1,FALSE),'Dosis Mx'!$R$20:$X$36,6,FALSE),0) -> 0 | Y6: =IFERROR(VLOOKUP(VLOOKUP(E6,'Dosis Mx'!$R$37:$X$54,1,FALSE),'Dosis Mx'!$R$37:$X$54,6,FALSE),0) -> 200 | Z6: =IFERROR(VLOOKUP(VLOOKUP(E6,'Dosis Mx'!$R$55:$X$78,1,FALSE),'Dosis Mx'!$R$55:$X$78,6,FALSE),0) -> 250 | AA6: =+F6*(24/H6) -> 3000 | AB6: 7
A7: 4 | B7: 602-5 | C7: 1032262943 | D7: SALONAE GUISAO MONTOYA | E7: AMPIcilina Sodica/SULBactam Sodico 1000/500mg Polvo para iny (Ped) | F7: 570 | G7: MG | H7: 6 | I7: H | S7: J159 | T7: NEUMONIA BACTERIANA, NO ESPECIFICADA | U7: =+V7*(W7+X7+Y7+Z7) -> 2080 | V7: 10.4 | W7: =IFERROR(VLOOKUP(VLOOKUP(E7,'Dosis Mx'!$R$1:$X$19,1,FALSE),'Dosis Mx'!$R$1:$X$19,6,FALSE),0) -> 0 | X7: =IFERROR(VLOOKUP(VLOOKUP(E7,'Dosis Mx'!$R$20:$X$36,1,FALSE),'Dosis Mx'!$R$20:$X$36,6,FALSE),0) -> 0 | Y7: =IFERROR(VLOOKUP(VLOOKUP(E7,'Dosis Mx'!$R$37:$X$54,1,FALSE),'Dosis Mx'!$R$37:$X$54,6,FALSE),0) -> 200 | Z7: =IFERROR(VLOOKUP(VLOOKUP(E7,'Dosis Mx'!$R$55:$X$78,1,FALSE),'Dosis Mx'!$R$55:$X$78,6,FALSE),0) -> 0 | AA7: =+F7*(24/H7) -> 2280 | AB7: UCI | AC7: 9
A8: 5 | B8: 603-1 | C8: 1025909844 | D8: ASHLEY VICTORIA ANGULO GARCIA | E8: AZITromicina200mg/5 ml (4%)Polvo para reconstituirx15ml | F8: 125 | G8: MG | H8: 24 | I8: H | S8: J159 | T8: NEUMONIA BACTERIANA, NO ESPECIFICADA | U8: =+V8*(W8+X8+Y8+Z8) -> 117 | V8: 15.6 | W8: =IFERROR(VLOOKUP(VLOOKUP(E8,'Dosis Mx'!$R$1:$X$19,1,FALSE),'Dosis Mx'!$R$1:$X$19,6,FALSE),0) -> 0 | X8: =IFERROR(VLOOKUP(VLOOKUP(E8,'Dosis Mx'!$R$20:$X$36,1,FALSE),'Dosis Mx'!$R$20:$X$36,6,FALSE),0) -> 0 | Y8: =IFERROR(VLOOKUP(VLOOKUP(E8,'Dosis Mx'!$R$37:$X$54,1,FALSE),'Dosis Mx'!$R$37:$X$54,6,FALSE),0) -> 7.5 | Z8: =IFERROR(VLOOKUP(VLOOKUP(E8,'Dosis Mx'!$R$55:$X$78,1,FALSE),'Dosis Mx'!$R$55:$X$78,6,FALSE),0) -> 0 | AA8: =+F8*(24/H8) -> 125 | AB8: URGENCIAS | AC8: 12
A9: 6 | B9: 603-1 | C9: 1025909844 | D9: ASHLEY VICTORIA ANGULO GARCIA | E9: AMPIcilina 500 mg Polvo para Inyeccion | F9: 625 | G9: MG | H9: 6 | I9: H | S9: J159 | T9: NEUMONIA BACTERIANA, NO ESPECIFICADA | U9: =+V9*(W9+X9+Y9+Z9) -> 7200 | V9: 16 | W9: =IFERROR(VLOOKUP(VLOOKUP(E9,'Dosis Mx'!$R$1:$X$19,1,FALSE),'Dosis Mx'!$R$1:$X$19,6,FALSE),0) -> 0 | X9: =IFERROR(VLOOKUP(VLOOKUP(E9,'Dosis Mx'!$R$20:$X$36,1,FALSE),'Dosis Mx'!$R$20:$X$36,6,FALSE),0) -> 0 | Y9: =IFERROR(VLOOKUP(VLOOKUP(E9,'Dosis Mx'!$R$37:$X$54,1,FALSE),'Dosis Mx'!$R$37:$X$54,6,FALSE),0) -> 200 | Z9: =IFERROR(VLOOKUP(VLOOKUP(E9,'Dosis Mx'!$R$55:$X$78,1,FALSE),'Dosis Mx'!$R$55:$X$78,6,FALSE),0) -> 250 | AA9: =+F9*(24/H9) -> 2500
A10: 7 | B10: 604-1 | C10: 1031946972 | D10: MAXIMILIANO AGUDELO SERNA | E10: Ceftriaxona (Sal Sodica) 1000 mg Polvo para Inyeccion | F10: 140 | G10: MG | H10: 24 | I10: H | S10: J159 | T10: NEUMONIA BACTERIANA, NO ESPECIFICADA | U10: =+V10*(W10+X10+Y10+Z10) -> 4655 | V10: 9.8 | W10: =IFERROR(VLOOKUP(VLOOKUP(E10,'Dosis Mx'!$R$1:$X$19,1,FALSE),'Dosis Mx'!$R$1:$X$19,6,FALSE),0) -> 300 | X10: =IFERROR(VLOOKUP(VLOOKUP(E10,'Dosis Mx'!$R$20:$X$36,1,FALSE),'Dosis Mx'!$R$20:$X$36,6,FALSE),0) -> 0 | Y10: =IFERROR(VLOOKUP(VLOOKUP(E10,'Dosis Mx'!$R$37:$X$54,1,FALSE),'Dosis Mx'!$R$37:$X$54,6,FALSE),0) -> 75 | Z10: =IFERROR(VLOOKUP(VLOOKUP(E10,'Dosis Mx'!$R$55:$X$78,1,FALSE),'Dosis Mx'!$R$55:$X$78,6,FALSE),0) -> 100 | AA10: =+F10*(24/H10) -> 140
A11: 8 | B11: 604-2 | C11: 1025907262 | D11: LIAM MATIAS ESPINAL RESTREPO | E11: AMPIcilina (Sal Sodica) x 1000 mg Polvo para Inyeccion | F11: 800 | G11: MG | H11: 6 | I11: H | S11: J459 | T11: ASMA, NO ESPECIFICADO | U11: =+V11*(W11+X11+Y11+Z11) -> 20475 | V11: 45.5 | W11: =IFERROR(VLOOKUP(VLOOKUP(E11,'Dosis Mx'!$R$1:$X$19,1,FALSE),'Dosis Mx'!$R$1:$X$19,6,FALSE),0) -> 0 | X11: =IFERROR(VLOOKUP(VLOOKUP(E11,'Dosis Mx'!$R$20:$X$36,1,FALSE),'Dosis Mx'!$R$20:$X$36,6,FALSE),0) -> 0 | Y11: =IFERROR(VLOOKUP(VLOOKUP(E11,'Dosis Mx'!$R$37:$X$54,1,FALSE),'Dosis Mx'!$R$37:$X$54,6,FALSE),0) -> 200 | Z11: =IFERROR(VLOOKUP(VLOOKUP(E11,'Dosis Mx'!$R$55:$X$78,1,FALSE),'Dosis Mx'!$R$55:$X$78,6,FALSE),0) -> 250 | AA11: =+F11*(24/H11) -> 3200
A12: 9 | B12: 604-3 | C12: 1032195341 | D12: ROBER ANDRES VARGAS TONCEL | E12: AMPIcilina 500 mg Polvo para Inyeccion | F12: 500 | G12: MG | H12: 6 | I12: H | S12: J459 | T12: ASMA, NO ESPECIFICADO | U12: =+V12*(W12+X12+Y12+Z12) -> 6300 | V12: 14 | W12: =IFERROR(VLOOKUP(VLOOKUP(E12,'Dosis Mx'!$R$1:$X$19,1,FALSE),'Dosis Mx'!$R$1:$X$19,6,FALSE),0) -> 0 | X12: =IFERROR(VLOOKUP(VLOOKUP(E12,'Dosis Mx'!$R$20:$X$36,1,FALSE),'Dosis Mx'!$R$20:$X$36,6,FALSE),0) -> 0 | Y12: =IFERROR(VLOOKUP(VLOOKUP(E12,'Dosis Mx'!$R$37:$X$54,1,FALSE),'Dosis Mx'!$R$37:$X$54,6,FALSE),0) -> 200 | Z12: =IFERROR(VLOOKUP(VLOOKUP(E12,'Dosis Mx'!$R$55:$X$78,1,FALSE),'Dosis Mx'!$R$55:$X$78,6,FALSE),0) -> 250 | AA12: =+F12*(24/H12) -> 2000
A13: 10 | B13: 604-5 | C13: 1025776778 | D13: AMAIA VALENCIA QUINTERO | E13: AMPIcilina Sodica/SULBactam Sodico 1000/500mg Polvo para iny (Ped) | F13: 400 | G13: MG | H13: 6 | I13: H | S13: J159 | T13: NEUMONIA BACTERIANA, NO ESPECIFICADA | U13: =+V13*(W13+X13+Y13+Z13) -> 8000 | V13: 40 | W13: =IFERROR(VLOOKUP(VLOOKUP(E13,'Dosis Mx'!$R$1:$X$19,1,FALSE),'Dosis Mx'!$R$1:$X$19,6,FALSE),0) -> 0 | X13: =IFERROR(VLOOKUP(VLOOKUP(E13,'Dosis Mx'!$R$20:$X$36,1,FALSE),'Dosis Mx'!$R$20:$X$36,6,FALSE),0) -> 0 | Y13: =IFERROR(VLOOKUP(VLOOKUP(E13,'Dosis Mx'!$R$37:$X$54,1,FALSE),'Dosis Mx'!$R$37:$X$54,6,FALSE),0) -> 200 | Z13: =IFERROR(VLOOKUP(VLOOKUP(E13,'Dosis Mx'!$R$55:$X$78,1,FALSE),'Dosis Mx'!$R$55:$X$78,6,FALSE),0) -> 0 | AA13: =+F13*(24/H13) -> 1600
A14: 11 | B14: 604-6 | C14: 1018276805 | D14: SANTIAGO GALLEGO CASTRILLON | E14: AMPIcilina Sodica/SULBactam Sodico 1000/500mg Polvo para iny (Ped) | F14: 550 | G14: MG | H14: 6 | I14: H | S14: J22X | T14: INFECCION AGUDA NO ESPECIFICADA DE LAS VIAS RESPIRATORIAS INFERIORES | U14: =+V14*(W14+X14+Y14+Z14) -> 2200 | V14: 11 | W14: =IFERROR(VLOOKUP(VLOOKUP(E14,'Dosis Mx'!$R$1:$X$19,1,FALSE),'Dosis Mx'!$R$1:$X$19,6,FALSE),0) -> 0 | X14: =IFERROR(VLOOKUP(VLOOKUP(E14,'Dosis Mx'!$R$20:$X$36,1,FALSE),'Dosis Mx'!$R$20:$X$36,6,FALSE),0) -> 0 | Y14: =IFERROR(VLOOKUP(VLOOKUP(E14,'Dosis Mx'!$R$37:$X$54,1,FALSE),'Dosis Mx'!$R$37:$X$54,6,FALSE),0) -> 200 | Z14: =IFERROR(VLOOKUP(VLOOKUP(E14,'Dosis Mx'!$R$55:$X$78,1,FALSE),'Dosis Mx'!$R$55:$X$78,6,FALSE),0) -> 0 | AA14: =+F14*(24/H14) -> 2200
A15: 12 | B15: 605-4 | C15: 1018273143 | D15: NICOL DAHIANA OSORIO ORTIZ | E15: AMPIcilina (Sal Sodica) x 1000 mg Polvo para Inyeccion | F15: 850 | G15: MG | H15: 6 | I15: H | S15: J22X | T15: INFECCION AGUDA NO ESPECIFICADA DE LAS VIAS RESPIRATORIAS INFERIORES | U15: =+V15*(W15+X15+Y15+Z15) -> 3690 | V15: 8.2 | W15: =IFERROR(VLOOKUP(VLOOKUP(E15,'Dosis Mx'!$R$1:$X$19,1,FALSE),'Dosis Mx'!$R$1:$X$19,6,FALSE),0) -> 0 | X15: =IFERROR(VLOOKUP(VLOOKUP(E15,'Dosis Mx'!$R$20:$X$36,1,FALSE),'Dosis Mx'!$R$20:$X$36,6,FALSE),0) -> 0 | Y15: =IFERROR(VLOOKUP(VLOOKUP(E15,'Dosis Mx'!$R$37:$X$54,1,FALSE),'Dosis Mx'!$R$37:$X$54,6,FALSE),0) -> 200 | Z15: =IFERROR(VLOOKUP(VLOOKUP(E15,'Dosis Mx'!$R$55:$X$78,1,FALSE),'Dosis Mx'!$R$55:$X$78,6,FALSE),0) -> 250 | AA15: =+F15*(24/H15) -> 3400
A16: 13 | B16: 605-6 | C16: 1031949871 | D16: CIELO MARIA TEQUIA BUCAMA | E16: AMPIcilina Sodica/SULBactam Sodico 1000/500mg Polvo para iny (Ped) | F16: 390 | G16: MG | H16: 6 | I16: H | S16: E440 | T16: DESNUTRICION PROTEICOCALORICA MODERADA | U16: =+V16*(W16+X16+Y16+Z16) -> 1960 | V16: 9.8 | W16: =IFERROR(VLOOKUP(VLOOKUP(E16,'Dosis Mx'!$R$1:$X$19,1,FALSE),'Dosis Mx'!$R$1:$X$19,6,FALSE),0) -> 0 | X16: =IFERROR(VLOOKUP(VLOOKUP(E16,'Dosis Mx'!$R$20:$X$36,1,FALSE),'Dosis Mx'!$R$20:$X$36,6,FALSE),0) -> 0 | Y16: =IFERROR(VLOOKUP(VLOOKUP(E16,'Dosis Mx'!$R$37:$X$54,1,FALSE),'Dosis Mx'!$R$37:$X$54,6,FALSE),0) -> 200 | Z16: =IFERROR(VLOOKUP(VLOOKUP(E16,'Dosis Mx'!$R$55:$X$78,1,FALSE),'Dosis Mx'!$R$55:$X$78,6,FALSE),0) -> 0 | AA16: =+F16*(24/H16) -> 1560
A17: 14 | B17: 606-5 | C17: 1025909918 | D17: MARIANGEL CASTAÑO POSADA | E17: AMPIcilina (Sal Sodica) x 1000 mg Polvo para Inyeccion | F17: 600 | G17: MG | H17: 6 | I17: H | S17: J189 | T17: NEUMONIA, NO ESPECIFICADA | U17: =+V17*(W17+X17+Y17+Z17) -> 7245 | V17: 16.1 | W17: =IFERROR(VLOOKUP(VLOOKUP(E17,'Dosis Mx'!$R$1:$X$19,1,FALSE),'Dosis Mx'!$R$1:$X$19,6,FALSE),0) -> 0 | X17: =IFERROR(VLOOKUP(VLOOKUP(E17,'Dosis Mx'!$R$20:$X$36,1,FALSE),'Dosis Mx'!$R$20:$X$36,6,FALSE),0) -> 0 | Y17: =IFERROR(VLOOKUP(VLOOKUP(E17,'Dosis Mx'!$R$37:$X$54,1,FALSE),'Dosis Mx'!$R$37:$X$54,6,FALSE),0) -> 200 | Z17: =IFERROR(VLOOKUP(VLOOKUP(E17,'Dosis Mx'!$R$55:$X$78,1,FALSE),'Dosis Mx'!$R$55:$X$78,6,FALSE),0) -> 250 | AA17: =+F17*(24/H17) -> 2400
A18: 15 | B18: ObsAisl 1 | C18: 23099110655662 | D18: HIJO DE EMILSE PAOLA OSORIO | E18: Oxacilina (Sal Sodica) 1000 mg Polvo para Inyeccion | F18: 100 | G18: MG | H18: 8 | I18: H | J18: I | L18: X | S18: L032 | T18: CELULITIS DE LA CARA | U18: =+V18*(W18+X18+Y18+Z18) -> 6400 | V18: 16 | W18: =IFERROR(VLOOKUP(VLOOKUP(E18,'Dosis Mx'!$R$1:$X$19,1,FALSE),'Dosis Mx'!$R$1:$X$19,6,FALSE),0) -> 0 | X18: =IFERROR(VLOOKUP(VLOOKUP(E18,'Dosis Mx'!$R$20:$X$36,1,FALSE),'Dosis Mx'!$R$20:$X$36,6,FALSE),0) -> 200 | Y18: =IFERROR(VLOOKUP(VLOOKUP(E18,'Dosis Mx'!$R$37:$X$54,1,FALSE),'Dosis Mx'!$R$37:$X$54,6,FALSE),0) -> 0 | Z18: =IFERROR(VLOOKUP(VLOOKUP(E18,'Dosis Mx'!$R$55:$X$78,1,FALSE),'Dosis Mx'!$R$55:$X$78,6,FALSE),0) -> 200 | AA18: =+F18*(24/H18) -> 300
A19: 16 | B19: UCE 03 | C19: 1041633640 | D19: ANGELA MARIA POSADA GONZALEZ | E19: AZITromicina200mg/5 ml (4%)Polvo para reconstituirx15ml | F19: 500 | G19: MG | H19: 24 | I19: H | J19: I | L19: X | S19: I272 | T19: OTRAS HIPERTENSIONES PULMONARES SECUNDARIAS | U19: =+V19*(W19+X19+Y19+Z19) -> 27.75 | V19: 3.7 | W19: =IFERROR(VLOOKUP(VLOOKUP(E19,'Dosis Mx'!$R$1:$X$19,1,FALSE),'Dosis Mx'!$R$1:$X$19,6,FALSE),0) -> 0 | X19: =IFERROR(VLOOKUP(VLOOKUP(E19,'Dosis Mx'!$R$20:$X$36,1,FALSE),'Dosis Mx'!$R$20:$X$36,6,FALSE),0) -> 0 | Y19: =IFERROR(VLOOKUP(VLOOKUP(E19,'Dosis Mx'!$R$37:$X$54,1,FALSE),'Dosis Mx'!$R$37:$X$54,6,FALSE),0) -> 7.5 | Z19: =IFERROR(VLOOKUP(VLOOKUP(E19,'Dosis Mx'!$R$55:$X$78,1,FALSE),'Dosis Mx'!$R$55:$X$78,6,FALSE),0) -> 0 | AA19: =+F19*(24/H19) -> 500
A20: 17 | B20: UCE 03 | C20: 1041633640 | D20: ANGELA MARIA POSADA GONZALEZ | E20: AMPIcilina Sodica/SULBactam Sodico 1000/500mg Polvo para iny (Ped) | F20: 2000 | G20: MG | H20: 6 | I20: H | J20: I | L20: X | S20: I272 | T20: OTRAS HIPERTENSIONES PULMONARES SECUNDARIAS | U20: =+V20*(W20+X20+Y20+Z20) -> 940 | V20: 4.7 | W20: =IFERROR(VLOOKUP(VLOOKUP(E20,'Dosis Mx'!$R$1:$X$19,1,FALSE),'Dosis Mx'!$R$1:$X$19,6,FALSE),0) -> 0 | X20: =IFERROR(VLOOKUP(VLOOKUP(E20,'Dosis Mx'!$R$20:$X$36,1,FALSE),'Dosis Mx'!$R$20:$X$36,6,FALSE),0) -> 0 | Y20: =IFERROR(VLOOKUP(VLOOKUP(E20,'Dosis Mx'!$R$37:$X$54,1,FALSE),'Dosis Mx'!$R$37:$X$54,6,FALSE),0) -> 200 | Z20: =IFERROR(VLOOKUP(VLOOKUP(E20,'Dosis Mx'!$R$55:$X$78,1,FALSE),'Dosis Mx'!$R$55:$X$78,6,FALSE),0) -> 0 | AA20: =+F20*(24/H20) -> 8000
A21: 18 | B21: UCE 07 | C21: 1026004290 | D21: MARIA JOSE CASTAÑO MARIN | E21: AMPIcilina (Sal Sodica) x 1000 mg Polvo para Inyeccion | F21: 245 | G21: MG | H21: 6 | I21: H | R21: ALTA | S21: J219 | T21: BRONQUIOLITIS AGUDA, NO ESPECIFICADA | U21: =+V21*(W21+X21+Y21+Z21) -> 3195 | V21: 7.1 | W21: =IFERROR(VLOOKUP(VLOOKUP(E21,'Dosis Mx'!$R$1:$X$19,1,FALSE),'Dosis Mx'!$R$1:$X$19,6,FALSE),0) -> 0 | X21: =IFERROR(VLOOKUP(VLOOKUP(E21,'Dosis Mx'!$R$20:$X$36,1,FALSE),'Dosis Mx'!$R$20:$X$36,6,FALSE),0) -> 0 | Y21: =IFERROR(VLOOKUP(VLOOKUP(E21,'Dosis Mx'!$R$37:$X$54,1,FALSE),'Dosis Mx'!$R$37:$X$54,6,FALSE),0) -> 200 | Z21: =IFERROR(VLOOKUP(VLOOKUP(E21,'Dosis Mx'!$R$55:$X$78,1,FALSE),'Dosis Mx'!$R$55:$X$78,6,FALSE),0) -> 250 | AA21: =+F21*(24/H21) -> 980
A22: 19 | B22: UCE 08AISL | C22: 1023639296 | D22: MICHEL GRAJALES | E22: AMPIcilina Sodica/SULBactam Sodico 1000/500mg Polvo para iny (Ped) | F22: 1250 | G22: MG | H22: 6 | I22: H | J22: I | S22: J690 | T22: NEUMONITIS DEBIDA A ASPIRACION DE ALIMENTO O VOMITO | U22: =+V22*(W22+X22+Y22+Z22) -> 1700 | V22: 8.5 | W22: =IFERROR(VLOOKUP(VLOOKUP(E22,'Dosis Mx'!$R$1:$X$19,1,FALSE),'Dosis Mx'!$R$1:$X$19,6,FALSE),0) -> 0 | X22: =IFERROR(VLOOKUP(VLOOKUP(E22,'Dosis Mx'!$R$20:$X$36,1,FALSE),'Dosis Mx'!$R$20:$X$36,6,FALSE),0) -> 0 | Y22: =IFERROR(VLOOKUP(VLOOKUP(E22,'Dosis Mx'!$R$37:$X$54,1,FALSE),'Dosis Mx'!$R$37:$X$54,6,FALSE),0) -> 200 | Z22: =IFERROR(VLOOKUP(VLOOKUP(E22,'Dosis Mx'!$R$55:$X$78,1,FALSE),'Dosis Mx'!$R$55:$X$78,6,FALSE),0) -> 0 | AA22: =+F22*(24/H22) -> 5000
A23: 20 | B23: UCI 01 | C23: 1247049299 | D23: ANALIZ VICTORIA GONZALEZ FUENTES | E23: AMPIcilina Sodica/SULBactam Sodico 1000/500mg Polvo para iny (Ped) | F23: 280 | G23: MG | H23: 6 | I23: H | J23: NI | L23: X | M23: X | S23: J219 | T23: BRONQUIOLITIS AGUDA, NO ESPECIFICADA | U23: =+V23*(W23+X23+Y23+Z23) -> 1800 | V23: 9 | W23: =IFERROR(VLOOKUP(VLOOKUP(E23,'Dosis Mx'!$R$1:$X$19,1,FALSE),'Dosis Mx'!$R$1:$X$19,6,FALSE),0) -> 0 | X23: =IFERROR(VLOOKUP(VLOOKUP(E23,'Dosis Mx'!$R$20:$X$36,1,FALSE),'Dosis Mx'!$R$20:$X$36,6,FALSE),0) -> 0 | Y23: =IFERROR(VLOOKUP(VLOOKUP(E23,'Dosis Mx'!$R$37:$X$54,1,FALSE),'Dosis Mx'!$R$37:$X$54,6,FALSE),0) -> 200 | Z23: =IFERROR(VLOOKUP(VLOOKUP(E23,'Dosis Mx'!$R$55:$X$78,1,FALSE),'Dosis Mx'!$R$55:$X$78,6,FALSE),0) -> 0 | AA23: =+F23*(24/H23) -> 1120
A24: 21 | B24: UCI 01 | C24: 1247049299 | D24: ANALIZ VICTORIA GONZALEZ FUENTES | E24: AZITromicina200mg/5 ml (4%)Polvo para reconstituirx15ml | F24: 45 | G24: MG | H24: 24 | I24: H | J24: NI | L24: X | M24: X | S24: J219 | T24: BRONQUIOLITIS AGUDA, NO ESPECIFICADA | U24: =+V24*(W24+X24+Y24+Z24) -> 49.125 | V24: 6.55 | W24: =IFERROR(VLOOKUP(VLOOKUP(E24,'Dosis Mx'!$R$1:$X$19,1,FALSE),'Dosis Mx'!$R$1:$X$19,6,FALSE),0) -> 0 | X24: =IFERROR(VLOOKUP(VLOOKUP(E24,'Dosis Mx'!$R$20:$X$36,1,FALSE),'Dosis Mx'!$R$20:$X$36,6,FALSE),0) -> 0 | Y24: =IFERROR(VLOOKUP(VLOOKUP(E24,'Dosis Mx'!$R$37:$X$54,1,FALSE),'Dosis Mx'!$R$37:$X$54,6,FALSE),0) -> 7.5 | Z24: =IFERROR(VLOOKUP(VLOOKUP(E24,'Dosis Mx'!$R$55:$X$78,1,FALSE),'Dosis Mx'!$R$55:$X$78,6,FALSE),0) -> 0 | AA24: =+F24*(24/H24) -> 45
A25: 22 | B25: UCI 02 | C25: 1011420925 | D25: ALAN CAMILO MUÑOZ ZAPATA | E25: AMPIcilina Sodica/SULBactam Sodico 1000/500mg Polvo para iny (Ped) | F25: 450 | G25: MG | H25: 6 | I25: H | J25: I | R25: 5 DÍAS | S25: J219 | T25: BRONQUIOLITIS AGUDA, NO ESPECIFICADA | U25: =+V25*(W25+X25+Y25+Z25) -> 540 | V25: 2.7 | W25: =IFERROR(VLOOKUP(VLOOKUP(E25,'Dosis Mx'!$R$1:$X$19,1,FALSE),'Dosis Mx'!$R$1:$X$19,6,FALSE),0) -> 0 | X25: =IFERROR(VLOOKUP(VLOOKUP(E25,'Dosis Mx'!$R$20:$X$36,1,FALSE),'Dosis Mx'!$R$20:$X$36,6,FALSE),0) -> 0 | Y25: =IFERROR(VLOOKUP(VLOOKUP(E25,'Dosis Mx'!$R$37:$X$54,1,FALSE),'Dosis Mx'!$R$37:$X$54,6,FALSE),0) -> 200 | Z25: =IFERROR(VLOOKUP(VLOOKUP(E25,'Dosis Mx'!$R$55:$X$78,1,FALSE),'Dosis Mx'!$R$55:$X$78,6,FALSE),0) -> 0 | AA25: =+F25*(24/H25) -> 1800
A26: 23 | B26: UCI 04 | C26: 1031944635 | D26: IKER YULIAN DAVID MARTINEZ | E26: Cefepime 1000 mg Polvo para inyeccion | F26: 200 | G26: MG | H26: 8 | I26: H | J26: I | L26: X | N26: X | R26: 7 DÍAS | S26: I272 | T26: OTRAS HIPERTENSIONES PULMONARES SECUNDARIAS | U26: =+V26*(W26+X26+Y26+Z26) -> 0 | W26: =IFERROR(VLOOKUP(VLOOKUP(E26,'Dosis Mx'!$R$1:$X$19,1,FALSE),'Dosis Mx'!$R$1:$X$19,6,FALSE),0) -> 90 | X26: =IFERROR(VLOOKUP(VLOOKUP(E26,'Dosis Mx'!$R$20:$X$36,1,FALSE),'Dosis Mx'!$R$20:$X$36,6,FALSE),0) -> 0 | Y26: =IFERROR(VLOOKUP(VLOOKUP(E26,'Dosis Mx'!$R$37:$X$54,1,FALSE),'Dosis Mx'!$R$37:$X$54,6,FALSE),0) -> 0 | Z26: =IFERROR(VLOOKUP(VLOOKUP(E26,'Dosis Mx'!$R$55:$X$78,1,FALSE),'Dosis Mx'!$R$55:$X$78,6,FALSE),0) -> 150 | AA26: =+F26*(24/H26) -> 600
A27: 24 | B27: UCI 05 | C27: 1023544374 | D27: SANTIAGO GONZALEZ OSORIO | E27: Vancomicina (Clorhidrato) 500 mg Polvo para Inyeccion | F27: 190 | G27: MG | H27: 6 | I27: H | J27: I | L27: X | M27: X | S27: Q213 | T27: TETRALOGIA DE FALLOT | U27: =+V27*(W27+X27+Y27+Z27) -> 0 | W27: =IFERROR(VLOOKUP(VLOOKUP(E27,'Dosis Mx'!$R$1:$X$19,1,FALSE),'Dosis Mx'!$R$1:$X$19,6,FALSE),0) -> 0 | X27: =IFERROR(VLOOKUP(VLOOKUP(E27,'Dosis Mx'!$R$20:$X$36,1,FALSE),'Dosis Mx'!$R$20:$X$36,6,FALSE),0) -> 60 | Y27: =IFERROR(VLOOKUP(VLOOKUP(E27,'Dosis Mx'!$R$37:$X$54,1,FALSE),'Dosis Mx'!$R$37:$X$54,6,FALSE),0) -> 60 | Z27: =IFERROR(VLOOKUP(VLOOKUP(E27,'Dosis Mx'!$R$55:$X$78,1,FALSE),'Dosis Mx'!$R$55:$X$78,6,FALSE),0) -> 60 | AA27: =+F27*(24/H27) -> 760
A28: 25 | B28: UCI 05 | C28: 1023544374 | D28: SANTIAGO GONZALEZ OSORIO | E28: Ceftriaxona (Sal Sodica) 1000 mg Polvo para Inyeccion | F28: 640 | G28: MG | H28: 12 | I28: H | J28: I | L28: X | Q28: X | R28: C/24 HORAS 75MG | S28: Q213 | T28: TETRALOGIA DE FALLOT | U28: =+V28*(W28+X28+Y28+Z28) -> 0 | W28: =IFERROR(VLOOKUP(VLOOKUP(E28,'Dosis Mx'!$R$1:$X$19,1,FALSE),'Dosis Mx'!$R$1:$X$19,6,FALSE),0) -> 300 | X28: =IFERROR(VLOOKUP(VLOOKUP(E28,'Dosis Mx'!$R$20:$X$36,1,FALSE),'Dosis Mx'!$R$20:$X$36,6,FALSE),0) -> 0 | Y28: =IFERROR(VLOOKUP(VLOOKUP(E28,'Dosis Mx'!$R$37:$X$54,1,FALSE),'Dosis Mx'!$R$37:$X$54,6,FALSE),0) -> 75 | Z28: =IFERROR(VLOOKUP(VLOOKUP(E28,'Dosis Mx'!$R$55:$X$78,1,FALSE),'Dosis Mx'!$R$55:$X$78,6,FALSE),0) -> 100 | AA28: =+F28*(24/H28) -> 1280
A29: 26 | B29: UCI 06 | C29: 1078474669 | D29: CATALINA GONZALEZ TUNAY | E29: Vancomicina (Clorhidrato) 500 mg Polvo para Inyeccion | F29: 90 | G29: MG | H29: 6 | I29: H | J29: I | L29: X | M29: X | R29: ANALISIS TB | S29: J158 | T29: OTRAS NEUMONIAS BACTERIANAS | U29: =+V29*(W29+X29+Y29+Z29) -> 0 | W29: =IFERROR(VLOOKUP(VLOOKUP(E29,'Dosis Mx'!$R$1:$X$19,1,FALSE),'Dosis Mx'!$R$1:$X$19,6,FALSE),0) -> 0 | X29: =IFERROR(VLOOKUP(VLOOKUP(E29,'Dosis Mx'!$R$20:$X$36,1,FALSE),'Dosis Mx'!$R$20:$X$36,6,FALSE),0) -> 60 | Y29: =IFERROR(VLOOKUP(VLOOKUP(E29,'Dosis Mx'!$R$37:$X$54,1,FALSE),'Dosis Mx'!$R$37:$X$54,6,FALSE),0) -> 60 | Z29: =IFERROR(VLOOKUP(VLOOKUP(E29,'Dosis Mx'!$R$55:$X$78,1,FALSE),'Dosis Mx'!$R$55:$X$78,6,FALSE),0) -> 60 | AA29: =+F29*(24/H29) -> 360
A30: 27 | B30: UCI 06 | C30: 1078474669 | D30: CATALINA GONZALEZ TUNAY | E30: Ceftriaxona (Sal Sodica) 1000 mg Polvo para Inyeccion | F30: 300 | G30: MG | H30: 12 | I30: H | J30: I | Q30: X | R30: C/24 HORAS 75MG | S30: J158 | T30: OTRAS NEUMONIAS BACTERIANAS | U30: =+V30*(W30+X30+Y30+Z30) -> 0 | W30: =IFERROR(VLOOKUP(VLOOKUP(E30,'Dosis Mx'!$R$1:$X$19,1,FALSE),'Dosis Mx'!$R$1:$X$19,6,FALSE),0) -> 300 | X30: =IFERROR(VLOOKUP(VLOOKUP(E30,'Dosis Mx'!$R$20:$X$36,1,FALSE),'Dosis Mx'!$R$20:$X$36,6,FALSE),0) -> 0 | Y30: =IFERROR(VLOOKUP(VLOOKUP(E30,'Dosis Mx'!$R$37:$X$54,1,FALSE),'Dosis Mx'!$R$37:$X$54,6,FALSE),0) -> 75 | Z30: =IFERROR(VLOOKUP(VLOOKUP(E30,'Dosis Mx'!$R$55:$X$78,1,FALSE),'Dosis Mx'!$R$55:$X$78,6,FALSE),0) -> 100 | AA30: =+F30*(24/H30) -> 600
A31: No | B31: Servicio | E31: Nombre | F31: Dosis | G31: Medidadosis | H31: Frecuencia | I31: Unidadfrecuencia | J31: Tto Empirico | K31: Tto Dirigido | L31: cultivo | M31: Suspender | N31: Cambiar | R31: Observacionesorden | S31: Codigo Diagnostico | T31: Diagnostico | U31: Dosis | V31: Peso(kg) | W31: ITU | X31: ITB | Y31: NEUMONIA | Z31: MENINGITIS | AA31: Dosis recetada
N32: Escalar | O32: Desescalar | P32: RXN adversa | Q32: Por dosis
U33: =+V33*(W33+X33+Y33+Z33) -> 0 | W33: =IFERROR(VLOOKUP(VLOOKUP(E33,'Dosis Mx'!$R$1:$X$19,1,FALSE),'Dosis Mx'!$R$1:$X$19,6,FALSE),0) -> 0 | X33: =IFERROR(VLOOKUP(VLOOKUP(E33,'Dosis Mx'!$R$20:$X$36,1,FALSE),'Dosis Mx'!$R$20:$X$36,6,FALSE),0) -> 0 | Y33: =IFERROR(VLOOKUP(VLOOKUP(E33,'Dosis Mx'!$R$37:$X$54,1,FALSE),'Dosis Mx'!$R$37:$X$54,6,FALSE),0) -> 0 | Z33: =IFERROR(VLOOKUP(VLOOKUP(E33,'Dosis Mx'!$R$55:$X$78,1,FALSE),'Dosis Mx'!$R$55:$X$78,6,FALSE),0) -> 0 | AA33: =+F33*(24/H33) -> #DIV/0!
U34: =+V34*(W34+X34+Y34+Z34) -> 0 | W34: =IFERROR(VLOOKUP(VLOOKUP(E34,'Dosis Mx'!$R$1:$X$19,1,FALSE),'Dosis Mx'!$R$1:$X$19,6,FALSE),0) -> 0 | X34: =IFERROR(VLOOKUP(VLOOKUP(E34,'Dosis Mx'!$R$20:$X$36,1,FALSE),'Dosis Mx'!$R$20:$X$36,6,FALSE),0) -> 0 | Y34: =IFERROR(VLOOKUP(VLOOKUP(E34,'Dosis Mx'!$R$37:$X$54,1,FALSE),'Dosis Mx'!$R$37:$X$54,6,FALSE),0) -> 0 | Z34: =IFERROR(VLOOKUP(VLOOKUP(E34,'Dosis Mx'!$R$55:$X$78,1,FALSE),'Dosis Mx'!$R$55:$X$78,6,FALSE),0) -> 0 | AA34: =+F34*(24/H34) -> #DIV/0!
U35: =+V35*(W35+X35+Y35+Z35) -> 0 | W35: =IFERROR(VLOOKUP(VLOOKUP(E35,'Dosis Mx'!$R$1:$X$19,1,FALSE),'Dosis Mx'!$R$1:$X$19,6,FALSE),0) -> 0 | X35: =IFERROR(VLOOKUP(VLOOKUP(E35,'Dosis Mx'!$R$20:$X$36,1,FALSE),'Dosis Mx'!$R$20:$X$36,6,FALSE),0) -> 0 | Y35: =IFERROR(VLOOKUP(VLOOKUP(E35,'Dosis Mx'!$R$37:$X$54,1,FALSE),'Dosis Mx'!$R$37:$X$54,6,FALSE),0) -> 0 | Z35: =IFERROR(VLOOKUP(VLOOKUP(E35,'Dosis Mx'!$R$55:$X$78,1,FALSE),'Dosis Mx'!$R$55:$X$78,6,FALSE),0) -> 0 | AA35: =+F35*(24/H35) -> #DIV/0!
U36: =+V36*(W36+X36+Y36+Z36) -> 0 | W36: =IFERROR(VLOOKUP(VLOOKUP(E36,'Dosis Mx'!$R$1:$X$19,1,FALSE),'Dosis Mx'!$R$1:$X$19,6,FALSE),0) -> 0 | X36: =IFERROR(VLOOKUP(VLOOKUP(E36,'Dosis Mx'!$R$20:$X$36,1,FALSE),'Dosis Mx'!$R$20:$X$36,6,FALSE),0) -> 0 | Y36: =IFERROR(VLOOKUP(VLOOKUP(E36,'Dosis Mx'!$R$37:$X$54,1,FALSE),'Dosis Mx'!$R$37:$X$54,6,FALSE),0) -> 0 | Z36: =IFERROR(VLOOKUP(VLOOKUP(E36,'Dosis Mx'!$R$55:$X$78,1,FALSE),'Dosis Mx'!$R$55:$X$78,6,FALSE),0) -> 0 | AA36: =+F36*(24/H36) -> #DIV/0!
U37: =+V37*(W37+X37+Y37+Z37) -> 0 | W37: =IFERROR(VLOOKUP(VLOOKUP(E37,'Dosis Mx'!$R$1:$X$19,1,FALSE),'Dosis Mx'!$R$1:$X$19,6,FALSE),0) -> 0 | X37: =IFERROR(VLOOKUP(VLOOKUP(E37,'Dosis Mx'!$R$20:$X$36,1,FALSE),'Dosis Mx'!$R$20:$X$36,6,FALSE),0) -> 0 | Y37: =IFERROR(VLOOKUP(VLOOKUP(E37,'Dosis Mx'!$R$37:$X$54,1,FALSE),'Dosis Mx'!$R$37:$X$54,6,FALSE),0) -> 0 | Z37: =IFERROR(VLOOKUP(VLOOKUP(E37,'Dosis Mx'!$R$55:$X$78,1,FALSE),'Dosis Mx'!$R$55:$X$78,6,FALSE),0) -> 0 | AA37: =+F37*(24/H37) -> #DIV/0!
U38: =+V38*(W38+X38+Y38+Z38) -> 0 | W38: =IFERROR(VLOOKUP(VLOOKUP(E38,'Dosis Mx'!$R$1:$X$19,1,FALSE),'Dosis Mx'!$R$1:$X$19,6,FALSE),0) -> 0 | X38: =IFERROR(VLOOKUP(VLOOKUP(E38,'Dosis Mx'!$R$20:$X$36,1,FALSE),'Dosis Mx'!$R$20:$X$36,6,FALSE),0) -> 0 | Y38: =IFERROR(VLOOKUP(VLOOKUP(E38,'Dosis Mx'!$R$37:$X$54,1,FALSE),'Dosis Mx'!$R$37:$X$54,6,FALSE),0) -> 0 | Z38: =IFERROR(VLOOKUP(VLOOKUP(E38,'Dosis Mx'!$R$55:$X$78,1,FALSE),'Dosis Mx'!$R$55:$X$78,6,FALSE),0) -> 0 | AA38: =+F38*(24/H38) -> #DIV/0!
U39: =+V39*(W39+X39+Y39+Z39) -> 0 | W39: =IFERROR(VLOOKUP(VLOOKUP(E39,'Dosis Mx'!$R$1:$X$19,1,FALSE),'Dosis Mx'!$R$1:$X$19,6,FALSE),0) -> 0 | X39: =IFERROR(VLOOKUP(VLOOKUP(E39,'Dosis Mx'!$R$20:$X$36,1,FALSE),'Dosis Mx'!$R$20:$X$36,6,FALSE),0) -> 0 | Y39: =IFERROR(VLOOKUP(VLOOKUP(E39,'Dosis Mx'!$R$37:$X$54,1,FALSE),'Dosis Mx'!$R$37:$X$54,6,FALSE),0) -> 0 | Z39: =IFERROR(VLOOKUP(VLOOKUP(E39,'Dosis Mx'!$R$55:$X$78,1,FALSE),'Dosis Mx'!$R$55:$X$78,6,FALSE),0) -> 0 | AA39: =+F39*(24/H39) -> #DIV/0!
U40: =+V40*(W40+X40+Y40+Z40) -> 0 | W40: =IFERROR(VLOOKUP(VLOOKUP(E40,'Dosis Mx'!$R$1:$X$19,1,FALSE),'Dosis Mx'!$R$1:$X$19,6,FALSE),0) -> 0 | X40: =IFERROR(VLOOKUP(VLOOKUP(E40,'Dosis Mx'!$R$20:$X$36,1,FALSE),'Dosis Mx'!$R$20:$X$36,6,FALSE),0) -> 0 | Y40: =IFERROR(VLOOKUP(VLOOKUP(E40,'Dosis Mx'!$R$37:$X$54,1,FALSE),'Dosis Mx'!$R$37:$X$54,6,FALSE),0) -> 0 | Z40: =IFERROR(VLOOKUP(VLOOKUP(E40,'Dosis Mx'!$R$55:$X$78,1,FALSE),'Dosis Mx'!$R$55:$X$78,6,FALSE),0) -> 0 | AA40: =+F40*(24/H40) -> #DIV/0!
U41: =+V41*(W41+X41+Y41+Z41) -> 0 | W41: =IFERROR(VLOOKUP(VLOOKUP(E41,'Dosis Mx'!$R$1:$X$19,1,FALSE),'Dosis Mx'!$R$1:$X$19,6,FALSE),0) -> 0 | X41: =IFERROR(VLOOKUP(VLOOKUP(E41,'Dosis Mx'!$R$20:$X$36,1,FALSE),'Dosis Mx'!$R$20:$X$36,6,FALSE),0) -> 0 | Y41: =IFERROR(VLOOKUP(VLOOKUP(E41,'Dosis Mx'!$R$37:$X$54,1,FALSE),'Dosis Mx'!$R$37:$X$54,6,FALSE),0) -> 0 | Z41: =IFERROR(VLOOKUP(VLOOKUP(E41,'Dosis Mx'!$R$55:$X$78,1,FALSE),'Dosis Mx'!$R$55:$X$78,6,FALSE),0) -> 0 | AA41: =+F41*(24/H41) -> #DIV/0!
U42: =+V42*(W42+X42+Y42+Z42) -> 0 | W42: =IFERROR(VLOOKUP(VLOOKUP(E42,'Dosis Mx'!$R$1:$X$19,1,FALSE),'Dosis Mx'!$R$1:$X$19,6,FALSE),0) -> 0 | X42: =IFERROR(VLOOKUP(VLOOKUP(E42,'Dosis Mx'!$R$20:$X$36,1,FALSE),'Dosis Mx'!$R$20:$X$36,6,FALSE),0) -> 0 | Y42: =IFERROR(VLOOKUP(VLOOKUP(E42,'Dosis Mx'!$R$37:$X$54,1,FALSE),'Dosis Mx'!$R$37:$X$54,6,FALSE),0) -> 0 | Z42: =IFERROR(VLOOKUP(VLOOKUP(E42,'Dosis Mx'!$R$55:$X$78,1,FALSE),'Dosis Mx'!$R$55:$X$78,6,FALSE),0) -> 0 | AA42: =+F42*(24/H42) -> #DIV/0!
U43: =+V43*(W43+X43+Y43+Z43) -> 0 | W43: =IFERROR(VLOOKUP(VLOOKUP(E43,'Dosis Mx'!$R$1:$X$19,1,FALSE),'Dosis Mx'!$R$1:$X$19,6,FALSE),0) -> 0 | X43: =IFERROR(VLOOKUP(VLOOKUP(E43,'Dosis Mx'!$R$20:$X$36,1,FALSE),'Dosis Mx'!$R$20:$X$36,6,FALSE),0) -> 0 | Y43: =IFERROR(VLOOKUP(VLOOKUP(E43,'Dosis Mx'!$R$37:$X$54,1,FALSE),'Dosis Mx'!$R$37:$X$54,6,FALSE),0) -> 0 | Z43: =IFERROR(VLOOKUP(VLOOKUP(E43,'Dosis Mx'!$R$55:$X$78,1,FALSE),'Dosis Mx'!$R$55:$X$78,6,FALSE),0) -> 0 | AA43: =+F43*(24/H43) -> #DIV/0!
U44: =+V44*(W44+X44+Y44+Z44) -> 0 | W44: =IFERROR(VLOOKUP(VLOOKUP(E44,'Dosis Mx'!$R$1:$X$19,1,FALSE),'Dosis Mx'!$R$1:$X$19,6,FALSE),0) -> 0 | X44: =IFERROR(VLOOKUP(VLOOKUP(E44,'Dosis Mx'!$R$20:$X$36,1,FALSE),'Dosis Mx'!$R$20:$X$36,6,FALSE),0) -> 0 | Y44: =IFERROR(VLOOKUP(VLOOKUP(E44,'Dosis Mx'!$R$37:$X$54,1,FALSE),'Dosis Mx'!$R$37:$X$54,6,FALSE),0) -> 0 | Z44: =IFERROR(VLOOKUP(VLOOKUP(E44,'Dosis Mx'!$R$55:$X$78,1,FALSE),'Dosis Mx'!$R$55:$X$78,6,FALSE),0) -> 0 | AA44: =+F44*(24/H44) -> #DIV/0!
... U61: =+V61*(W61+X61+Y61+Z61) -> 0 | W61: =IFERROR(VLOOKUP(VLOOKUP(E61,'Dosis Mx'!$R$1:$X$19,1,FALSE),'Dosis Mx'!$R$1:$X$19,6,FALSE),0) -> 0 | X61: =IFERROR(VLOOKUP(VLOOKUP(E61,'Dosis Mx'!$R$20:$X$36,1,FALSE),'Dosis Mx'!$R$20:$X$36,6,FALSE),0) -> 0 | Y61: =IFERROR(VLOOKUP(VLOOKUP(E61,'Dosis Mx'!$R$37:$X$54,1,FALSE),'Dosis Mx'!$R$37:$X$54,6,FALSE),0) -> 0 | Z61: =IFERROR(VLOOKUP(VLOOKUP(E61,'Dosis Mx'!$R$55:$X$78,1,FALSE),'Dosis Mx'!$R$55:$X$78,6,FALSE),0) -> 0 | AA61: =+F61*(24/H61) -> #DIV/0!

Sheet 13-10-2023
B1: FECHA | C1: 45212
A2: No | B2: Servicio | C2: Docidentidad | D2: Usuario | E2: Nombre | F2: Dosis | G2: Medidadosis | H2: Frecuencia | I2: Unidadfrecuencia | J2: Tto Empirico | K2: Tto Dirigido | L2: cultivo | M2: Suspender | N2: Cambiar | R2: Observacionesorden | S2: Codigo Diagnostico | T2: Diagnostico | U2: Dosis | V2: Peso(kg) | W2: ITU | X2: ITB | Y2: NEUMONIA | Z2: MENINGITIS | AA2: Dosis recetada
N3: Escalar | O3: Desescalar | P3: RXN adversa | Q3: Por dosis
A4: 1 | B4: 501-4 | C4: 1038550461 | D4: ADHARA GALEANO | E4: Clindamicina (Fosfato) 600 mg /4ml Solucion Inyectable | F4: 70 | G4: MG | H4: 6 | I4: H | J4: I | S4: L029 | T4: ABSCESO CUTANEO, FURUNCULO Y ANTRAX DE SITIO NO ESPECIFICADO | U4: =+V4*(W4+X4+Y4+Z4) -> 314.55 | V4: 6.99 | W4: =IFERROR(VLOOKUP(VLOOKUP(E4,'Dosis Mx'!$R$1:$X$19,1,FALSE),'Dosis Mx'!$R$1:$X$19,6,FALSE),0) -> 0 | X4: =IFERROR(VLOOKUP(VLOOKUP(E4,'Dosis Mx'!$R$20:$X$36,1,FALSE),'Dosis Mx'!$R$20:$X$36,6,FALSE),0) -> 10 | Y4: =IFERROR(VLOOKUP(VLOOKUP(E4,'Dosis Mx'!$R$37:$X$54,1,FALSE),'Dosis Mx'!$R$37:$X$54,6,FALSE),0) -> 35 | Z4: =IFERROR(VLOOKUP(VLOOKUP(E4,'Dosis Mx'!$R$55:$X$78,1,FALSE),'Dosis Mx'!$R$55:$X$78,6,FALSE),0) -> 0 | AA4: =+F4*(24/H4) -> 280 | AB4: 5 | AC4: 31
A5: 2 | B5: 502-3 | C5: 1129604154 | D5: LUCIANA LEAL TANGARIFE | E5: Nistatina 100.000 U/ml Suspension Oral Frasco X 60 ml | F5: 5 | G5: 15 | H5: 6 | I5: H | J5: NI | M5: X | S5: K121 | T5: OTRAS FORMAS DE ESTOMATITIS | U5: =+V5*(W5+X5+Y5+Z5) -> 0 | V5: 7.17 | W5: =IFERROR(VLOOKUP(VLOOKUP(E5,'Dosis Mx'!$R$1:$X$19,1,FALSE),'Dosis Mx'!$R$1:$X$19,6,FALSE),0) -> 0 | X5: =IFERROR(VLOOKUP(VLOOKUP(E5,'Dosis Mx'!$R$20:$X$36,1,FALSE),'Dosis Mx'!$R$20:$X$36,6,FALSE),0) -> 0 | Y5: =IFERROR(VLOOKUP(VLOOKUP(E5,'Dosis Mx'!$R$37:$X$54,1,FALSE),'Dosis Mx'!$R$37:$X$54,6,FALSE),0) -> 0 | Z5: =IFERROR(VLOOKUP(VLOOKUP(E5,'Dosis Mx'!$R$55:$X$78,1,FALSE),'Dosis Mx'!$R$55:$X$78,6,FALSE),0) -> 0 | AA5: =+F5*(24/H5) -> 20 | AB5: 6 | AC5: 12
A6: 3 | B6: 502-4 | C6: 1018279481 | D6: CHLOE HENAO VILLEGAS | E6: AMIKacina (Sulfato) 100 mg/2 ml Solucion Inyectable | F6: 135 | G6: MG | H6: 24 | I6: H | J6: I | L6: X | S6: N390 | T6: INFECCION DE VIAS URINARIAS, SITIO NO ESPECIFICADO | U6: =+V6*(W6+X6+Y6+Z6) -> 299 | V6: 9.2 | W6: =IFERROR(VLOOKUP(VLOOKUP(E6,'Dosis Mx'!$R$1:$X$19,1,FALSE),'Dosis Mx'!$R$1:$X$19,6,FALSE),0) -> 15 | X6: =IFERROR(VLOOKUP(VLOOKUP(E6,'Dosis Mx'!$R$20:$X$36,1,FALSE),'Dosis Mx'!$R$20:$X$36,6,FALSE),0) -> 0 | Y6: =IFERROR(VLOOKUP(VLOOKUP(E6,'Dosis Mx'!$R$37:$X$54,1,FALSE),'Dosis Mx'!$R$37:$X$54,6,FALSE),0) -> 0 | Z6: =IFERROR(VLOOKUP(VLOOKUP(E6,'Dosis Mx'!$R$55:$X$78,1,FALSE),'Dosis Mx'!$R$55:$X$78,6,FALSE),0) -> 17.5 | AA6: =+F6*(24/H6) -> 135 | AB6: 7
A7: 4 | B7: 502-5 | C7: 1022170611 | D7: LIAM DAVID GONZALEZ MARRUGO | E7: AMIKacina (Sulfato) 100 mg/2 ml Solucion Inyectable | F7: 150 | G7: MG | H7: 24 | I7: H | J7: I | L7: X | S7: F445 | T7: CONVULSIONES DISOCIATIVAS | U7: =+V7*(W7+X7+Y7+Z7) -> 338 | V7: 10.4 | W7: =IFERROR(VLOOKUP(VLOOKUP(E7,'Dosis Mx'!$R$1:$X$19,1,FALSE),'Dosis Mx'!$R$1:$X$19,6,FALSE),0) -> 15 | X7: =IFERROR(VLOOKUP(VLOOKUP(E7,'Dosis Mx'!$R$20:$X$36,1,FALSE),'Dosis Mx'!$R$20:$X$36,6,FALSE),0) -> 0 | Y7: =IFERROR(VLOOKUP(VLOOKUP(E7,'Dosis Mx'!$R$37:$X$54,1,FALSE),'Dosis Mx'!$R$37:$X$54,6,FALSE),0) -> 0 | Z7: =IFERROR(VLOOKUP(VLOOKUP(E7,'Dosis Mx'!$R$55:$X$78,1,FALSE),'Dosis Mx'!$R$55:$X$78,6,FALSE),0) -> 17.5 | AA7: =+F7*(24/H7) -> 150 | AB7: UCI
A8: 5 | B8: 503-5 | C8: 1039380512 | D8: SARAY MARTINEZ MAYA | E8: AMIKacina (Sulfato) 500 mg/2 ml Solucion Inyectable | F8: 240 | G8: MG | H8: 24 | I8: H | J8: I | L8: X | S8: N390 | T8: INFECCION DE VIAS URINARIAS, SITIO NO ESPECIFICADO | U8: =+V8*(W8+X8+Y8+Z8) -> 507 | V8: 15.6 | W8: =IFERROR(VLOOKUP(VLOOKUP(E8,'Dosis Mx'!$R$1:$X$19,1,FALSE),'Dosis Mx'!$R$1:$X$19,6,FALSE),0) -> 15 | X8: =IFERROR(VLOOKUP(VLOOKUP(E8,'Dosis Mx'!$R$20:$X$36,1,FALSE),'Dosis Mx'!$R$20:$X$36,6,FALSE),0) -> 0 | Y8: =IFERROR(VLOOKUP(VLOOKUP(E8,'Dosis Mx'!$R$37:$X$54,1,FALSE),'Dosis Mx'!$R$37:$X$54,6,FALSE),0) -> 0 | Z8: =IFERROR(VLOOKUP(VLOOKUP(E8,'Dosis Mx'!$R$55:$X$78,1,FALSE),'Dosis Mx'!$R$55:$X$78,6,FALSE),0) -> 17.5 | AA8: =+F8*(24/H8) -> 240 | AB8: URGENCIAS
A9: 6 | B9: 506-1 | C9: 1034927181 | D9: JULIETA GARCIA RODRIGUEZ | E9: AMIKacina (Sulfato) 500 mg/2 ml Solucion Inyectable | F9: 240 | G9: MG | H9: 24 | I9: H | R9: ALTA, CEFALEXINA 7 DÍAS | S9: N390 | T9: INFECCION DE VIAS URINARIAS, SITIO NO ESPECIFICADO | U9: =+V9*(W9+X9+Y9+Z9) -> 520 | V9: 16 | W9: =IFERROR(VLOOKUP(VLOOKUP(E9,'Dosis Mx'!$R$1:$X$19,1,FALSE),'Dosis Mx'!$R$1:$X$19,6,FALSE),0) -> 15 | X9: =IFERROR(VLOOKUP(VLOOKUP(E9,'Dosis Mx'!$R$20:$X$36,1,FALSE),'Dosis Mx'!$R$20:$X$36,6,FALSE),0) -> 0 | Y9: =IFERROR(VLOOKUP(VLOOKUP(E9,'Dosis Mx'!$R$37:$X$54,1,FALSE),'Dosis Mx'!$R$37:$X$54,6,FALSE),0) -> 0 | Z9: =IFERROR(VLOOKUP(VLOOKUP(E9,'Dosis Mx'!$R$55:$X$78,1,FALSE),'Dosis Mx'!$R$55:$X$78,6,FALSE),0) -> 17.5 | AA9: =+F9*(24/H9) -> 240
A10: 7 | B10: 506-2 | C10: 1039912668 | D10: ANGELESS SOFIA QUINTERO CAMARGO | E10: AMIKacina (Sulfato) 100 mg/2 ml Solucion Inyectable | F10: 147 | G10: MG | H10: 24 | I10: H | J10: I | L10: X | S10: N390 | T10: INFECCION DE VIAS URINARIAS, SITIO NO ESPECIFICADO | U10: =+V10*(W10+X10+Y10+Z10) -> 318.5 | V10: 9.8 | W10: =IFERROR(VLOOKUP(VLOOKUP(E10,'Dosis Mx'!$R$1:$X$19,1,FALSE),'Dosis Mx'!$R$1:$X$19,6,FALSE),0) -> 15 | X10: =IFERROR(VLOOKUP(VLOOKUP(E10,'Dosis Mx'!$R$20:$X$36,1,FALSE),'Dosis Mx'!$R$20:$X$36,6,FALSE),0) -> 0 | Y10: =IFERROR(VLOOKUP(VLOOKUP(E10,'Dosis Mx'!$R$37:$X$54,1,FALSE),'Dosis Mx'!$R$37:$X$54,6,FALSE),0) -> 0 | Z10: =IFERROR(VLOOKUP(VLOOKUP(E10,'Dosis Mx'!$R$55:$X$78,1,FALSE),'Dosis Mx'!$R$55:$X$78,6,FALSE),0) -> 17.5 | AA10: =+F10*(24/H10) -> 147
A11: 8 | B11: Aisl 500 | C11: 1023526248 | D11: MARIANA LOPEZ MUNERA | E11: AMPIcilina Sodica/SULBactam Sodico 1000/500mg Polvo para iny (Ped) | F11: 2000 | G11: MG | H11: 6 | I11: H | J11: NI | L11: X | S11: R509 | T11: FIEBRE, NO ESPECIFICADA | U11: =+V11*(W11+X11+Y11+Z11) -> 9100 | V11: 45.5 | W11: =IFERROR(VLOOKUP(VLOOKUP(E11,'Dosis Mx'!$R$1:$X$19,1,FALSE),'Dosis Mx'!$R$1:$X$19,6,FALSE),0) -> 0 | X11: =IFERROR(VLOOKUP(VLOOKUP(E11,'Dosis Mx'!$R$20:$X$36,1,FALSE),'Dosis Mx'!$R$20:$X$36,6,FALSE),0) -> 0 | Y11: =IFERROR(VLOOKUP(VLOOKUP(E11,'Dosis Mx'!$R$37:$X$54,1,FALSE),'Dosis Mx'!$R$37:$X$54,6,FALSE),0) -> 200 | Z11: =IFERROR(VLOOKUP(VLOOKUP(E11,'Dosis Mx'!$R$55:$X$78,1,FALSE),'Dosis Mx'!$R$55:$X$78,6,FALSE),0) -> 0 | AA11: =+F11*(24/H11) -> 8000
A12: 9 | B12: 708-3 | C12: 1039050469 | D12: JEHILYN HENAO BERMUDEZ | E12: AMIKacina (Sulfato) 100 mg/2 ml Solucion Inyectable | F12: 200 | G12: MG | H12: 24 | I12: H | J12: I | S12: N390 | T12: INFECCION DE VIAS URINARIAS, SITIO NO ESPECIFICADO | U12: =+V12*(W12+X12+Y12+Z12) -> 455 | V12: 14 | W12: =IFERROR(VLOOKUP(VLOOKUP(E12,'Dosis Mx'!$R$1:$X$19,1,FALSE),'Dosis Mx'!$R$1:$X$19,6,FALSE),0) -> 15 | X12: =IFERROR(VLOOKUP(VLOOKUP(E12,'Dosis Mx'!$R$20:$X$36,1,FALSE),'Dosis Mx'!$R$20:$X$36,6,FALSE),0) -> 0 | Y12: =IFERROR(VLOOKUP(VLOOKUP(E12,'Dosis Mx'!$R$37:$X$54,1,FALSE),'Dosis Mx'!$R$37:$X$54,6,FALSE),0) -> 0 | Z12: =IFERROR(VLOOKUP(VLOOKUP(E12,'Dosis Mx'!$R$55:$X$78,1,FALSE),'Dosis Mx'!$R$55:$X$78,6,FALSE),0) -> 17.5 | AA12: =+F12*(24/H12) -> 200
A13: 10 | B13: 708-4 | C13: 1015071491 | D13: MARIA STEFANNY QUINTERO HENAO | E13: Ciprofloxacina (Clorhidrato) 100 mg/10 ml Sln Inyectable | F13: 320 | G13: MG | H13: 8 | I13: H | J13: I | L13: X | S13: N390 | T13: INFECCION DE VIAS URINARIAS, SITIO NO ESPECIFICADO | U13: =+V13*(W13+X13+Y13+Z13) -> 1000 | V13: 40 | W13: =IFERROR(VLOOKUP(VLOOKUP(E13,'Dosis Mx'!$R$1:$X$19,1,FALSE),'Dosis Mx'!$R$1:$X$19,6,FALSE),0) -> 25 | X13: =IFERROR(VLOOKUP(VLOOKUP(E13,'Dosis Mx'!$R$20:$X$36,1,FALSE),'Dosis Mx'!$R$20:$X$36,6,FALSE),0) -> 0 | Y13: =IFERROR(VLOOKUP(VLOOKUP(E13,'Dosis Mx'!$R$37:$X$54,1,FALSE),'Dosis Mx'!$R$37:$X$54,6,FALSE),0) -> 0 | Z13: =IFERROR(VLOOKUP(VLOOKUP(E13,'Dosis Mx'!$R$55:$X$78,1,FALSE),'Dosis Mx'!$R$55:$X$78,6,FALSE),0) -> 0 | AA13: =+F13*(24/H13) -> 960
A14: 11 | B14: 708-6 | C14: 1025677881 | D14: MIA ANDRADES MURILLO | E14: AMIKacina (Sulfato) 500 mg/2 ml Solucion Inyectable | F14: 165 | G14: MG | H14: 24 | I14: H | J14: I | R14: ALTA | S14: N390 | T14: INFECCION DE VIAS URINARIAS, SITIO NO ESPECIFICADO | U14: =+V14*(W14+X14+Y14+Z14) -> 357.5 | V14: 11 | W14: =IFERROR(VLOOKUP(VLOOKUP(E14,'Dosis Mx'!$R$1:$X$19,1,FALSE),'Dosis Mx'!$R$1:$X$19,6,FALSE),0) -> 15 | X14: =IFERROR(VLOOKUP(VLOOKUP(E14,'Dosis Mx'!$R$20:$X$36,1,FALSE),'Dosis Mx'!$R$20:$X$36,6,FALSE),0) -> 0 | Y14: =IFERROR(VLOOKUP(VLOOKUP(E14,'Dosis Mx'!$R$37:$X$54,1,FALSE),'Dosis Mx'!$R$37:$X$54,6,FALSE),0) -> 0 | Z14: =IFERROR(VLOOKUP(VLOOKUP(E14,'Dosis Mx'!$R$55:$X$78,1,FALSE),'Dosis Mx'!$R$55:$X$78,6,FALSE),0) -> 17.5 | AA14: =+F14*(24/H14) -> 165
A15: 12 | B15: 709-1 | C15: 1023665226 | D15: ANTHONY BLANCO GELEZ | E15: AMPIcilina Sodica/SULBactam Sodico 1000/500mg Polvo para iny (Ped) | F15: 400 | G15: MG | H15: 6 | I15: H | J15: I | M15: X | R15: ALTA | S15: A499 | T15: INFECCION BACTERIANA, NO ESPECIFICADA | U15: =+V15*(W15+X15+Y15+Z15) -> 1640 | V15: 8.2 | W15: =IFERROR(VLOOKUP(VLOOKUP(E15,'Dosis Mx'!$R$1:$X$19,1,FALSE),'Dosis Mx'!$R$1:$X$19,6,FALSE),0) -> 0 | X15: =IFERROR(VLOOKUP(VLOOKUP(E15,'Dosis Mx'!$R$20:$X$36,1,FALSE),'Dosis Mx'!$R$20:$X$36,6,FALSE),0) -> 0 | Y15: =IFERROR(VLOOKUP(VLOOKUP(E15,'Dosis Mx'!$R$37:$X$54,1,FALSE),'Dosis Mx'!$R$37:$X$54,6,FALSE),0) -> 200 | Z15: =IFERROR(VLOOKUP(VLOOKUP(E15,'Dosis Mx'!$R$55:$X$78,1,FALSE),'Dosis Mx'!$R$55:$X$78,6,FALSE),0) -> 0 | AA15: =+F15*(24/H15) -> 1600
A16: 13 | B16: 709-4 | C16: 1011420656 | D16: JULIETA MARULANDA RODRIGUEZ | E16: Cefazolina 1000 mg Polvo para Inyeccion | F16: 250 | G16: MG | H16: 6 | I16: H | J16: I | S16: L040 | T16: LINFADENITIS AGUDA DE CARA, CABEZA Y CUELLO | U16: =+V16*(W16+X16+Y16+Z16) -> 980 | V16: 9.8 | W16: =IFERROR(VLOOKUP(VLOOKUP(E16,'Dosis Mx'!$R$1:$X$19,1,FALSE),'Dosis Mx'!$R$1:$X$19,6,FALSE),0) -> 0 | X16: =IFERROR(VLOOKUP(VLOOKUP(E16,'Dosis Mx'!$R$20:$X$36,1,FALSE),'Dosis Mx'!$R$20:$X$36,6,FALSE),0) -> 100 | Y16: =IFERROR(VLOOKUP(VLOOKUP(E16,'Dosis Mx'!$R$37:$X$54,1,FALSE),'Dosis Mx'!$R$37:$X$54,6,FALSE),0) -> 0 | Z16: =IFERROR(VLOOKUP(VLOOKUP(E16,'Dosis Mx'!$R$55:$X$78,1,FALSE),'Dosis Mx'!$R$55:$X$78,6,FALSE),0) -> 0 | AA16: =+F16*(24/H16) -> 1000
A17: 14 | B17: 709-6 | C17: 1078692967 | D17: THARA MARIAM PEÑA ANGULO | E17: Clindamicina (Fosfato) 600 mg /4ml Solucion Inyectable | F17: 160 | G17: MG | H17: 6 | I17: H | J17: I | S17: M255 | T17: DOLOR EN ARTICULACION | U17: =+V17*(W17+X17+Y17+Z17) -> 724.5 | V17: 16.1 | W17: =IFERROR(VLOOKUP(VLOOKUP(E17,'Dosis Mx'!$R$1:$X$19,1,FALSE),'Dosis Mx'!$R$1:$X$19,6,FALSE),0) -> 0 | X17: =IFERROR(VLOOKUP(VLOOKUP(E17,'Dosis Mx'!$R$20:$X$36,1,FALSE),'Dosis Mx'!$R$20:$X$36,6,FALSE),0) -> 10 | Y17: =IFERROR(VLOOKUP(VLOOKUP(E17,'Dosis Mx'!$R$37:$X$54,1,FALSE),'Dosis Mx'!$R$37:$X$54,6,FALSE),0) -> 35 | Z17: =IFERROR(VLOOKUP(VLOOKUP(E17,'Dosis Mx'!$R$55:$X$78,1,FALSE),'Dosis Mx'!$R$55:$X$78,6,FALSE),0) -> 0 | AA17: =+F17*(24/H17) -> 640
A18: 15 | B18: 710-1 | C18: 1023556882 | D18: NICOLAS MONTOYA BEDOYA | E18: AMPIcilina Sodica/SULBactam Sodico 1000/500mg Polvo para iny (Ped) | F18: 800 | G18: MG | H18: 6 | I18: H | J18: I | S18: R509 | T18: FIEBRE, NO ESPECIFICADA | U18: =+V18*(W18+X18+Y18+Z18) -> 3200 | V18: 16 | W18: =IFERROR(VLOOKUP(VLOOKUP(E18,'Dosis Mx'!$R$1:$X$19,1,FALSE),'Dosis Mx'!$R$1:$X$19,6,FALSE),0) -> 0 | X18: =IFERROR(VLOOKUP(VLOOKUP(E18,'Dosis Mx'!$R$20:$X$36,1,FALSE),'Dosis Mx'!$R$20:$X$36,6,FALSE),0) -> 0 | Y18: =IFERROR(VLOOKUP(VLOOKUP(E18,'Dosis Mx'!$R$37:$X$54,1,FALSE),'Dosis Mx'!$R$37:$X$54,6,FALSE),0) -> 200 | Z18: =IFERROR(VLOOKUP(VLOOKUP(E18,'Dosis Mx'!$R$55:$X$78,1,FALSE),'Dosis Mx'!$R$55:$X$78,6,FALSE),0) -> 0 | AA18: =+F18*(24/H18) -> 3200
A19: 16 | B19: 710-5 | C19: 1042095438 | D19: DARIANA MILAGROS YEPES VERGARA | E19: Clindamicina (Fosfato) 600 mg /4ml Solucion Inyectable | F19: 90 | G19: MG | H19: 6 | I19: H | J19: I | S19: L024 | T19: ABSCESO CUTANEO, FURUNCULO Y ANTRAX DE MIEMBRO | U19: =+V19*(W19+X19+Y19+Z19) -> 166.5 | V19: 3.7 | W19: =IFERROR(VLOOKUP(VLOOKUP(E19,'Dosis Mx'!$R$1:$X$19,1,FALSE),'Dosis Mx'!$R$1:$X$19,6,FALSE),0) -> 0 | X19: =IFERROR(VLOOKUP(VLOOKUP(E19,'Dosis Mx'!$R$20:$X$36,1,FALSE),'Dosis Mx'!$R$20:$X$36,6,FALSE),0) -> 10 | Y19: =IFERROR(VLOOKUP(VLOOKUP(E19,'Dosis Mx'!$R$37:$X$54,1,FALSE),'Dosis Mx'!$R$37:$X$54,6,FALSE),0) -> 35 | Z19: =IFERROR(VLOOKUP(VLOOKUP(E19,'Dosis Mx'!$R$55:$X$78,1,FALSE),'Dosis Mx'!$R$55:$X$78,6,FALSE),0) -> 0 | AA19: =+F19*(24/H19) -> 360
A20: 17 | B20: Aisl 701 | C20: 1017284099 | D20: ASHLY JIREH CASTILLO SANCHEZ | E20: AZITromicina200mg/5 ml (4%)Polvo para reconstituirx15ml | F20: 47 | G20: MG | H20: 24 | I20: H | J20: I | S20: R509 | T20: FIEBRE, NO ESPECIFICADA | U20: =+V20*(W20+X20+Y20+Z20) -> 35.25 | V20: 4.7 | W20: =IFERROR(VLOOKUP(VLOOKUP(E20,'Dosis Mx'!$R$1:$X$19,1,FALSE),'Dosis Mx'!$R$1:$X$19,6,FALSE),0) -> 0 | X20: =IFERROR(VLOOKUP(VLOOKUP(E20,'Dosis Mx'!$R$20:$X$36,1,FALSE),'Dosis Mx'!$R$20:$X$36,6,FALSE),0) -> 0 | Y20: =IFERROR(VLOOKUP(VLOOKUP(E20,'Dosis Mx'!$R$37:$X$54,1,FALSE),'Dosis Mx'!$R$37:$X$54,6,FALSE),0) -> 7.5 | Z20: =IFERROR(VLOOKUP(VLOOKUP(E20,'Dosis Mx'!$R$55:$X$78,1,FALSE),'Dosis Mx'!$R$55:$X$78,6,FALSE),0) -> 0 | AA20: =+F20*(24/H20) -> 47
A21: 18 | B21: Aisl 702 | C21: VEN005084 | D21: DIEGO RAFAEL MORALES FLAMEZ | E21: Ceftriaxona (Sal Sodica) 1000 mg Polvo para Inyeccion | F21: 390 | G21: MG | H21: 12 | I21: H | J21: I | S21: N179 | T21: INSUFICIENCIA RENAL AGUDA, NO ESPECIFICADA | U21: =+V21*(W21+X21+Y21+Z21) -> 3372.5 | V21: 7.1 | W21: =IFERROR(VLOOKUP(VLOOKUP(E21,'Dosis Mx'!$R$1:$X$19,1,FALSE),'Dosis Mx'!$R$1:$X$19,6,FALSE),0) -> 300 | X21: =IFERROR(VLOOKUP(VLOOKUP(E21,'Dosis Mx'!$R$20:$X$36,1,FALSE),'Dosis Mx'!$R$20:$X$36,6,FALSE),0) -> 0 | Y21: =IFERROR(VLOOKUP(VLOOKUP(E21,'Dosis Mx'!$R$37:$X$54,1,FALSE),'Dosis Mx'!$R$37:$X$54,6,FALSE),0) -> 75 | Z21: =IFERROR(VLOOKUP(VLOOKUP(E21,'Dosis Mx'!$R$55:$X$78,1,FALSE),'Dosis Mx'!$R$55:$X$78,6,FALSE),0) -> 100 | AA21: =+F21*(24/H21) -> 780
A22: 19 | B22: Aisl 703 | C22: 1011420925 | D22: ALAN CAMILO MUÑOZ ZAPATA | E22: AMPIcilina Sodica/SULBactam Sodico 1000/500mg Polvo para iny (Ped) | F22: 450 | G22: MG | H22: 6 | I22: H | J22: I | S22: J219 | T22: BRONQUIOLITIS AGUDA, NO ESPECIFICADA | U22: =+V22*(W22+X22+Y22+Z22) -> 1700 | V22: 8.5 | W22: =IFERROR(VLOOKUP(VLOOKUP(E22,'Dosis Mx'!$R$1:$X$19,1,FALSE),'Dosis Mx'!$R$1:$X$19,6,FALSE),0) -> 0 | X22: =IFERROR(VLOOKUP(VLOOKUP(E22,'Dosis Mx'!$R$20:$X$36,1,FALSE),'Dosis Mx'!$R$20:$X$36,6,FALSE),0) -> 0 | Y22: =IFERROR(VLOOKUP(VLOOKUP(E22,'Dosis Mx'!$R$37:$X$54,1,FALSE),'Dosis Mx'!$R$37:$X$54,6,FALSE),0) -> 200 | Z22: =IFERROR(VLOOKUP(VLOOKUP(E22,'Dosis Mx'!$R$55:$X$78,1,FALSE),'Dosis Mx'!$R$55:$X$78,6,FALSE),0) -> 0 | AA22: =+F22*(24/H22) -> 1800
A23: 20 | B23: Aisl 705 | C23: 1031948923 | D23: MATEO VALENCIA VASQUEZ | E23: Ciprofloxacina (Clorhidrato) 100 mg/10 ml Sln Inyectable | F23: 90 | G23: MG | H23: 12 | I23: H | J23: I | L23: X | S23: A090 | T23: OTRAS GASTROENTERITIS Y COLITIS DE ORIGEN INFECCIOSO | U23: =+V23*(W23+X23+Y23+Z23) -> 225 | V23: 9 | W23: =IFERROR(VLOOKUP(VLOOKUP(E23,'Dosis Mx'!$R$1:$X$19,1,FALSE),'Dosis Mx'!$R$1:$X$19,6,FALSE),0) -> 25 | X23: =IFERROR(VLOOKUP(VLOOKUP(E23,'Dosis Mx'!$R$20:$X$36,1,FALSE),'Dosis Mx'!$R$20:$X$36,6,FALSE),0) -> 0 | Y23: =IFERROR(VLOOKUP(VLOOKUP(E23,'Dosis Mx'!$R$37:$X$54,1,FALSE),'Dosis Mx'!$R$37:$X$54,6,FALSE),0) -> 0 | Z23: =IFERROR(VLOOKUP(VLOOKUP(E23,'Dosis Mx'!$R$55:$X$78,1,FALSE),'Dosis Mx'!$R$55:$X$78,6,FALSE),0) -> 0 | AA23: =+F23*(24/H23) -> 180
A24: 21 | B24: Aisl 706 | C24: 1040262325 | D24: VICTOR ALFONSO FLOREZ AGUDELO | E24: Fluconazol 50 mg/5 ml Polvo para Suspension Frasco X 20 ml | F24: 85 | G24: MG | H24: 24 | I24: H | J24: I | R24: PROFILACTICO | S24: L080 | T24: PIODERMA | U24: =+V24*(W24+X24+Y24+Z24) -> 0 | V24: 6.55 | W24: =IFERROR(VLOOKUP(VLOOKUP(E24,'Dosis Mx'!$R$1:$X$19,1,FALSE),'Dosis Mx'!$R$1:$X$19,6,FALSE),0) -> 0 | X24: =IFERROR(VLOOKUP(VLOOKUP(E24,'Dosis Mx'!$R$20:$X$36,1,FALSE),'Dosis Mx'!$R$20:$X$36,6,FALSE),0) -> 0 | Y24: =IFERROR(VLOOKUP(VLOOKUP(E24,'Dosis Mx'!$R$37:$X$54,1,FALSE),'Dosis Mx'!$R$37:$X$54,6,FALSE),0) -> 0 | Z24: =IFERROR(VLOOKUP(VLOOKUP(E24,'Dosis Mx'!$R$55:$X$78,1,FALSE),'Dosis Mx'!$R$55:$X$78,6,FALSE),0) -> 0 | AA24: =+F24*(24/H24) -> 85
A25: 22 | B25: Aisl 707 | C25: 23099110655662 | D25: HIJO DE EMILSE PAOLA OSORIO | E25: Oxacilina (Sal Sodica) 1000 mg Polvo para Inyeccion | F25: 135 | G25: MG | H25: 6 | I25: H | R25: ALTA | S25: L032 | T25: CELULITIS DE LA CARA | U25: =+V25*(W25+X25+Y25+Z25) -> 1080 | V25: 2.7 | W25: =IFERROR(VLOOKUP(VLOOKUP(E25,'Dosis Mx'!$R$1:$X$19,1,FALSE),'Dosis Mx'!$R$1:$X$19,6,FALSE),0) -> 0 | X25: =IFERROR(VLOOKUP(VLOOKUP(E25,'Dosis Mx'!$R$20:$X$36,1,FALSE),'Dosis Mx'!$R$20:$X$36,6,FALSE),0) -> 200 | Y25: =IFERROR(VLOOKUP(VLOOKUP(E25,'Dosis Mx'!$R$37:$X$54,1,FALSE),'Dosis Mx'!$R$37:$X$54,6,FALSE),0) -> 0 | Z25: =IFERROR(VLOOKUP(VLOOKUP(E25,'Dosis Mx'!$R$55:$X$78,1,FALSE),'Dosis Mx'!$R$55:$X$78,6,FALSE),0) -> 200 | AA25: =+F25*(24/H25) -> 540
A26: 23 | U26: =+V26*(W26+X26+Y26+Z26) -> 0 | W26: =IFERROR(VLOOKUP(VLOOKUP(E26,'Dosis Mx'!$R$1:$X$19,1,FALSE),'Dosis Mx'!$R$1:$X$19,6,FALSE),0) -> 0 | X26: =IFERROR(VLOOKUP(VLOOKUP(E26,'Dosis Mx'!$R$20:$X$36,1,FALSE),'Dosis Mx'!$R$20:$X$36,6,FALSE),0) -> 0 | Y26: =IFERROR(VLOOKUP(VLOOKUP(E26,'Dosis Mx'!$R$37:$X$54,1,FALSE),'Dosis Mx'!$R$37:$X$54,6,FALSE),0) -> 0 | Z26: =IFERROR(VLOOKUP(VLOOKUP(E26,'Dosis Mx'!$R$55:$X$78,1,FALSE),'Dosis Mx'!$R$55:$X$78,6,FALSE),0) -> 0 | AA26: =+F26*(24/H26) -> #DIV/0!
A27: 24 | U27: =+V27*(W27+X27+Y27+Z27) -> 0 | W27: =IFERROR(VLOOKUP(VLOOKUP(E27,'Dosis Mx'!$R$1:$X$19,1,FALSE),'Dosis Mx'!$R$1:$X$19,6,FALSE),0) -> 0 | X27: =IFERROR(VLOOKUP(VLOOKUP(E27,'Dosis Mx'!$R$20:$X$36,1,FALSE),'Dosis Mx'!$R$20:$X$36,6,FALSE),0) -> 0 | Y27: =IFERROR(VLOOKUP(VLOOKUP(E27,'Dosis Mx'!$R$37:$X$54,1,FALSE),'Dosis Mx'!$R$37:$X$54,6,FALSE),0) -> 0 | Z27: =IFERROR(VLOOKUP(VLOOKUP(E27,'Dosis Mx'!$R$55:$X$78,1,FALSE),'Dosis Mx'!$R$55:$X$78,6,FALSE),0) -> 0 | AA27: =+F27*(24/H27) -> #DIV/0!
A28: 25 | U28: =+V28*(W28+X28+Y28+Z28) -> 0 | W28: =IFERROR(VLOOKUP(VLOOKUP(E28,'Dosis Mx'!$R$1:$X$19,1,FALSE),'Dosis Mx'!$R$1:$X$19,6,FALSE),0) -> 0 | X28: =IFERROR(VLOOKUP(VLOOKUP(E28,'Dosis Mx'!$R$20:$X$36,1,FALSE),'Dosis Mx'!$R$20:$X$36,6,FALSE),0) -> 0 | Y28: =IFERROR(VLOOKUP(VLOOKUP(E28,'Dosis Mx'!$R$37:$X$54,1,FALSE),'Dosis Mx'!$R$37:$X$54,6,FALSE),0) -> 0 | Z28: =IFERROR(VLOOKUP(VLOOKUP(E28,'Dosis Mx'!$R$55:$X$78,1,FALSE),'Dosis Mx'!$R$55:$X$78,6,FALSE),0) -> 0 | AA28: =+F28*(24/H28) -> #DIV/0!
A29: 26 | U29: =+V29*(W29+X29+Y29+Z29) -> 0 | W29: =IFERROR(VLOOKUP(VLOOKUP(E29,'Dosis Mx'!$R$1:$X$19,1,FALSE),'Dosis Mx'!$R$1:$X$19,6,FALSE),0) -> 0 | X29: =IFERROR(VLOOKUP(VLOOKUP(E29,'Dosis Mx'!$R$20:$X$36,1,FALSE),'Dosis Mx'!$R$20:$X$36,6,FALSE),0) -> 0 | Y29: =IFERROR(VLOOKUP(VLOOKUP(E29,'Dosis Mx'!$R$37:$X$54,1,FALSE),'Dosis Mx'!$R$37:$X$54,6,FALSE),0) -> 0 | Z29: =IFERROR(VLOOKUP(VLOOKUP(E29,'Dosis Mx'!$R$55:$X$78,1,FALSE),'Dosis Mx'!$R$55:$X$78,6,FALSE),0) -> 0 | AA29: =+F29*(24/H29) -> #DIV/0!
A30: 27 | U30: =+V30*(W30+X30+Y30+Z30) -> 0 | W30: =IFERROR(VLOOKUP(VLOOKUP(E30,'Dosis Mx'!$R$1:$X$19,1,FALSE),'Dosis Mx'!$R$1:$X$19,6,FALSE),0) -> 0 | X30: =IFERROR(VLOOKUP(VLOOKUP(E30,'Dosis Mx'!$R$20:$X$36,1,FALSE),'Dosis Mx'!$R$20:$X$36,6,FALSE),0) -> 0 | Y30: =IFERROR(VLOOKUP(VLOOKUP(E30,'Dosis Mx'!$R$37:$X$54,1,FALSE),'Dosis Mx'!$R$37:$X$54,6,FALSE),0) -> 0 | Z30: =IFERROR(VLOOKUP(VLOOKUP(E30,'Dosis Mx'!$R$55:$X$78,1,FALSE),'Dosis Mx'!$R$55:$X$78,6,FALSE),0) -> 0 | AA30: =+F30*(24/H30) -> #DIV/0!
A31: 28 | U31: =+V31*(W31+X31+Y31+Z31) -> 0 | W31: =IFERROR(VLOOKUP(VLOOKUP(E31,'Dosis Mx'!$R$1:$X$19,1,FALSE),'Dosis Mx'!$R$1:$X$19,6,FALSE),0) -> 0 | X31: =IFERROR(VLOOKUP(VLOOKUP(E31,'Dosis Mx'!$R$20:$X$36,1,FALSE),'Dosis Mx'!$R$20:$X$36,6,FALSE),0) -> 0 | Y31: =IFERROR(VLOOKUP(VLOOKUP(E31,'Dosis Mx'!$R$37:$X$54,1,FALSE),'Dosis Mx'!$R$37:$X$54,6,FALSE),0) -> 0 | Z31: =IFERROR(VLOOKUP(VLOOKUP(E31,'Dosis Mx'!$R$55:$X$78,1,FALSE),'Dosis Mx'!$R$55:$X$78,6,FALSE),0) -> 0 | AA31: =+F31*(24/H31) -> #DIV/0!
A32: 29 | U32: =+V32*(W32+X32+Y32+Z32) -> 0 | W32: =IFERROR(VLOOKUP(VLOOKUP(E32,'Dosis Mx'!$R$1:$X$19,1,FALSE),'Dosis Mx'!$R$1:$X$19,6,FALSE),0) -> 0 | X32: =IFERROR(VLOOKUP(VLOOKUP(E32,'Dosis Mx'!$R$20:$X$36,1,FALSE),'Dosis Mx'!$R$20:$X$36,6,FALSE),0) -> 0 | Y32: =IFERROR(VLOOKUP(VLOOKUP(E32,'Dosis Mx'!$R$37:$X$54,1,FALSE),'Dosis Mx'!$R$37:$X$54,6,FALSE),0) -> 0 | Z32: =IFERROR(VLOOKUP(VLOOKUP(E32,'Dosis Mx'!$R$55:$X$78,1,FALSE),'Dosis Mx'!$R$55:$X$78,6,FALSE),0) -> 0 | AA32: =+F32*(24/H32) -> #DIV/0!
A33: No | B33: Servicio | E33: Nombre | F33: Dosis | G33: Medidadosis | H33: Frecuencia | I33: Unidadfrecuencia | J33: Tto Empirico | K33: Tto Dirigido | L33: cultivo | M33: Suspender | N33: Cambiar | R33: Observacionesorden | S33: Codigo Diagnostico | T33: Diagnostico | U33: Dosis | V33: Peso(kg) | W33: ITU | X33: ITB | Y33: NEUMONIA | Z33: MENINGITIS | AA33: Dosis recetada
N34: Escalar | O34: Desescalar | P34: RXN adversa | Q34: Por dosis
U35: =+V35*(W35+X35+Y35+Z35) -> 0 | W35: =IFERROR(VLOOKUP(VLOOKUP(E35,'Dosis Mx'!$R$1:$X$19,1,FALSE),'Dosis Mx'!$R$1:$X$19,6,FALSE),0) -> 0 | X35: =IFERROR(VLOOKUP(VLOOKUP(E35,'Dosis Mx'!$R$20:$X$36,1,FALSE),'Dosis Mx'!$R$20:$X$36,6,FALSE),0) -> 0 | Y35: =IFERROR(VLOOKUP(VLOOKUP(E35,'Dosis Mx'!$R$37:$X$54,1,FALSE),'Dosis Mx'!$R$37:$X$54,6,FALSE),0) -> 0 | Z35: =IFERROR(VLOOKUP(VLOOKUP(E35,'Dosis Mx'!$R$55:$X$78,1,FALSE),'Dosis Mx'!$R$55:$X$78,6,FALSE),0) -> 0 | AA35: =+F35*(24/H35) -> #DIV/0!
U36: =+V36*(W36+X36+Y36+Z36) -> 0 | W36: =IFERROR(VLOOKUP(VLOOKUP(E36,'Dosis Mx'!$R$1:$X$19,1,FALSE),'Dosis Mx'!$R$1:$X$19,6,FALSE),0) -> 0 | X36: =IFERROR(VLOOKUP(VLOOKUP(E36,'Dosis Mx'!$R$20:$X$36,1,FALSE),'Dosis Mx'!$R$20:$X$36,6,FALSE),0) -> 0 | Y36: =IFERROR(VLOOKUP(VLOOKUP(E36,'Dosis Mx'!$R$37:$X$54,1,FALSE),'Dosis Mx'!$R$37:$X$54,6,FALSE),0) -> 0 | Z36: =IFERROR(VLOOKUP(VLOOKUP(E36,'Dosis Mx'!$R$55:$X$78,1,FALSE),'Dosis Mx'!$R$55:$X$78,6,FALSE),0) -> 0 | AA36: =+F36*(24/H36) -> #DIV/0!
U37: =+V37*(W37+X37+Y37+Z37) -> 0 | W37: =IFERROR(VLOOKUP(VLOOKUP(E37,'Dosis Mx'!$R$1:$X$19,1,FALSE),'Dosis Mx'!$R$1:$X$19,6,FALSE),0) -> 0 | X37: =IFERROR(VLOOKUP(VLOOKUP(E37,'Dosis Mx'!$R$20:$X$36,1,FALSE),'Dosis Mx'!$R$20:$X$36,6,FALSE),0) -> 0 | Y37: =IFERROR(VLOOKUP(VLOOKUP(E37,'Dosis Mx'!$R$37:$X$54,1,FALSE),'Dosis Mx'!$R$37:$X$54,6,FALSE),0) -> 0 | Z37: =IFERROR(VLOOKUP(VLOOKUP(E37,'Dosis Mx'!$R$55:$X$78,1,FALSE),'Dosis Mx'!$R$55:$X$78,6,FALSE),0) -> 0 | AA37: =+F37*(24/H37) -> #DIV/0!
U38: =+V38*(W38+X38+Y38+Z38) -> 0 | W38: =IFERROR(VLOOKUP(VLOOKUP(E38,'Dosis Mx'!$R$1:$X$19,1,FALSE),'Dosis Mx'!$R$1:$X$19,6,FALSE),0) -> 0 | X38: =IFERROR(VLOOKUP(VLOOKUP(E38,'Dosis Mx'!$R$20:$X$36,1,FALSE),'Dosis Mx'!$R$20:$X$36,6,FALSE),0) -> 0 | Y38: =IFERROR(VLOOKUP(VLOOKUP(E38,'Dosis Mx'!$R$37:$X$54,1,FALSE),'Dosis Mx'!$R$37:$X$54,6,FALSE),0) -> 0 | Z38: =IFERROR(VLOOKUP(VLOOKUP(E38,'Dosis Mx'!$R$55:$X$78,1,FALSE),'Dosis Mx'!$R$55:$X$78,6,FALSE),0) -> 0 | AA38: =+F38*(24/H38) -> #DIV/0!
U39: =+V39*(W39+X39+Y39+Z39) -> 0 | W39: =IFERROR(VLOOKUP(VLOOKUP(E39,'Dosis Mx'!$R$1:$X$19,1,FALSE),'Dosis Mx'!$R$1:$X$19,6,FALSE),0) -> 0 | X39: =IFERROR(VLOOKUP(VLOOKUP(E39,'Dosis Mx'!$R$20:$X$36,1,FALSE),'Dosis Mx'!$R$20:$X$36,6,FALSE),0) -> 0 | Y39: =IFERROR(VLOOKUP(VLOOKUP(E39,'Dosis Mx'!$R$37:$X$54,1,FALSE),'Dosis Mx'!$R$37:$X$54,6,FALSE),0) -> 0 | Z39: =IFERROR(VLOOKUP(VLOOKUP(E39,'Dosis Mx'!$R$55:$X$78,1,FALSE),'Dosis Mx'!$R$55:$X$78,6,FALSE),0) -> 0 | AA39: =+F39*(24/H39) -> #DIV/0!
U40: =+V40*(W40+X40+Y40+Z40) -> 0 | W40: =IFERROR(VLOOKUP(VLOOKUP(E40,'Dosis Mx'!$R$1:$X$19,1,FALSE),'Dosis Mx'!$R$1:$X$19,6,FALSE),0) -> 0 | X40: =IFERROR(VLOOKUP(VLOOKUP(E40,'Dosis Mx'!$R$20:$X$36,1,FALSE),'Dosis Mx'!$R$20:$X$36,6,FALSE),0) -> 0 | Y40: =IFERROR(VLOOKUP(VLOOKUP(E40,'Dosis Mx'!$R$37:$X$54,1,FALSE),'Dosis Mx'!$R$37:$X$54,6,FALSE),0) -> 0 | Z40: =IFERROR(VLOOKUP(VLOOKUP(E40,'Dosis Mx'!$R$55:$X$78,1,FALSE),'Dosis Mx'!$R$55:$X$78,6,FALSE),0) -> 0 | AA40: =+F40*(24/H40) -> #DIV/0!
U41: =+V41*(W41+X41+Y41+Z41) -> 0 | W41: =IFERROR(VLOOKUP(VLOOKUP(E41,'Dosis Mx'!$R$1:$X$19,1,FALSE),'Dosis Mx'!$R$1:$X$19,6,FALSE),0) -> 0 | X41: =IFERROR(VLOOKUP(VLOOKUP(E41,'Dosis Mx'!$R$20:$X$36,1,FALSE),'Dosis Mx'!$R$20:$X$36,6,FALSE),0) -> 0 | Y41: =IFERROR(VLOOKUP(VLOOKUP(E41,'Dosis Mx'!$R$37:$X$54,1,FALSE),'Dosis Mx'!$R$37:$X$54,6,FALSE),0) -> 0 | Z41: =IFERROR(VLOOKUP(VLOOKUP(E41,'Dosis Mx'!$R$55:$X$78,1,FALSE),'Dosis Mx'!$R$55:$X$78,6,FALSE),0) -> 0 | AA41: =+F41*(24/H41) -> #DIV/0!
U42: =+V42*(W42+X42+Y42+Z42) -> 0 | W42: =IFERROR(VLOOKUP(VLOOKUP(E42,'Dosis Mx'!$R$1:$X$19,1,FALSE),'Dosis Mx'!$R$1:$X$19,6,FALSE),0) -> 0 | X42: =IFERROR(VLOOKUP(VLOOKUP(E42,'Dosis Mx'!$R$20:$X$36,1,FALSE),'Dosis Mx'!$R$20:$X$36,6,FALSE),0) -> 0 | Y42: =IFERROR(VLOOKUP(VLOOKUP(E42,'Dosis Mx'!$R$37:$X$54,1,FALSE),'Dosis Mx'!$R$37:$X$54,6,FALSE),0) -> 0 | Z42: =IFERROR(VLOOKUP(VLOOKUP(E42,'Dosis Mx'!$R$55:$X$78,1,FALSE),'Dosis Mx'!$R$55:$X$78,6,FALSE),0) -> 0 | AA42: =+F42*(24/H42) -> #DIV/0!
U43: =+V43*(W43+X43+Y43+Z43) -> 0 | W43: =IFERROR(VLOOKUP(VLOOKUP(E43,'Dosis Mx'!$R$1:$X$19,1,FALSE),'Dosis Mx'!$R$1:$X$19,6,FALSE),0) -> 0 | X43: =IFERROR(VLOOKUP(VLOOKUP(E43,'Dosis Mx'!$R$20:$X$36,1,FALSE),'Dosis Mx'!$R$20:$X$36,6,FALSE),0) -> 0 | Y43: =IFERROR(VLOOKUP(VLOOKUP(E43,'Dosis Mx'!$R$37:$X$54,1,FALSE),'Dosis Mx'!$R$37:$X$54,6,FALSE),0) -> 0 | Z43: =IFERROR(VLOOKUP(VLOOKUP(E43,'Dosis Mx'!$R$55:$X$78,1,FALSE),'Dosis Mx'!$R$55:$X$78,6,FALSE),0) -> 0 | AA43: =+F43*(24/H43) -> #DIV/0!
U44: =+V44*(W44+X44+Y44+Z44) -> 0 | W44: =IFERROR(VLOOKUP(VLOOKUP(E44,'Dosis Mx'!$R$1:$X$19,1,FALSE),'Dosis Mx'!$R$1:$X$19,6,FALSE),0) -> 0 | X44: =IFERROR(VLOOKUP(VLOOKUP(E44,'Dosis Mx'!$R$20:$X$36,1,FALSE),'Dosis Mx'!$R$20:$X$36,6,FALSE),0) -> 0 | Y44: =IFERROR(VLOOKUP(VLOOKUP(E44,'Dosis Mx'!$R$37:$X$54,1,FALSE),'Dosis Mx'!$R$37:$X$54,6,FALSE),0) -> 0 | Z44: =IFERROR(VLOOKUP(VLOOKUP(E44,'Dosis Mx'!$R$55:$X$78,1,FALSE),'Dosis Mx'!$R$55:$X$78,6,FALSE),0) -> 0 | AA44: =+F44*(24/H44) -> #DIV/0!
U45: =+V45*(W45+X45+Y45+Z45) -> 0 | W45: =IFERROR(VLOOKUP(VLOOKUP(E45,'Dosis Mx'!$R$1:$X$19,1,FALSE),'Dosis Mx'!$R$1:$X$19,6,FALSE),0) -> 0 | X45: =IFERROR(VLOOKUP(VLOOKUP(E45,'Dosis Mx'!$R$20:$X$36,1,FALSE),'Dosis Mx'!$R$20:$X$36,6,FALSE),0) -> 0 | Y45: =IFERROR(VLOOKUP(VLOOKUP(E45,'Dosis Mx'!$R$37:$X$54,1,FALSE),'Dosis Mx'!$R$37:$X$54,6,FALSE),0) -> 0 | Z45: =IFERROR(VLOOKUP(VLOOKUP(E45,'Dosis Mx'!$R$55:$X$78,1,FALSE),'Dosis Mx'!$R$55:$X$78,6,FALSE),0) -> 0 | AA45: =+F45*(24/H45) -> #DIV/0!
U46: =+V46*(W46+X46+Y46+Z46) -> 0 | W46: =IFERROR(VLOOKUP(VLOOKUP(E46,'Dosis Mx'!$R$1:$X$19,1,FALSE),'Dosis Mx'!$R$1:$X$19,6,FALSE),0) -> 0 | X46: =IFERROR(VLOOKUP(VLOOKUP(E46,'Dosis Mx'!$R$20:$X$36,1,FALSE),'Dosis Mx'!$R$20:$X$36,6,FALSE),0) -> 0 | Y46: =IFERROR(VLOOKUP(VLOOKUP(E46,'Dosis Mx'!$R$37:$X$54,1,FALSE),'Dosis Mx'!$R$37:$X$54,6,FALSE),0) -> 0 | Z46: =IFERROR(VLOOKUP(VLOOKUP(E46,'Dosis Mx'!$R$55:$X$78,1,FALSE),'Dosis Mx'!$R$55:$X$78,6,FALSE),0) -> 0 | AA46: =+F46*(24/H46) -> #DIV/0!
... U63: =+V63*(W63+X63+Y63+Z63) -> 0 | W63: =IFERROR(VLOOKUP(VLOOKUP(E63,'Dosis Mx'!$R$1:$X$19,1,FALSE),'Dosis Mx'!$R$1:$X$19,6,FALSE),0) -> 0 | X63: =IFERROR(VLOOKUP(VLOOKUP(E63,'Dosis Mx'!$R$20:$X$36,1,FALSE),'Dosis Mx'!$R$20:$X$36,6,FALSE),0) -> 0 | Y63: =IFERROR(VLOOKUP(VLOOKUP(E63,'Dosis Mx'!$R$37:$X$54,1,FALSE),'Dosis Mx'!$R$37:$X$54,6,FALSE),0) -> 0 | Z63: =IFERROR(VLOOKUP(VLOOKUP(E63,'Dosis Mx'!$R$55:$X$78,1,FALSE),'Dosis Mx'!$R$55:$X$78,6,FALSE),0) -> 0 | AA63: =+F63*(24/H63) -> #DIV/0!

Sheet 17-10-2023
B1: FECHA | C1: 45216
A2: No | B2: Servicio | C2: Docidentidad | D2: Usuario | E2: Nombre | F2: Dosis | G2: Medidadosis | H2: Frecuencia | I2: Unidadfrecuencia | J2: Tto Empirico | K2: Tto Dirigido | L2: cultivo | M2: Suspender | N2: Cambiar | R2: Observacionesorden | S2: Codigo Diagnostico | T2: Diagnostico | U2: Dosis | V2: Peso(kg) | W2: ITU | X2: ITB | Y2: NEUMONIA | Z2: MENINGITIS | AA2: Dosis recetada
N3: Escalar | O3: Desescalar | P3: RXN adversa | Q3: Por dosis
A4: 1 | B4: 601-3 | C4: 1023547489 | D4: MARIANTONIA BURITICA RESTREPO | E4: AMPIcilina (Sal Sodica) x 1000 mg Polvo para Inyeccion | F4: 850 | G4: MG | H4: 6 | I4: H | S4: E86X | T4: DEPLECION DEL VOLUMEN | U4: =+V4*(W4+X4+Y4+Z4) -> 8010 | V4: 17.8 | W4: =IFERROR(VLOOKUP(VLOOKUP(E4,'Dosis Mx'!$R$1:$X$19,1,FALSE),'Dosis Mx'!$R$1:$X$19,6,FALSE),0) -> 0 | X4: =IFERROR(VLOOKUP(VLOOKUP(E4,'Dosis Mx'!$R$20:$X$36,1,FALSE),'Dosis Mx'!$R$20:$X$36,6,FALSE),0) -> 0 | Y4: =IFERROR(VLOOKUP(VLOOKUP(E4,'Dosis Mx'!$R$37:$X$54,1,FALSE),'Dosis Mx'!$R$37:$X$54,6,FALSE),0) -> 200 | Z4: =IFERROR(VLOOKUP(VLOOKUP(E4,'Dosis Mx'!$R$55:$X$78,1,FALSE),'Dosis Mx'!$R$55:$X$78,6,FALSE),0) -> 250 | AA4: =+F4*(24/H4) -> 3400 | AB4: 5
A5: 2 | B5: 601-6 | C5: 1037676780 | D5: MARIA ANTONIA HENAO FONNEGRA | E5: Ceftriaxona (Sal Sodica) 1000 mg Polvo para Inyeccion | F5: 180 | G5: MG | H5: 12 | I5: H | S5: J219 | T5: BRONQUIOLITIS AGUDA, NO ESPECIFICADA | U5: =+V5*(W5+X5+Y5+Z5) -> 1425 | V5: 3 | W5: =IFERROR(VLOOKUP(VLOOKUP(E5,'Dosis Mx'!$R$1:$X$19,1,FALSE),'Dosis Mx'!$R$1:$X$19,6,FALSE),0) -> 300 | X5: =IFERROR(VLOOKUP(VLOOKUP(E5,'Dosis Mx'!$R$20:$X$36,1,FALSE),'Dosis Mx'!$R$20:$X$36,6,FALSE),0) -> 0 | Y5: =IFERROR(VLOOKUP(VLOOKUP(E5,'Dosis Mx'!$R$37:$X$54,1,FALSE),'Dosis Mx'!$R$37:$X$54,6,FALSE),0) -> 75 | Z5: =IFERROR(VLOOKUP(VLOOKUP(E5,'Dosis Mx'!$R$55:$X$78,1,FALSE),'Dosis Mx'!$R$55:$X$78,6,FALSE),0) -> 100 | AA5: =+F5*(24/H5) -> 360 | AB5: 6
A6: 3 | B6: 602-1 | C6: 1037505755 | D6: MARIANGEL SOSA ISAZA | E6: AMPIcilina (Sal Sodica) x 1000 mg Polvo para Inyeccion | F6: 390 | G6: MG | H6: 6 | I6: H | S6: J159 | T6: NEUMONIA BACTERIANA, NO ESPECIFICADA | U6: =+V6*(W6+X6+Y6+Z6) -> 3510 | V6: 7.8 | W6: =IFERROR(VLOOKUP(VLOOKUP(E6,'Dosis Mx'!$R$1:$X$19,1,FALSE),'Dosis Mx'!$R$1:$X$19,6,FALSE),0) -> 0 | X6: =IFERROR(VLOOKUP(VLOOKUP(E6,'Dosis Mx'!$R$20:$X$36,1,FALSE),'Dosis Mx'!$R$20:$X$36,6,FALSE),0) -> 0 | Y6: =IFERROR(VLOOKUP(VLOOKUP(E6,'Dosis Mx'!$R$37:$X$54,1,FALSE),'Dosis Mx'!$R$37:$X$54,6,FALSE),0) -> 200 | Z6: =IFERROR(VLOOKUP(VLOOKUP(E6,'Dosis Mx'!$R$55:$X$78,1,FALSE),'Dosis Mx'!$R$55:$X$78,6,FALSE),0) -> 250 | AA6: =+F6*(24/H6) -> 1560 | AB6: 7
A7: 4 | B7: 603-5 | C7: 1038145231 | D7: MARTIN ALEJANDRO LONDOÑO JARAMILLO | E7: Clindamicina (Fosfato) 600 mg /4ml Solucion Inyectable | F7: 160 | G7: MG | H7: 6 | I7: H | S7: R599 | T7: ADENOMEGALIA, NO ESPECIFICADA | U7: =+V7*(W7+X7+Y7+Z7) -> 720 | V7: 16 | W7: =IFERROR(VLOOKUP(VLOOKUP(E7,'Dosis Mx'!$R$1:$X$19,1,FALSE),'Dosis Mx'!$R$1:$X$19,6,FALSE),0) -> 0 | X7: =IFERROR(VLOOKUP(VLOOKUP(E7,'Dosis Mx'!$R$20:$X$36,1,FALSE),'Dosis Mx'!$R$20:$X$36,6,FALSE),0) -> 10 | Y7: =IFERROR(VLOOKUP(VLOOKUP(E7,'Dosis Mx'!$R$37:$X$54,1,FALSE),'Dosis Mx'!$R$37:$X$54,6,FALSE),0) -> 35 | Z7: =IFERROR(VLOOKUP(VLOOKUP(E7,'Dosis Mx'!$R$55:$X$78,1,FALSE),'Dosis Mx'!$R$55:$X$78,6,FALSE),0) -> 0 | AA7: =+F7*(24/H7) -> 640 | AB7: UCI
A8: 5 | B8: 604-4 | C8: 1027815922 | D8: ASHLEY MEDINA VINASCO | E8: AZITromicina200mg/5 ml (4%)Polvo para reconstituirx15ml | F8: 110 | G8: MG | H8: 24 | I8: H | S8: J129 | T8: NEUMONIA VIRAL, NO ESPECIFICADA | U8: =+V8*(W8+X8+Y8+Z8) -> 82.5 | V8: 11 | W8: =IFERROR(VLOOKUP(VLOOKUP(E8,'Dosis Mx'!$R$1:$X$19,1,FALSE),'Dosis Mx'!$R$1:$X$19,6,FALSE),0) -> 0 | X8: =IFERROR(VLOOKUP(VLOOKUP(E8,'Dosis Mx'!$R$20:$X$36,1,FALSE),'Dosis Mx'!$R$20:$X$36,6,FALSE),0) -> 0 | Y8: =IFERROR(VLOOKUP(VLOOKUP(E8,'Dosis Mx'!$R$37:$X$54,1,FALSE),'Dosis Mx'!$R$37:$X$54,6,FALSE),0) -> 7.5 | Z8: =IFERROR(VLOOKUP(VLOOKUP(E8,'Dosis Mx'!$R$55:$X$78,1,FALSE),'Dosis Mx'!$R$55:$X$78,6,FALSE),0) -> 0 | AA8: =+F8*(24/H8) -> 110 | AB8: URGENCIAS
A9: 6 | B9: 606-1 | C9: 1077652699 | D9: HEINNI KARINA CHAMARRA OBISPO | E9: AMPIcilina Sodica/SULBactam Sodico 1000/500mg Polvo para iny (Ped) | F9: 250 | G9: MG | H9: 6 | I9: H | S9: Q250 | T9: CONDUCTO ARTERIOSO PERSISTENTE | U9: =+V9*(W9+X9+Y9+Z9) -> 1040 | V9: 5.2 | W9: =IFERROR(VLOOKUP(VLOOKUP(E9,'Dosis Mx'!$R$1:$X$19,1,FALSE),'Dosis Mx'!$R$1:$X$19,6,FALSE),0) -> 0 | X9: =IFERROR(VLOOKUP(VLOOKUP(E9,'Dosis Mx'!$R$20:$X$36,1,FALSE),'Dosis Mx'!$R$20:$X$36,6,FALSE),0) -> 0 | Y9: =IFERROR(VLOOKUP(VLOOKUP(E9,'Dosis Mx'!$R$37:$X$54,1,FALSE),'Dosis Mx'!$R$37:$X$54,6,FALSE),0) -> 200 | Z9: =IFERROR(VLOOKUP(VLOOKUP(E9,'Dosis Mx'!$R$55:$X$78,1,FALSE),'Dosis Mx'!$R$55:$X$78,6,FALSE),0) -> 0 | AA9: =+F9*(24/H9) -> 1000
A10: 7 | B10: 606-2 | C10: 1013370693 | D10: JERONIMO VELEZ ARENAS | E10: AMPIcilina Sodica/SULBactam Sodico 1000/500mg Polvo para iny (Ped) | F10: 1000 | G10: MG | H10: 6 | I10: H | S10: J22X | T10: INFECCION AGUDA NO ESPECIFICADA DE LAS VIAS RESPIRATORIAS INFERIORES | U10: =+V10*(W10+X10+Y10+Z10) -> 3560 | V10: 17.8 | W10: =IFERROR(VLOOKUP(VLOOKUP(E10,'Dosis Mx'!$R$1:$X$19,1,FALSE),'Dosis Mx'!$R$1:$X$19,6,FALSE),0) -> 0 | X10: =IFERROR(VLOOKUP(VLOOKUP(E10,'Dosis Mx'!$R$20:$X$36,1,FALSE),'Dosis Mx'!$R$20:$X$36,6,FALSE),0) -> 0 | Y10: =IFERROR(VLOOKUP(VLOOKUP(E10,'Dosis Mx'!$R$37:$X$54,1,FALSE),'Dosis Mx'!$R$37:$X$54,6,FALSE),0) -> 200 | Z10: =IFERROR(VLOOKUP(VLOOKUP(E10,'Dosis Mx'!$R$55:$X$78,1,FALSE),'Dosis Mx'!$R$55:$X$78,6,FALSE),0) -> 0 | AA10: =+F10*(24/H10) -> 4000
A11: 8 | B11: Obs 10 | C11: 1033206498 | D11: ALAN ZAID CORREA ECHEVERRY | E11: AMPIcilina Sodica/SULBactam Sodico 1000/500mg Polvo para iny (Ped) | F11: 900 | G11: MG | H11: 6 | I11: H | S11: J459 | T11: ASMA, NO ESPECIFICADO | U11: =+V11*(W11+X11+Y11+Z11) -> 2400 | V11: 12 | W11: =IFERROR(VLOOKUP(VLOOKUP(E11,'Dosis Mx'!$R$1:$X$19,1,FALSE),'Dosis Mx'!$R$1:$X$19,6,FALSE),0) -> 0 | X11: =IFERROR(VLOOKUP(VLOOKUP(E11,'Dosis Mx'!$R$20:$X$36,1,FALSE),'Dosis Mx'!$R$20:$X$36,6,FALSE),0) -> 0 | Y11: =IFERROR(VLOOKUP(VLOOKUP(E11,'Dosis Mx'!$R$37:$X$54,1,FALSE),'Dosis Mx'!$R$37:$X$54,6,FALSE),0) -> 200 | Z11: =IFERROR(VLOOKUP(VLOOKUP(E11,'Dosis Mx'!$R$55:$X$78,1,FALSE),'Dosis Mx'!$R$55:$X$78,6,FALSE),0) -> 0 | AA11: =+F11*(24/H11) -> 3600
A12: 9 | B12: S2 Silla 4 | C12: 1023662936 | D12: EMILIANO CARDONA MONTES | E12: AMPIcilina 500 mg Polvo para Inyeccion | F12: 490 | G12: MG | H12: 6 | I12: H | S12: H650 | T12: OTITIS MEDIA AGUDA SEROSA | U12: =+V12*(W12+X12+Y12+Z12) -> 4770 | V12: 10.6 | W12: =IFERROR(VLOOKUP(VLOOKUP(E12,'Dosis Mx'!$R$1:$X$19,1,FALSE),'Dosis Mx'!$R$1:$X$19,6,FALSE),0) -> 0 | X12: =IFERROR(VLOOKUP(VLOOKUP(E12,'Dosis Mx'!$R$20:$X$36,1,FALSE),'Dosis Mx'!$R$20:$X$36,6,FALSE),0) -> 0 | Y12: =IFERROR(VLOOKUP(VLOOKUP(E12,'Dosis Mx'!$R$37:$X$54,1,FALSE),'Dosis Mx'!$R$37:$X$54,6,FALSE),0) -> 200 | Z12: =IFERROR(VLOOKUP(VLOOKUP(E12,'Dosis Mx'!$R$55:$X$78,1,FALSE),'Dosis Mx'!$R$55:$X$78,6,FALSE),0) -> 250 | AA12: =+F12*(24/H12) -> 1960
A13: 10 | B13: S3 Silla12 | C13: 1017255324 | D13: SAMANTHA VALENTINA CARMONA GARCIA | E13: Cefazolina 1000 mg Polvo para Inyeccion | F13: 700 | G13: MG | H13: 8 | I13: H | S13: S925 | T13: FRACTURA DE LOS HUESOS DE OTRO(S) DEDO(S) DEL PIE | U13: =+V13*(W13+X13+Y13+Z13) -> 2700 | V13: 27 | W13: =IFERROR(VLOOKUP(VLOOKUP(E13,'Dosis Mx'!$R$1:$X$19,1,FALSE),'Dosis Mx'!$R$1:$X$19,6,FALSE),0) -> 0 | X13: =IFERROR(VLOOKUP(VLOOKUP(E13,'Dosis Mx'!$R$20:$X$36,1,FALSE),'Dosis Mx'!$R$20:$X$36,6,FALSE),0) -> 100 | Y13: =IFERROR(VLOOKUP(VLOOKUP(E13,'Dosis Mx'!$R$37:$X$54,1,FALSE),'Dosis Mx'!$R$37:$X$54,6,FALSE),0) -> 0 | Z13: =IFERROR(VLOOKUP(VLOOKUP(E13,'Dosis Mx'!$R$55:$X$78,1,FALSE),'Dosis Mx'!$R$55:$X$78,6,FALSE),0) -> 0 | AA13: =+F13*(24/H13) -> 2100
A14: 11 | B14: UCE 02 | C14: 1032027895 | D14: JUAN ANDRES PATIÑO ROLDAN | E14: AZITromicina 500 mg Tableta | F14: 500 | G14: MG | H14: 24 | I14: H | S14: J46X | T14: ESTADO ASMATICO | U14: =+V14*(W14+X14+Y14+Z14) -> 412.5 | V14: 55 | W14: =IFERROR(VLOOKUP(VLOOKUP(E14,'Dosis Mx'!$R$1:$X$19,1,FALSE),'Dosis Mx'!$R$1:$X$19,6,FALSE),0) -> 0 | X14: =IFERROR(VLOOKUP(VLOOKUP(E14,'Dosis Mx'!$R$20:$X$36,1,FALSE),'Dosis Mx'!$R$20:$X$36,6,FALSE),0) -> 0 | Y14: =IFERROR(VLOOKUP(VLOOKUP(E14,'Dosis Mx'!$R$37:$X$54,1,FALSE),'Dosis Mx'!$R$37:$X$54,6,FALSE),0) -> 7.5 | Z14: =IFERROR(VLOOKUP(VLOOKUP(E14,'Dosis Mx'!$R$55:$X$78,1,FALSE),'Dosis Mx'!$R$55:$X$78,6,FALSE),0) -> 0 | AA14: =+F14*(24/H14) -> 500
A15: 12 | B15: UCE 04 | C15: 1037138346 | D15: ISABELLA MANCO LUNA | E15: Cefepime 1000 mg Polvo para inyeccion | F15: 150 | G15: MG | H15: 8 | I15: H | S15: J219 | T15: BRONQUIOLITIS AGUDA, NO ESPECIFICADA | U15: =+V15*(W15+X15+Y15+Z15) -> 792 | V15: 3.3 | W15: =IFERROR(VLOOKUP(VLOOKUP(E15,'Dosis Mx'!$R$1:$X$19,1,FALSE),'Dosis Mx'!$R$1:$X$19,6,FALSE),0) -> 90 | X15: =IFERROR(VLOOKUP(VLOOKUP(E15,'Dosis Mx'!$R$20:$X$36,1,FALSE),'Dosis Mx'!$R$20:$X$36,6,FALSE),0) -> 0 | Y15: =IFERROR(VLOOKUP(VLOOKUP(E15,'Dosis Mx'!$R$37:$X$54,1,FALSE),'Dosis Mx'!$R$37:$X$54,6,FALSE),0) -> 0 | Z15: =IFERROR(VLOOKUP(VLOOKUP(E15,'Dosis Mx'!$R$55:$X$78,1,FALSE),'Dosis Mx'!$R$55:$X$78,6,FALSE),0) -> 150 | AA15: =+F15*(24/H15) -> 450
A16: 13 | B16: UCE 05 | C16: 1040808764 | D16: YOBANIEL DAVID DOMICO PERNIA | E16: Vancomicina (Clorhidrato) 500 mg Polvo para Inyeccion | F16: 60 | G16: MG | H16: 6 | I16: H | S16: B86X | T16: ESCABIOSIS | U16: =+V16*(W16+X16+Y16+Z16) -> 792 | V16: 4.4 | W16: =IFERROR(VLOOKUP(VLOOKUP(E16,'Dosis Mx'!$R$1:$X$19,1,FALSE),'Dosis Mx'!$R$1:$X$19,6,FALSE),0) -> 0 | X16: =IFERROR(VLOOKUP(VLOOKUP(E16,'Dosis Mx'!$R$20:$X$36,1,FALSE),'Dosis Mx'!$R$20:$X$36,6,FALSE),0) -> 60 | Y16: =IFERROR(VLOOKUP(VLOOKUP(E16,'Dosis Mx'!$R$37:$X$54,1,FALSE),'Dosis Mx'!$R$37:$X$54,6,FALSE),0) -> 60 | Z16: =IFERROR(VLOOKUP(VLOOKUP(E16,'Dosis Mx'!$R$55:$X$78,1,FALSE),'Dosis Mx'!$R$55:$X$78,6,FALSE),0) -> 60 | AA16: =+F16*(24/H16) -> 240
A17: 14 | B17: UCI 06 | C17: 1078474669 | D17: CATALINA GONZALEZ TUNAY | E17: Cefepime 1000 mg Polvo para inyeccion | F17: 300 | G17: MG | H17: 8 | I17: H | S17: J158 | T17: OTRAS NEUMONIAS BACTERIANAS | U17: =+V17*(W17+X17+Y17+Z17) -> 1536 | V17: 6.4 | W17: =IFERROR(VLOOKUP(VLOOKUP(E17,'Dosis Mx'!$R$1:$X$19,1,FALSE),'Dosis Mx'!$R$1:$X$19,6,FALSE),0) -> 90 | X17: =IFERROR(VLOOKUP(VLOOKUP(E17,'Dosis Mx'!$R$20:$X$36,1,FALSE),'Dosis Mx'!$R$20:$X$36,6,FALSE),0) -> 0 | Y17: =IFERROR(VLOOKUP(VLOOKUP(E17,'Dosis Mx'!$R$37:$X$54,1,FALSE),'Dosis Mx'!$R$37:$X$54,6,FALSE),0) -> 0 | Z17: =IFERROR(VLOOKUP(VLOOKUP(E17,'Dosis Mx'!$R$55:$X$78,1,FALSE),'Dosis Mx'!$R$55:$X$78,6,FALSE),0) -> 150 | AA17: =+F17*(24/H17) -> 900
A18: 15 | B18: UCI 07 | C18: 1033207665 | D18: SAMUEL GARCIA JARAMILLO | E18: Cefepime 1000 mg Polvo para inyeccion | F18: 200 | G18: MG | H18: 8 | I18: H | S18: J219 | T18: BRONQUIOLITIS AGUDA, NO ESPECIFICADA | U18: =+V18*(W18+X18+Y18+Z18) -> 854.4 | V18: 3.56 | W18: =IFERROR(VLOOKUP(VLOOKUP(E18,'Dosis Mx'!$R$1:$X$19,1,FALSE),'Dosis Mx'!$R$1:$X$19,6,FALSE),0) -> 90 | X18: =IFERROR(VLOOKUP(VLOOKUP(E18,'Dosis Mx'!$R$20:$X$36,1,FALSE),'Dosis Mx'!$R$20:$X$36,6,FALSE),0) -> 0 | Y18: =IFERROR(VLOOKUP(VLOOKUP(E18,'Dosis Mx'!$R$37:$X$54,1,FALSE),'Dosis Mx'!$R$37:$X$54,6,FALSE),0) -> 0 | Z18: =IFERROR(VLOOKUP(VLOOKUP(E18,'Dosis Mx'!$R$55:$X$78,1,FALSE),'Dosis Mx'!$R$55:$X$78,6,FALSE),0) -> 150 | AA18: =+F18*(24/H18) -> 600
A19: 16 | U19: =+V19*(W19+X19+Y19+Z19) -> 0 | W19: =IFERROR(VLOOKUP(VLOOKUP(E19,'Dosis Mx'!$R$1:$X$19,1,FALSE),'Dosis Mx'!$R$1:$X$19,6,FALSE),0) -> 0 | X19: =IFERROR(VLOOKUP(VLOOKUP(E19,'Dosis Mx'!$R$20:$X$36,1,FALSE),'Dosis Mx'!$R$20:$X$36,6,FALSE),0) -> 0 | Y19: =IFERROR(VLOOKUP(VLOOKUP(E19,'Dosis Mx'!$R$37:$X$54,1,FALSE),'Dosis Mx'!$R$37:$X$54,6,FALSE),0) -> 0 | Z19: =IFERROR(VLOOKUP(VLOOKUP(E19,'Dosis Mx'!$R$55:$X$78,1,FALSE),'Dosis Mx'!$R$55:$X$78,6,FALSE),0) -> 0 | AA19: =+F19*(24/H19) -> #DIV/0!
A20: 17 | U20: =+V20*(W20+X20+Y20+Z20) -> 0 | W20: =IFERROR(VLOOKUP(VLOOKUP(E20,'Dosis Mx'!$R$1:$X$19,1,FALSE),'Dosis Mx'!$R$1:$X$19,6,FALSE),0) -> 0 | X20: =IFERROR(VLOOKUP(VLOOKUP(E20,'Dosis Mx'!$R$20:$X$36,1,FALSE),'Dosis Mx'!$R$20:$X$36,6,FALSE),0) -> 0 | Y20: =IFERROR(VLOOKUP(VLOOKUP(E20,'Dosis Mx'!$R$37:$X$54,1,FALSE),'Dosis Mx'!$R$37:$X$54,6,FALSE),0) -> 0 | Z20: =IFERROR(VLOOKUP(VLOOKUP(E20,'Dosis Mx'!$R$55:$X$78,1,FALSE),'Dosis Mx'!$R$55:$X$78,6,FALSE),0) -> 0 | AA20: =+F20*(24/H20) -> #DIV/0!
A21: 18 | U21: =+V21*(W21+X21+Y21+Z21) -> 0 | W21: =IFERROR(VLOOKUP(VLOOKUP(E21,'Dosis Mx'!$R$1:$X$19,1,FALSE),'Dosis Mx'!$R$1:$X$19,6,FALSE),0) -> 0 | X21: =IFERROR(VLOOKUP(VLOOKUP(E21,'Dosis Mx'!$R$20:$X$36,1,FALSE),'Dosis Mx'!$R$20:$X$36,6,FALSE),0) -> 0 | Y21: =IFERROR(VLOOKUP(VLOOKUP(E21,'Dosis Mx'!$R$37:$X$54,1,FALSE),'Dosis Mx'!$R$37:$X$54,6,FALSE),0) -> 0 | Z21: =IFERROR(VLOOKUP(VLOOKUP(E21,'Dosis Mx'!$R$55:$X$78,1,FALSE),'Dosis Mx'!$R$55:$X$78,6,FALSE),0) -> 0 | AA21: =+F21*(24/H21) -> #DIV/0!
A22: 19 | U22: =+V22*(W22+X22+Y22+Z22) -> 0 | W22: =IFERROR(VLOOKUP(VLOOKUP(E22,'Dosis Mx'!$R$1:$X$19,1,FALSE),'Dosis Mx'!$R$1:$X$19,6,FALSE),0) -> 0 | X22: =IFERROR(VLOOKUP(VLOOKUP(E22,'Dosis Mx'!$R$20:$X$36,1,FALSE),'Dosis Mx'!$R$20:$X$36,6,FALSE),0) -> 0 | Y22: =IFERROR(VLOOKUP(VLOOKUP(E22,'Dosis Mx'!$R$37:$X$54,1,FALSE),'Dosis Mx'!$R$37:$X$54,6,FALSE),0) -> 0 | Z22: =IFERROR(VLOOKUP(VLOOKUP(E22,'Dosis Mx'!$R$55:$X$78,1,FALSE),'Dosis Mx'!$R$55:$X$78,6,FALSE),0) -> 0 | AA22: =+F22*(24/H22) -> #DIV/0!
A23: 20 | U23: =+V23*(W23+X23+Y23+Z23) -> 0 | W23: =IFERROR(VLOOKUP(VLOOKUP(E23,'Dosis Mx'!$R$1:$X$19,1,FALSE),'Dosis Mx'!$R$1:$X$19,6,FALSE),0) -> 0 | X23: =IFERROR(VLOOKUP(VLOOKUP(E23,'Dosis Mx'!$R$20:$X$36,1,FALSE),'Dosis Mx'!$R$20:$X$36,6,FALSE),0) -> 0 | Y23: =IFERROR(VLOOKUP(VLOOKUP(E23,'Dosis Mx'!$R$37:$X$54,1,FALSE),'Dosis Mx'!$R$37:$X$54,6,FALSE),0) -> 0 | Z23: =IFERROR(VLOOKUP(VLOOKUP(E23,'Dosis Mx'!$R$55:$X$78,1,FALSE),'Dosis Mx'!$R$55:$X$78,6,FALSE),0) -> 0 | AA23: =+F23*(24/H23) -> #DIV/0!
A24: 21 | U24: =+V24*(W24+X24+Y24+Z24) -> 0 | W24: =IFERROR(VLOOKUP(VLOOKUP(E24,'Dosis Mx'!$R$1:$X$19,1,FALSE),'Dosis Mx'!$R$1:$X$19,6,FALSE),0) -> 0 | X24: =IFERROR(VLOOKUP(VLOOKUP(E24,'Dosis Mx'!$R$20:$X$36,1,FALSE),'Dosis Mx'!$R$20:$X$36,6,FALSE),0) -> 0 | Y24: =IFERROR(VLOOKUP(VLOOKUP(E24,'Dosis Mx'!$R$37:$X$54,1,FALSE),'Dosis Mx'!$R$37:$X$54,6,FALSE),0) -> 0 | Z24: =IFERROR(VLOOKUP(VLOOKUP(E24,'Dosis Mx'!$R$55:$X$78,1,FALSE),'Dosis Mx'!$R$55:$X$78,6,FALSE),0) -> 0 | AA24: =+F24*(24/H24) -> #DIV/0!
A25: 22 | U25: =+V25*(W25+X25+Y25+Z25) -> 0 | W25: =IFERROR(VLOOKUP(VLOOKUP(E25,'Dosis Mx'!$R$1:$X$19,1,FALSE),'Dosis Mx'!$R$1:$X$19,6,FALSE),0) -> 0 | X25: =IFERROR(VLOOKUP(VLOOKUP(E25,'Dosis Mx'!$R$20:$X$36,1,FALSE),'Dosis Mx'!$R$20:$X$36,6,FALSE),0) -> 0 | Y25: =IFERROR(VLOOKUP(VLOOKUP(E25,'Dosis Mx'!$R$37:$X$54,1,FALSE),'Dosis Mx'!$R$37:$X$54,6,FALSE),0) -> 0 | Z25: =IFERROR(VLOOKUP(VLOOKUP(E25,'Dosis Mx'!$R$55:$X$78,1,FALSE),'Dosis Mx'!$R$55:$X$78,6,FALSE),0) -> 0 | AA25: =+F25*(24/H25) -> #DIV/0!
A26: 23 | U26: =+V26*(W26+X26+Y26+Z26) -> 0 | W26: =IFERROR(VLOOKUP(VLOOKUP(E26,'Dosis Mx'!$R$1:$X$19,1,FALSE),'Dosis Mx'!$R$1:$X$19,6,FALSE),0) -> 0 | X26: =IFERROR(VLOOKUP(VLOOKUP(E26,'Dosis Mx'!$R$20:$X$36,1,FALSE),'Dosis Mx'!$R$20:$X$36,6,FALSE),0) -> 0 | Y26: =IFERROR(VLOOKUP(VLOOKUP(E26,'Dosis Mx'!$R$37:$X$54,1,FALSE),'Dosis Mx'!$R$37:$X$54,6,FALSE),0) -> 0 | Z26: =IFERROR(VLOOKUP(VLOOKUP(E26,'Dosis Mx'!$R$55:$X$78,1,FALSE),'Dosis Mx'!$R$55:$X$78,6,FALSE),0) -> 0 | AA26: =+F26*(24/H26) -> #DIV/0!
A27: 24 | U27: =+V27*(W27+X27+Y27+Z27) -> 0 | W27: =IFERROR(VLOOKUP(VLOOKUP(E27,'Dosis Mx'!$R$1:$X$19,1,FALSE),'Dosis Mx'!$R$1:$X$19,6,FALSE),0) -> 0 | X27: =IFERROR(VLOOKUP(VLOOKUP(E27,'Dosis Mx'!$R$20:$X$36,1,FALSE),'Dosis Mx'!$R$20:$X$36,6,FALSE),0) -> 0 | Y27: =IFERROR(VLOOKUP(VLOOKUP(E27,'Dosis Mx'!$R$37:$X$54,1,FALSE),'Dosis Mx'!$R$37:$X$54,6,FALSE),0) -> 0 | Z27: =IFERROR(VLOOKUP(VLOOKUP(E27,'Dosis Mx'!$R$55:$X$78,1,FALSE),'Dosis Mx'!$R$55:$X$78,6,FALSE),0) -> 0 | AA27: =+F27*(24/H27) -> #DIV/0!
A28: 25 | U28: =+V28*(W28+X28+Y28+Z28) -> 0 | W28: =IFERROR(VLOOKUP(VLOOKUP(E28,'Dosis Mx'!$R$1:$X$19,1,FALSE),'Dosis Mx'!$R$1:$X$19,6,FALSE),0) -> 0 | X28: =IFERROR(VLOOKUP(VLOOKUP(E28,'Dosis Mx'!$R$20:$X$36,1,FALSE),'Dosis Mx'!$R$20:$X$36,6,FALSE),0) -> 0 | Y28: =IFERROR(VLOOKUP(VLOOKUP(E28,'Dosis Mx'!$R$37:$X$54,1,FALSE),'Dosis Mx'!$R$37:$X$54,6,FALSE),0) -> 0 | Z28: =IFERROR(VLOOKUP(VLOOKUP(E28,'Dosis Mx'!$R$55:$X$78,1,FALSE),'Dosis Mx'!$R$55:$X$78,6,FALSE),0) -> 0 | AA28: =+F28*(24/H28) -> #DIV/0!
A29: 26 | U29: =+V29*(W29+X29+Y29+Z29) -> 0 | W29: =IFERROR(VLOOKUP(VLOOKUP(E29,'Dosis Mx'!$R$1:$X$19,1,FALSE),'Dosis Mx'!$R$1:$X$19,6,FALSE),0) -> 0 | X29: =IFERROR(VLOOKUP(VLOOKUP(E29,'Dosis Mx'!$R$20:$X$36,1,FALSE),'Dosis Mx'!$R$20:$X$36,6,FALSE),0) -> 0 | Y29: =IFERROR(VLOOKUP(VLOOKUP(E29,'Dosis Mx'!$R$37:$X$54,1,FALSE),'Dosis Mx'!$R$37:$X$54,6,FALSE),0) -> 0 | Z29: =IFERROR(VLOOKUP(VLOOKUP(E29,'Dosis Mx'!$R$55:$X$78,1,FALSE),'Dosis Mx'!$R$55:$X$78,6,FALSE),0) -> 0 | AA29: =+F29*(24/H29) -> #DIV/0!
A30: 27 | U30: =+V30*(W30+X30+Y30+Z30) -> 0 | W30: =IFERROR(VLOOKUP(VLOOKUP(E30,'Dosis Mx'!$R$1:$X$19,1,FALSE),'Dosis Mx'!$R$1:$X$19,6,FALSE),0) -> 0 | X30: =IFERROR(VLOOKUP(VLOOKUP(E30,'Dosis Mx'!$R$20:$X$36,1,FALSE),'Dosis Mx'!$R$20:$X$36,6,FALSE),0) -> 0 | Y30: =IFERROR(VLOOKUP(VLOOKUP(E30,'Dosis Mx'!$R$37:$X$54,1,FALSE),'Dosis Mx'!$R$37:$X$54,6,FALSE),0) -> 0 | Z30: =IFERROR(VLOOKUP(VLOOKUP(E30,'Dosis Mx'!$R$55:$X$78,1,FALSE),'Dosis Mx'!$R$55:$X$78,6,FALSE),0) -> 0 | AA30: =+F30*(24/H30) -> #DIV/0!
... A32: 29 | U32: =+V32*(W32+X32+Y32+Z32) -> 0 | W32: =IFERROR(VLOOKUP(VLOOKUP(E32,'Dosis Mx'!$R$1:$X$19,1,FALSE),'Dosis Mx'!$R$1:$X$19,6,FALSE),0) -> 0 | X32: =IFERROR(VLOOKUP(VLOOKUP(E32,'Dosis Mx'!$R$20:$X$36,1,FALSE),'Dosis Mx'!$R$20:$X$36,6,FALSE),0) -> 0 | Y32: =IFERROR(VLOOKUP(VLOOKUP(E32,'Dosis Mx'!$R$37:$X$54,1,FALSE),'Dosis Mx'!$R$37:$X$54,6,FALSE),0) -> 0 | Z32: =IFERROR(VLOOKUP(VLOOKUP(E32,'Dosis Mx'!$R$55:$X$78,1,FALSE),'Dosis Mx'!$R$55:$X$78,6,FALSE),0) -> 0 | AA32: =+F32*(24/H32) -> #DIV/0!
A33: No | B33: Servicio | E33: Nombre | F33: Dosis | G33: Medidadosis | H33: Frecuencia | I33: Unidadfrecuencia | J33: Tto Empirico | K33: Tto Dirigido | L33: cultivo | M33: Suspender | N33: Cambiar | R33: Observacionesorden | S33: Codigo Diagnostico | T33: Diagnostico | U33: Dosis | V33: Peso(kg) | W33: ITU | X33: ITB | Y33: NEUMONIA | Z33: MENINGITIS | AA33: Dosis recetada
N34: Escalar | O34: Desescalar | P34: RXN adversa | Q34: Por dosis
U35: =+V35*(W35+X35+Y35+Z35) -> 0 | W35: =IFERROR(VLOOKUP(VLOOKUP(E35,'Dosis Mx'!$R$1:$X$19,1,FALSE),'Dosis Mx'!$R$1:$X$19,6,FALSE),0) -> 0 | X35: =IFERROR(VLOOKUP(VLOOKUP(E35,'Dosis Mx'!$R$20:$X$36,1,FALSE),'Dosis Mx'!$R$20:$X$36,6,FALSE),0) -> 0 | Y35: =IFERROR(VLOOKUP(VLOOKUP(E35,'Dosis Mx'!$R$37:$X$54,1,FALSE),'Dosis Mx'!$R$37:$X$54,6,FALSE),0) -> 0 | Z35: =IFERROR(VLOOKUP(VLOOKUP(E35,'Dosis Mx'!$R$55:$X$78,1,FALSE),'Dosis Mx'!$R$55:$X$78,6,FALSE),0) -> 0 | AA35: =+F35*(24/H35) -> #DIV/0!
U36: =+V36*(W36+X36+Y36+Z36) -> 0 | W36: =IFERROR(VLOOKUP(VLOOKUP(E36,'Dosis Mx'!$R$1:$X$19,1,FALSE),'Dosis Mx'!$R$1:$X$19,6,FALSE),0) -> 0 | X36: =IFERROR(VLOOKUP(VLOOKUP(E36,'Dosis Mx'!$R$20:$X$36,1,FALSE),'Dosis Mx'!$R$20:$X$36,6,FALSE),0) -> 0 | Y36: =IFERROR(VLOOKUP(VLOOKUP(E36,'Dosis Mx'!$R$37:$X$54,1,FALSE),'Dosis Mx'!$R$37:$X$54,6,FALSE),0) -> 0 | Z36: =IFERROR(VLOOKUP(VLOOKUP(E36,'Dosis Mx'!$R$55:$X$78,1,FALSE),'Dosis Mx'!$R$55:$X$78,6,FALSE),0) -> 0 | AA36: =+F36*(24/H36) -> #DIV/0!
U37: =+V37*(W37+X37+Y37+Z37) -> 0 | W37: =IFERROR(VLOOKUP(VLOOKUP(E37,'Dosis Mx'!$R$1:$X$19,1,FALSE),'Dosis Mx'!$R$1:$X$19,6,FALSE),0) -> 0 | X37: =IFERROR(VLOOKUP(VLOOKUP(E37,'Dosis Mx'!$R$20:$X$36,1,FALSE),'Dosis Mx'!$R$20:$X$36,6,FALSE),0) -> 0 | Y37: =IFERROR(VLOOKUP(VLOOKUP(E37,'Dosis Mx'!$R$37:$X$54,1,FALSE),'Dosis Mx'!$R$37:$X$54,6,FALSE),0) -> 0 | Z37: =IFERROR(VLOOKUP(VLOOKUP(E37,'Dosis Mx'!$R$55:$X$78,1,FALSE),'Dosis Mx'!$R$55:$X$78,6,FALSE),0) -> 0 | AA37: =+F37*(24/H37) -> #DIV/0!
U38: =+V38*(W38+X38+Y38+Z38) -> 0 | W38: =IFERROR(VLOOKUP(VLOOKUP(E38,'Dosis Mx'!$R$1:$X$19,1,FALSE),'Dosis Mx'!$R$1:$X$19,6,FALSE),0) -> 0 | X38: =IFERROR(VLOOKUP(VLOOKUP(E38,'Dosis Mx'!$R$20:$X$36,1,FALSE),'Dosis Mx'!$R$20:$X$36,6,FALSE),0) -> 0 | Y38: =IFERROR(VLOOKUP(VLOOKUP(E38,'Dosis Mx'!$R$37:$X$54,1,FALSE),'Dosis Mx'!$R$37:$X$54,6,FALSE),0) -> 0 | Z38: =IFERROR(VLOOKUP(VLOOKUP(E38,'Dosis Mx'!$R$55:$X$78,1,FALSE),'Dosis Mx'!$R$55:$X$78,6,FALSE),0) -> 0 | AA38: =+F38*(24/H38) -> #DIV/0!
U39: =+V39*(W39+X39+Y39+Z39) -> 0 | W39: =IFERROR(VLOOKUP(VLOOKUP(E39,'Dosis Mx'!$R$1:$X$19,1,FALSE),'Dosis Mx'!$R$1:$X$19,6,FALSE),0) -> 0 | X39: =IFERROR(VLOOKUP(VLOOKUP(E39,'Dosis Mx'!$R$20:$X$36,1,FALSE),'Dosis Mx'!$R$20:$X$36,6,FALSE),0) -> 0 | Y39: =IFERROR(VLOOKUP(VLOOKUP(E39,'Dosis Mx'!$R$37:$X$54,1,FALSE),'Dosis Mx'!$R$37:$X$54,6,FALSE),0) -> 0 | Z39: =IFERROR(VLOOKUP(VLOOKUP(E39,'Dosis Mx'!$R$55:$X$78,1,FALSE),'Dosis Mx'!$R$55:$X$78,6,FALSE),0) -> 0 | AA39: =+F39*(24/H39) -> #DIV/0!
U40: =+V40*(W40+X40+Y40+Z40) -> 0 | W40: =IFERROR(VLOOKUP(VLOOKUP(E40,'Dosis Mx'!$R$1:$X$19,1,FALSE),'Dosis Mx'!$R$1:$X$19,6,FALSE),0) -> 0 | X40: =IFERROR(VLOOKUP(VLOOKUP(E40,'Dosis Mx'!$R$20:$X$36,1,FALSE),'Dosis Mx'!$R$20:$X$36,6,FALSE),0) -> 0 | Y40: =IFERROR(VLOOKUP(VLOOKUP(E40,'Dosis Mx'!$R$37:$X$54,1,FALSE),'Dosis Mx'!$R$37:$X$54,6,FALSE),0) -> 0 | Z40: =IFERROR(VLOOKUP(VLOOKUP(E40,'Dosis Mx'!$R$55:$X$78,1,FALSE),'Dosis Mx'!$R$55:$X$78,6,FALSE),0) -> 0 | AA40: =+F40*(24/H40) -> #DIV/0!
U41: =+V41*(W41+X41+Y41+Z41) -> 0 | W41: =IFERROR(VLOOKUP(VLOOKUP(E41,'Dosis Mx'!$R$1:$X$19,1,FALSE),'Dosis Mx'!$R$1:$X$19,6,FALSE),0) -> 0 | X41: =IFERROR(VLOOKUP(VLOOKUP(E41,'Dosis Mx'!$R$20:$X$36,1,FALSE),'Dosis Mx'!$R$20:$X$36,6,FALSE),0) -> 0 | Y41: =IFERROR(VLOOKUP(VLOOKUP(E41,'Dosis Mx'!$R$37:$X$54,1,FALSE),'Dosis Mx'!$R$37:$X$54,6,FALSE),0) -> 0 | Z41: =IFERROR(VLOOKUP(VLOOKUP(E41,'Dosis Mx'!$R$55:$X$78,1,FALSE),'Dosis Mx'!$R$55:$X$78,6,FALSE),0) -> 0 | AA41: =+F41*(24/H41) -> #DIV/0!
U42: =+V42*(W42+X42+Y42+Z42) -> 0 | W42: =IFERROR(VLOOKUP(VLOOKUP(E42,'Dosis Mx'!$R$1:$X$19,1,FALSE),'Dosis Mx'!$R$1:$X$19,6,FALSE),0) -> 0 | X42: =IFERROR(VLOOKUP(VLOOKUP(E42,'Dosis Mx'!$R$20:$X$36,1,FALSE),'Dosis Mx'!$R$20:$X$36,6,FALSE),0) -> 0 | Y42: =IFERROR(VLOOKUP(VLOOKUP(E42,'Dosis Mx'!$R$37:$X$54,1,FALSE),'Dosis Mx'!$R$37:$X$54,6,FALSE),0) -> 0 | Z42: =IFERROR(VLOOKUP(VLOOKUP(E42,'Dosis Mx'!$R$55:$X$78,1,FALSE),'Dosis Mx'!$R$55:$X$78,6,FALSE),0) -> 0 | AA42: =+F42*(24/H42) -> #DIV/0!
U43: =+V43*(W43+X43+Y43+Z43) -> 0 | W43: =IFERROR(VLOOKUP(VLOOKUP(E43,'Dosis Mx'!$R$1:$X$19,1,FALSE),'Dosis Mx'!$R$1:$X$19,6,FALSE),0) -> 0 | X43: =IFERROR(VLOOKUP(VLOOKUP(E43,'Dosis Mx'!$R$20:$X$36,1,FALSE),'Dosis Mx'!$R$20:$X$36,6,FALSE),0) -> 0 | Y43: =IFERROR(VLOOKUP(VLOOKUP(E43,'Dosis Mx'!$R$37:$X$54,1,FALSE),'Dosis Mx'!$R$37:$X$54,6,FALSE),0) -> 0 | Z43: =IFERROR(VLOOKUP(VLOOKUP(E43,'Dosis Mx'!$R$55:$X$78,1,FALSE),'Dosis Mx'!$R$55:$X$78,6,FALSE),0) -> 0 | AA43: =+F43*(24/H43) -> #DIV/0!
U44: =+V44*(W44+X44+Y44+Z44) -> 0 | W44: =IFERROR(VLOOKUP(VLOOKUP(E44,'Dosis Mx'!$R$1:$X$19,1,FALSE),'Dosis Mx'!$R$1:$X$19,6,FALSE),0) -> 0 | X44: =IFERROR(VLOOKUP(VLOOKUP(E44,'Dosis Mx'!$R$20:$X$36,1,FALSE),'Dosis Mx'!$R$20:$X$36,6,FALSE),0) -> 0 | Y44: =IFERROR(VLOOKUP(VLOOKUP(E44,'Dosis Mx'!$R$37:$X$54,1,FALSE),'Dosis Mx'!$R$37:$X$54,6,FALSE),0) -> 0 | Z44: =IFERROR(VLOOKUP(VLOOKUP(E44,'Dosis Mx'!$R$55:$X$78,1,FALSE),'Dosis Mx'!$R$55:$X$78,6,FALSE),0) -> 0 | AA44: =+F44*(24/H44) -> #DIV/0!
U45: =+V45*(W45+X45+Y45+Z45) -> 0 | W45: =IFERROR(VLOOKUP(VLOOKUP(E45,'Dosis Mx'!$R$1:$X$19,1,FALSE),'Dosis Mx'!$R$1:$X$19,6,FALSE),0) -> 0 | X45: =IFERROR(VLOOKUP(VLOOKUP(E45,'Dosis Mx'!$R$20:$X$36,1,FALSE),'Dosis Mx'!$R$20:$X$36,6,FALSE),0) -> 0 | Y45: =IFERROR(VLOOKUP(VLOOKUP(E45,'Dosis Mx'!$R$37:$X$54,1,FALSE),'Dosis Mx'!$R$37:$X$54,6,FALSE),0) -> 0 | Z45: =IFERROR(VLOOKUP(VLOOKUP(E45,'Dosis Mx'!$R$55:$X$78,1,FALSE),'Dosis Mx'!$R$55:$X$78,6,FALSE),0) -> 0 | AA45: =+F45*(24/H45) -> #DIV/0!
U46: =+V46*(W46+X46+Y46+Z46) -> 0 | W46: =IFERROR(VLOOKUP(VLOOKUP(E46,'Dosis Mx'!$R$1:$X$19,1,FALSE),'Dosis Mx'!$R$1:$X$19,6,FALSE),0) -> 0 | X46: =IFERROR(VLOOKUP(VLOOKUP(E46,'Dosis Mx'!$R$20:$X$36,1,FALSE),'Dosis Mx'!$R$20:$X$36,6,FALSE),0) -> 0 | Y46: =IFERROR(VLOOKUP(VLOOKUP(E46,'Dosis Mx'!$R$37:$X$54,1,FALSE),'Dosis Mx'!$R$37:$X$54,6,FALSE),0) -> 0 | Z46: =IFERROR(VLOOKUP(VLOOKUP(E46,'Dosis Mx'!$R$55:$X$78,1,FALSE),'Dosis Mx'!$R$55:$X$78,6,FALSE),0) -> 0 | AA46: =+F46*(24/H46) -> #DIV/0!
... U63: =+V63*(W63+X63+Y63+Z63) -> 0 | W63: =IFERROR(VLOOKUP(VLOOKUP(E63,'Dosis Mx'!$R$1:$X$19,1,FALSE),'Dosis Mx'!$R$1:$X$19,6,FALSE),0) -> 0 | X63: =IFERROR(VLOOKUP(VLOOKUP(E63,'Dosis Mx'!$R$20:$X$36,1,FALSE),'Dosis Mx'!$R$20:$X$36,6,FALSE),0) -> 0 | Y63: =IFERROR(VLOOKUP(VLOOKUP(E63,'Dosis Mx'!$R$37:$X$54,1,FALSE),'Dosis Mx'!$R$37:$X$54,6,FALSE),0) -> 0 | Z63: =IFERROR(VLOOKUP(VLOOKUP(E63,'Dosis Mx'!$R$55:$X$78,1,FALSE),'Dosis Mx'!$R$55:$X$78,6,FALSE),0) -> 0 | AA63: =+F63*(24/H63) -> #DIV/0!

Sheet 20-10-2023
B1: FECHA | C1: 45219
A2: No | B2: Servicio | C2: Docidentidad | D2: Usuario | E2: Nombre | F2: Dosis | G2: Medidadosis | H2: Frecuencia | I2: Unidadfrecuencia | J2: Tto Empirico | K2: Tto Dirigido | L2: cultivo | M2: Suspender | N2: Cambiar | R2: Observacionesorden | S2: Codigo Diagnostico | T2: Diagnostico | U2: Dosis | V2: Peso(kg) | W2: ITU | X2: ITB | Y2: NEUMONIA | Z2: MENINGITIS | AA2: Dosis recetada
N3: Escalar | O3: Desescalar | P3: RXN adversa | Q3: Por dosis
A4: 1 | B4: 501-2 | C4: 1018280900 | D4: AXEL EMILIANO SEGURA TORRES | E4: Cefazolina 1000 mg Polvo para Inyeccion | F4: 210 | G4: MG | H4: 6 | I4: H | S4: N390 | T4: INFECCION DE VIAS URINARIAS, SITIO NO ESPECIFICADO | U4: =+V4*(W4+X4+Y4+Z4) -> 830 | V4: 8.3 | W4: =IFERROR(VLOOKUP(VLOOKUP(E4,'Dosis Mx'!$R$1:$X$19,1,FALSE),'Dosis Mx'!$R$1:$X$19,6,FALSE),0) -> 0 | X4: =IFERROR(VLOOKUP(VLOOKUP(E4,'Dosis Mx'!$R$20:$X$36,1,FALSE),'Dosis Mx'!$R$20:$X$36,6,FALSE),0) -> 100 | Y4: =IFERROR(VLOOKUP(VLOOKUP(E4,'Dosis Mx'!$R$37:$X$54,1,FALSE),'Dosis Mx'!$R$37:$X$54,6,FALSE),0) -> 0 | Z4: =IFERROR(VLOOKUP(VLOOKUP(E4,'Dosis Mx'!$R$55:$X$78,1,FALSE),'Dosis Mx'!$R$55:$X$78,6,FALSE),0) -> 0 | AA4: =+F4*(24/H4) -> 840 | AB4: 5
A5: 2 | B5: 501-3 | C5: 1013359409 | D5: SARA CAMILA ZAPATA ATEHORTUA | E5: Clindamicina (Fosfato) 600 mg /4ml Solucion Inyectable | F5: 215 | G5: MG | H5: 6 | I5: H | S5: L030 | T5: CELULITIS DE LOS DEDOS DE LA MANO Y DEL PIE | U5: =+V5*(W5+X5+Y5+Z5) -> 967.5 | V5: 21.5 | W5: =IFERROR(VLOOKUP(VLOOKUP(E5,'Dosis Mx'!$R$1:$X$19,1,FALSE),'Dosis Mx'!$R$1:$X$19,6,FALSE),0) -> 0 | X5: =IFERROR(VLOOKUP(VLOOKUP(E5,'Dosis Mx'!$R$20:$X$36,1,FALSE),'Dosis Mx'!$R$20:$X$36,6,FALSE),0) -> 10 | Y5: =IFERROR(VLOOKUP(VLOOKUP(E5,'Dosis Mx'!$R$37:$X$54,1,FALSE),'Dosis Mx'!$R$37:$X$54,6,FALSE),0) -> 35 | Z5: =IFERROR(VLOOKUP(VLOOKUP(E5,'Dosis Mx'!$R$55:$X$78,1,FALSE),'Dosis Mx'!$R$55:$X$78,6,FALSE),0) -> 0 | AA5: =+F5*(24/H5) -> 860 | AB5: 6
A6: 3 | B6: 502-1 | C6: 1018272646 | D6: MARIENT GOMEZ GALEANO | E6: AMIKacina (Sulfato) 100 mg/2 ml Solucion Inyectable | F6: 234 | G6: MG | H6: 24 | I6: H | S6: N390 | T6: INFECCION DE VIAS URINARIAS, SITIO NO ESPECIFICADO | U6: =+V6*(W6+X6+Y6+Z6) -> 507 | V6: 15.6 | W6: =IFERROR(VLOOKUP(VLOOKUP(E6,'Dosis Mx'!$R$1:$X$19,1,FALSE),'Dosis Mx'!$R$1:$X$19,6,FALSE),0) -> 15 | X6: =IFERROR(VLOOKUP(VLOOKUP(E6,'Dosis Mx'!$R$20:$X$36,1,FALSE),'Dosis Mx'!$R$20:$X$36,6,FALSE),0) -> 0 | Y6: =IFERROR(VLOOKUP(VLOOKUP(E6,'Dosis Mx'!$R$37:$X$54,1,FALSE),'Dosis Mx'!$R$37:$X$54,6,FALSE),0) -> 0 | Z6: =IFERROR(VLOOKUP(VLOOKUP(E6,'Dosis Mx'!$R$55:$X$78,1,FALSE),'Dosis Mx'!$R$55:$X$78,6,FALSE),0) -> 17.5 | AA6: =+F6*(24/H6) -> 234 | AB6: 7
A7: 4 | B7: 502-3 | C7: 1025777037 | D7: ADHARA MEDINA DURANGO | E7: AMIKacina (Sulfato) 100 mg/2 ml Solucion Inyectable | F7: 75 | G7: MG | H7: 24 | I7: H | S7: R509 | T7: FIEBRE, NO ESPECIFICADA | U7: =+V7*(W7+X7+Y7+Z7) -> 159.25 | V7: 4.9 | W7: =IFERROR(VLOOKUP(VLOOKUP(E7,'Dosis Mx'!$R$1:$X$19,1,FALSE),'Dosis Mx'!$R$1:$X$19,6,FALSE),0) -> 15 | X7: =IFERROR(VLOOKUP(VLOOKUP(E7,'Dosis Mx'!$R$20:$X$36,1,FALSE),'Dosis Mx'!$R$20:$X$36,6,FALSE),0) -> 0 | Y7: =IFERROR(VLOOKUP(VLOOKUP(E7,'Dosis Mx'!$R$37:$X$54,1,FALSE),'Dosis Mx'!$R$37:$X$54,6,FALSE),0) -> 0 | Z7: =IFERROR(VLOOKUP(VLOOKUP(E7,'Dosis Mx'!$R$55:$X$78,1,FALSE),'Dosis Mx'!$R$55:$X$78,6,FALSE),0) -> 17.5 | AA7: =+F7*(24/H7) -> 75 | AB7: UCI
A8: 5 | B8: 503-3 | C8: 1013380007 | D8: GABRIELA ROLDAN TORRES | E8: AMIKacina (Sulfato) 100 mg/2 ml Solucion Inyectable | F8: 195 | G8: MG | H8: 24 | I8: H | S8: N390 | T8: INFECCION DE VIAS URINARIAS, SITIO NO ESPECIFICADO | U8: =+V8*(W8+X8+Y8+Z8) -> 422.5 | V8: 13 | W8: =IFERROR(VLOOKUP(VLOOKUP(E8,'Dosis Mx'!$R$1:$X$19,1,FALSE),'Dosis Mx'!$R$1:$X$19,6,FALSE),0) -> 15 | X8: =IFERROR(VLOOKUP(VLOOKUP(E8,'Dosis Mx'!$R$20:$X$36,1,FALSE),'Dosis Mx'!$R$20:$X$36,6,FALSE),0) -> 0 | Y8: =IFERROR(VLOOKUP(VLOOKUP(E8,'Dosis Mx'!$R$37:$X$54,1,FALSE),'Dosis Mx'!$R$37:$X$54,6,FALSE),0) -> 0 | Z8: =IFERROR(VLOOKUP(VLOOKUP(E8,'Dosis Mx'!$R$55:$X$78,1,FALSE),'Dosis Mx'!$R$55:$X$78,6,FALSE),0) -> 17.5 | AA8: =+F8*(24/H8) -> 195 | AB8: URGENCIAS
A9: 6 | B9: 503-5 | C9: 1018280799 | D9: MADISON VARELA VIDAL | E9: AMIKacina (Sulfato) 100 mg/2 ml Solucion Inyectable | F9: 140 | G9: MG | H9: 24 | I9: H | S9: N390 | T9: INFECCION DE VIAS URINARIAS, SITIO NO ESPECIFICADO | U9: =+V9*(W9+X9+Y9+Z9) -> 305.5 | V9: 9.4 | W9: =IFERROR(VLOOKUP(VLOOKUP(E9,'Dosis Mx'!$R$1:$X$19,1,FALSE),'Dosis Mx'!$R$1:$X$19,6,FALSE),0) -> 15 | X9: =IFERROR(VLOOKUP(VLOOKUP(E9,'Dosis Mx'!$R$20:$X$36,1,FALSE),'Dosis Mx'!$R$20:$X$36,6,FALSE),0) -> 0 | Y9: =IFERROR(VLOOKUP(VLOOKUP(E9,'Dosis Mx'!$R$37:$X$54,1,FALSE),'Dosis Mx'!$R$37:$X$54,6,FALSE),0) -> 0 | Z9: =IFERROR(VLOOKUP(VLOOKUP(E9,'Dosis Mx'!$R$55:$X$78,1,FALSE),'Dosis Mx'!$R$55:$X$78,6,FALSE),0) -> 17.5 | AA9: =+F9*(24/H9) -> 140
A10: 7 | B10: 504-1 | C10: 1040759862 | D10: CATALINA GRACIANO SIERRA | E10: AMIKacina (Sulfato) 500 mg/2 ml Solucion Inyectable | F10: 255 | G10: MG | H10: 24 | I10: H | S10: N390 | T10: INFECCION DE VIAS URINARIAS, SITIO NO ESPECIFICADO | U10: =+V10*(W10+X10+Y10+Z10) -> 552.5 | V10: 17 | W10: =IFERROR(VLOOKUP(VLOOKUP(E10,'Dosis Mx'!$R$1:$X$19,1,FALSE),'Dosis Mx'!$R$1:$X$19,6,FALSE),0) -> 15 | X10: =IFERROR(VLOOKUP(VLOOKUP(E10,'Dosis Mx'!$R$20:$X$36,1,FALSE),'Dosis Mx'!$R$20:$X$36,6,FALSE),0) -> 0 | Y10: =IFERROR(VLOOKUP(VLOOKUP(E10,'Dosis Mx'!$R$37:$X$54,1,FALSE),'Dosis Mx'!$R$37:$X$54,6,FALSE),0) -> 0 | Z10: =IFERROR(VLOOKUP(VLOOKUP(E10,'Dosis Mx'!$R$55:$X$78,1,FALSE),'Dosis Mx'!$R$55:$X$78,6,FALSE),0) -> 17.5 | AA10: =+F10*(24/H10) -> 255
A11: 8 | B11: 504-2 | C11: 1033204873 | D11: LUCIANA GUARIN AGUDELO | E11: AMPIcilina Sodica/SULBactam Sodico 1000/500mg Polvo para iny (Ped) | F11: 825 | G11: MG | H11: 6 | I11: H | S11: A099 | T11: GASTROENTERITIS Y COLITIS DE ORIGEN NO ESPECIFICADO | U11: =+V11*(W11+X11+Y11+Z11) -> 3300 | V11: 16.5 | W11: =IFERROR(VLOOKUP(VLOOKUP(E11,'Dosis Mx'!$R$1:$X$19,1,FALSE),'Dosis Mx'!$R$1:$X$19,6,FALSE),0) -> 0 | X11: =IFERROR(VLOOKUP(VLOOKUP(E11,'Dosis Mx'!$R$20:$X$36,1,FALSE),'Dosis Mx'!$R$20:$X$36,6,FALSE),0) -> 0 | Y11: =IFERROR(VLOOKUP(VLOOKUP(E11,'Dosis Mx'!$R$37:$X$54,1,FALSE),'Dosis Mx'!$R$37:$X$54,6,FALSE),0) -> 200 | Z11: =IFERROR(VLOOKUP(VLOOKUP(E11,'Dosis Mx'!$R$55:$X$78,1,FALSE),'Dosis Mx'!$R$55:$X$78,6,FALSE),0) -> 0 | AA11: =+F11*(24/H11) -> 3300
A12: 9 | B12: 504-6 | C12: 1214749112 | D12: MARIANGEL PEREA CASTRO | E12: AMIKacina (Sulfato) 500 mg/2 ml Solucion Inyectable | F12: 135 | G12: MG | H12: 24 | I12: H | S12: N390 | T12: INFECCION DE VIAS URINARIAS, SITIO NO ESPECIFICADO | U12: =+V12*(W12+X12+Y12+Z12) -> 292.5 | V12: 9 | W12: =IFERROR(VLOOKUP(VLOOKUP(E12,'Dosis Mx'!$R$1:$X$19,1,FALSE),'Dosis Mx'!$R$1:$X$19,6,FALSE),0) -> 15 | X12: =IFERROR(VLOOKUP(VLOOKUP(E12,'Dosis Mx'!$R$20:$X$36,1,FALSE),'Dosis Mx'!$R$20:$X$36,6,FALSE),0) -> 0 | Y12: =IFERROR(VLOOKUP(VLOOKUP(E12,'Dosis Mx'!$R$37:$X$54,1,FALSE),'Dosis Mx'!$R$37:$X$54,6,FALSE),0) -> 0 | Z12: =IFERROR(VLOOKUP(VLOOKUP(E12,'Dosis Mx'!$R$55:$X$78,1,FALSE),'Dosis Mx'!$R$55:$X$78,6,FALSE),0) -> 17.5 | AA12: =+F12*(24/H12) -> 135
A13: 10 | B13: 505-2 | C13: 1023663330 | D13: GABRIELA ORTIZ CALLEJAS | E13: AMPIcilina Sodica/SULBactam Sodico 1000/500mg Polvo para iny (Ped) | F13: 500 | G13: MG | H13: 6 | I13: H | S13: R509 | T13: FIEBRE, NO ESPECIFICADA | U13: =+V13*(W13+X13+Y13+Z13) -> 2000 | V13: 10 | W13: =IFERROR(VLOOKUP(VLOOKUP(E13,'Dosis Mx'!$R$1:$X$19,1,FALSE),'Dosis Mx'!$R$1:$X$19,6,FALSE),0) -> 0 | X13: =IFERROR(VLOOKUP(VLOOKUP(E13,'Dosis Mx'!$R$20:$X$36,1,FALSE),'Dosis Mx'!$R$20:$X$36,6,FALSE),0) -> 0 | Y13: =IFERROR(VLOOKUP(VLOOKUP(E13,'Dosis Mx'!$R$37:$X$54,1,FALSE),'Dosis Mx'!$R$37:$X$54,6,FALSE),0) -> 200 | Z13: =IFERROR(VLOOKUP(VLOOKUP(E13,'Dosis Mx'!$R$55:$X$78,1,FALSE),'Dosis Mx'!$R$55:$X$78,6,FALSE),0) -> 0 | AA13: =+F13*(24/H13) -> 2000
A14: 11 | B14: 505-3 | C14: 1036692900 | D14: IAN DAVID PERALTA CARDONA | E14: AMIKacina (Sulfato) 100 mg/2 ml Solucion Inyectable | F14: 150 | G14: MG | H14: 24 | I14: H | S14: N390 | T14: INFECCION DE VIAS URINARIAS, SITIO NO ESPECIFICADO | U14: =+V14*(W14+X14+Y14+Z14) -> 325 | V14: 10 | W14: =IFERROR(VLOOKUP(VLOOKUP(E14,'Dosis Mx'!$R$1:$X$19,1,FALSE),'Dosis Mx'!$R$1:$X$19,6,FALSE),0) -> 15 | X14: =IFERROR(VLOOKUP(VLOOKUP(E14,'Dosis Mx'!$R$20:$X$36,1,FALSE),'Dosis Mx'!$R$20:$X$36,6,FALSE),0) -> 0 | Y14: =IFERROR(VLOOKUP(VLOOKUP(E14,'Dosis Mx'!$R$37:$X$54,1,FALSE),'Dosis Mx'!$R$37:$X$54,6,FALSE),0) -> 0 | Z14: =IFERROR(VLOOKUP(VLOOKUP(E14,'Dosis Mx'!$R$55:$X$78,1,FALSE),'Dosis Mx'!$R$55:$X$78,6,FALSE),0) -> 17.5 | AA14: =+F14*(24/H14) -> 150
A15: 12 | B15: 505-5 | C15: 1037505012 | D15: MIGUEL ANGEL TORRES HENAO | E15: Cefazolina 1000 mg Polvo para Inyeccion | F15: 600 | G15: MG | H15: 8 | I15: H | S15: Q541 | T15: HIPOSPADIAS PENEANA | U15: =+V15*(W15+X15+Y15+Z15) -> 1800 | V15: 18 | W15: =IFERROR(VLOOKUP(VLOOKUP(E15,'Dosis Mx'!$R$1:$X$19,1,FALSE),'Dosis Mx'!$R$1:$X$19,6,FALSE),0) -> 0 | X15: =IFERROR(VLOOKUP(VLOOKUP(E15,'Dosis Mx'!$R$20:$X$36,1,FALSE),'Dosis Mx'!$R$20:$X$36,6,FALSE),0) -> 100 | Y15: =IFERROR(VLOOKUP(VLOOKUP(E15,'Dosis Mx'!$R$37:$X$54,1,FALSE),'Dosis Mx'!$R$37:$X$54,6,FALSE),0) -> 0 | Z15: =IFERROR(VLOOKUP(VLOOKUP(E15,'Dosis Mx'!$R$55:$X$78,1,FALSE),'Dosis Mx'!$R$55:$X$78,6,FALSE),0) -> 0 | AA15: =+F15*(24/H15) -> 1800
A16: 13 | B16: 505-6 | C16: 1023661575 | D16: EMILY QUINTERO LOPEZ | E16: Clindamicina (Fosfato) 600 mg /4ml Solucion Inyectable | F16: 110 | G16: MG | H16: 6 | I16: H | S16: L038 | T16: CELULITIS DE OTROS SITIOS | U16: =+V16*(W16+X16+Y16+Z16) -> 495 | V16: 11 | W16: =IFERROR(VLOOKUP(VLOOKUP(E16,'Dosis Mx'!$R$1:$X$19,1,FALSE),'Dosis Mx'!$R$1:$X$19,6,FALSE),0) -> 0 | X16: =IFERROR(VLOOKUP(VLOOKUP(E16,'Dosis Mx'!$R$20:$X$36,1,FALSE),'Dosis Mx'!$R$20:$X$36,6,FALSE),0) -> 10 | Y16: =IFERROR(VLOOKUP(VLOOKUP(E16,'Dosis Mx'!$R$37:$X$54,1,FALSE),'Dosis Mx'!$R$37:$X$54,6,FALSE),0) -> 35 | Z16: =IFERROR(VLOOKUP(VLOOKUP(E16,'Dosis Mx'!$R$55:$X$78,1,FALSE),'Dosis Mx'!$R$55:$X$78,6,FALSE),0) -> 0 | AA16: =+F16*(24/H16) -> 440
A17: 14 | B17: 506-5 | C17: 1033207603 | D17: SARAY TAMAYO QUEJADA | E17: AMIKacina (Sulfato) 100 mg/2 ml Solucion Inyectable | F17: 81 | G17: MG | H17: 24 | I17: H | S17: N390 | T17: INFECCION DE VIAS URINARIAS, SITIO NO ESPECIFICADO | U17: =+V17*(W17+X17+Y17+Z17) -> 175.5 | V17: 5.4 | W17: =IFERROR(VLOOKUP(VLOOKUP(E17,'Dosis Mx'!$R$1:$X$19,1,FALSE),'Dosis Mx'!$R$1:$X$19,6,FALSE),0) -> 15 | X17: =IFERROR(VLOOKUP(VLOOKUP(E17,'Dosis Mx'!$R$20:$X$36,1,FALSE),'Dosis Mx'!$R$20:$X$36,6,FALSE),0) -> 0 | Y17: =IFERROR(VLOOKUP(VLOOKUP(E17,'Dosis Mx'!$R$37:$X$54,1,FALSE),'Dosis Mx'!$R$37:$X$54,6,FALSE),0) -> 0 | Z17: =IFERROR(VLOOKUP(VLOOKUP(E17,'Dosis Mx'!$R$55:$X$78,1,FALSE),'Dosis Mx'!$R$55:$X$78,6,FALSE),0) -> 17.5 | AA17: =+F17*(24/H17) -> 81
A18: 15 | B18: 506-6 | C18: 1029300592 | D18: JUAN CAMILO MURILLO ATEHORTUA | E18: Cefazolina 1000 mg Polvo para Inyeccion | F18: 1000 | G18: MG | H18: 1 | I18: U | S18: K358 | T18: OTRAS APENDICITIS AGUDAS, Y LAS NO ESPECIFICADAS | U18: =+V18*(W18+X18+Y18+Z18) -> 2400 | V18: 24 | W18: =IFERROR(VLOOKUP(VLOOKUP(E18,'Dosis Mx'!$R$1:$X$19,1,FALSE),'Dosis Mx'!$R$1:$X$19,6,FALSE),0) -> 0 | X18: =IFERROR(VLOOKUP(VLOOKUP(E18,'Dosis Mx'!$R$20:$X$36,1,FALSE),'Dosis Mx'!$R$20:$X$36,6,FALSE),0) -> 100 | Y18: =IFERROR(VLOOKUP(VLOOKUP(E18,'Dosis Mx'!$R$37:$X$54,1,FALSE),'Dosis Mx'!$R$37:$X$54,6,FALSE),0) -> 0 | Z18: =IFERROR(VLOOKUP(VLOOKUP(E18,'Dosis Mx'!$R$55:$X$78,1,FALSE),'Dosis Mx'!$R$55:$X$78,6,FALSE),0) -> 0 | AA18: =+F18*(24/H18) -> 24000
A19: 16 | B19: 708-3 | C19: 1025679188 | D19: NOAH BEDOYA RENTERIA | E19: AMIKacina (Sulfato) 100 mg/2 ml Solucion Inyectable | F19: 63 | G19: MG | H19: 24 | I19: H | S19: N390 | T19: INFECCION DE VIAS URINARIAS, SITIO NO ESPECIFICADO | U19: =+V19*(W19+X19+Y19+Z19) -> 143 | V19: 4.4 | W19: =IFERROR(VLOOKUP(VLOOKUP(E19,'Dosis Mx'!$R$1:$X$19,1,FALSE),'Dosis Mx'!$R$1:$X$19,6,FALSE),0) -> 15 | X19: =IFERROR(VLOOKUP(VLOOKUP(E19,'Dosis Mx'!$R$20:$X$36,1,FALSE),'Dosis Mx'!$R$20:$X$36,6,FALSE),0) -> 0 | Y19: =IFERROR(VLOOKUP(VLOOKUP(E19,'Dosis Mx'!$R$37:$X$54,1,FALSE),'Dosis Mx'!$R$37:$X$54,6,FALSE),0) -> 0 | Z19: =IFERROR(VLOOKUP(VLOOKUP(E19,'Dosis Mx'!$R$55:$X$78,1,FALSE),'Dosis Mx'!$R$55:$X$78,6,FALSE),0) -> 17.5 | AA19: =+F19*(24/H19) -> 63
A20: 17 | B20: 708-4 | C20: 1040262325 | D20: VICTOR ALFONSO FLOREZ AGUDELO | E20: Fluconazol 50 mg/5 ml Polvo para Suspension Frasco X 20 ml | F20: 85 | G20: MG | H20: 24 | I20: H | S20: L080 | T20: PIODERMA | U20: =+V20*(W20+X20+Y20+Z20) -> 0 | V20: 6.55 | W20: =IFERROR(VLOOKUP(VLOOKUP(E20,'Dosis Mx'!$R$1:$X$19,1,FALSE),'Dosis Mx'!$R$1:$X$19,6,FALSE),0) -> 0 | X20: =IFERROR(VLOOKUP(VLOOKUP(E20,'Dosis Mx'!$R$20:$X$36,1,FALSE),'Dosis Mx'!$R$20:$X$36,6,FALSE),0) -> 0 | Y20: =IFERROR(VLOOKUP(VLOOKUP(E20,'Dosis Mx'!$R$37:$X$54,1,FALSE),'Dosis Mx'!$R$37:$X$54,6,FALSE),0) -> 0 | Z20: =IFERROR(VLOOKUP(VLOOKUP(E20,'Dosis Mx'!$R$55:$X$78,1,FALSE),'Dosis Mx'!$R$55:$X$78,6,FALSE),0) -> 0 | AA20: =+F20*(24/H20) -> 85
... A31: 29 | B31: Aisl 707 | C31: 1031948897 | D31: EMILIANO LONDOÑO RINCON | E31: AZITromicina200mg/5 ml (4%)Polvo para reconstituirx15ml | F31: 126 | G31: MG | H31: 24 | I31: H | S31: J22X | T31: INFECCION AGUDA NO ESPECIFICADA DE LAS VIAS RESPIRATORIAS INFERIORES | U31: =+V31*(W31+X31+Y31+Z31) -> 94.5 | V31: 12.6 | W31: =IFERROR(VLOOKUP(VLOOKUP(E31,'Dosis Mx'!$R$1:$X$19,1,FALSE),'Dosis Mx'!$R$1:$X$19,6,FALSE),0) -> 0 | X31: =IFERROR(VLOOKUP(VLOOKUP(E31,'Dosis Mx'!$R$20:$X$36,1,FALSE),'Dosis Mx'!$R$20:$X$36,6,FALSE),0) -> 0 | Y31: =IFERROR(VLOOKUP(VLOOKUP(E31,'Dosis Mx'!$R$37:$X$54,1,FALSE),'Dosis Mx'!$R$37:$X$54,6,FALSE),0) -> 7.5 | Z31: =IFERROR(VLOOKUP(VLOOKUP(E31,'Dosis Mx'!$R$55:$X$78,1,FALSE),'Dosis Mx'!$R$55:$X$78,6,FALSE),0) -> 0 | AA31: =+F31*(24/H31) -> 126
A32: No | B32: Servicio | C32: Docidentidad | D32: Usuario | E32: Nombre | F32: Dosis | G32: Medidadosis | H32: Frecuencia | I32: Unidadfrecuencia | J32: Tto Empirico | K32: Tto Dirigido | L32: cultivo | M32: Suspender | N32: Cambiar | R32: Observacionesorden | S32: Codigo Diagnostico | T32: Diagnostico | U32: Dosis | V32: Peso(kg) | W32: ITU | X32: ITB | Y32: NEUMONIA | Z32: MENINGITIS | AA32: Dosis recetada
N33: Escalar | O33: Desescalar | P33: RXN adversa | Q33: Por dosis
U34: =+V34*(W34+X34+Y34+Z34) -> 0 | W34: =IFERROR(VLOOKUP(VLOOKUP(E34,'Dosis Mx'!$R$1:$X$19,1,FALSE),'Dosis Mx'!$R$1:$X$19,6,FALSE),0) -> 0 | X34: =IFERROR(VLOOKUP(VLOOKUP(E34,'Dosis Mx'!$R$20:$X$36,1,FALSE),'Dosis Mx'!$R$20:$X$36,6,FALSE),0) -> 0 | Y34: =IFERROR(VLOOKUP(VLOOKUP(E34,'Dosis Mx'!$R$37:$X$54,1,FALSE),'Dosis Mx'!$R$37:$X$54,6,FALSE),0) -> 0 | Z34: =IFERROR(VLOOKUP(VLOOKUP(E34,'Dosis Mx'!$R$55:$X$78,1,FALSE),'Dosis Mx'!$R$55:$X$78,6,FALSE),0) -> 0 | AA34: =+F34*(24/H34) -> #DIV/0!
U35: =+V35*(W35+X35+Y35+Z35) -> 0 | W35: =IFERROR(VLOOKUP(VLOOKUP(E35,'Dosis Mx'!$R$1:$X$19,1,FALSE),'Dosis Mx'!$R$1:$X$19,6,FALSE),0) -> 0 | X35: =IFERROR(VLOOKUP(VLOOKUP(E35,'Dosis Mx'!$R$20:$X$36,1,FALSE),'Dosis Mx'!$R$20:$X$36,6,FALSE),0) -> 0 | Y35: =IFERROR(VLOOKUP(VLOOKUP(E35,'Dosis Mx'!$R$37:$X$54,1,FALSE),'Dosis Mx'!$R$37:$X$54,6,FALSE),0) -> 0 | Z35: =IFERROR(VLOOKUP(VLOOKUP(E35,'Dosis Mx'!$R$55:$X$78,1,FALSE),'Dosis Mx'!$R$55:$X$78,6,FALSE),0) -> 0 | AA35: =+F35*(24/H35) -> #DIV/0!
U36: =+V36*(W36+X36+Y36+Z36) -> 0 | W36: =IFERROR(VLOOKUP(VLOOKUP(E36,'Dosis Mx'!$R$1:$X$19,1,FALSE),'Dosis Mx'!$R$1:$X$19,6,FALSE),0) -> 0 | X36: =IFERROR(VLOOKUP(VLOOKUP(E36,'Dosis Mx'!$R$20:$X$36,1,FALSE),'Dosis Mx'!$R$20:$X$36,6,FALSE),0) -> 0 | Y36: =IFERROR(VLOOKUP(VLOOKUP(E36,'Dosis Mx'!$R$37:$X$54,1,FALSE),'Dosis Mx'!$R$37:$X$54,6,FALSE),0) -> 0 | Z36: =IFERROR(VLOOKUP(VLOOKUP(E36,'Dosis Mx'!$R$55:$X$78,1,FALSE),'Dosis Mx'!$R$55:$X$78,6,FALSE),0) -> 0 | AA36: =+F36*(24/H36) -> #DIV/0!
U37: =+V37*(W37+X37+Y37+Z37) -> 0 | W37: =IFERROR(VLOOKUP(VLOOKUP(E37,'Dosis Mx'!$R$1:$X$19,1,FALSE),'Dosis Mx'!$R$1:$X$19,6,FALSE),0) -> 0 | X37: =IFERROR(VLOOKUP(VLOOKUP(E37,'Dosis Mx'!$R$20:$X$36,1,FALSE),'Dosis Mx'!$R$20:$X$36,6,FALSE),0) -> 0 | Y37: =IFERROR(VLOOKUP(VLOOKUP(E37,'Dosis Mx'!$R$37:$X$54,1,FALSE),'Dosis Mx'!$R$37:$X$54,6,FALSE),0) -> 0 | Z37: =IFERROR(VLOOKUP(VLOOKUP(E37,'Dosis Mx'!$R$55:$X$78,1,FALSE),'Dosis Mx'!$R$55:$X$78,6,FALSE),0) -> 0 | AA37: =+F37*(24/H37) -> #DIV/0!
A38: 36 | U38: =+V38*(W38+X38+Y38+Z38) -> 0 | W38: =IFERROR(VLOOKUP(VLOOKUP(E38,'Dosis Mx'!$R$1:$X$19,1,FALSE),'Dosis Mx'!$R$1:$X$19,6,FALSE),0) -> 0 | X38: =IFERROR(VLOOKUP(VLOOKUP(E38,'Dosis Mx'!$R$20:$X$36,1,FALSE),'Dosis Mx'!$R$20:$X$36,6,FALSE),0) -> 0 | Y38: =IFERROR(VLOOKUP(VLOOKUP(E38,'Dosis Mx'!$R$37:$X$54,1,FALSE),'Dosis Mx'!$R$37:$X$54,6,FALSE),0) -> 0 | Z38: =IFERROR(VLOOKUP(VLOOKUP(E38,'Dosis Mx'!$R$55:$X$78,1,FALSE),'Dosis Mx'!$R$55:$X$78,6,FALSE),0) -> 0 | AA38: =+F38*(24/H38) -> #DIV/0!
A39: 37 | U39: =+V39*(W39+X39+Y39+Z39) -> 0 | W39: =IFERROR(VLOOKUP(VLOOKUP(E39,'Dosis Mx'!$R$1:$X$19,1,FALSE),'Dosis Mx'!$R$1:$X$19,6,FALSE),0) -> 0 | X39: =IFERROR(VLOOKUP(VLOOKUP(E39,'Dosis Mx'!$R$20:$X$36,1,FALSE),'Dosis Mx'!$R$20:$X$36,6,FALSE),0) -> 0 | Y39: =IFERROR(VLOOKUP(VLOOKUP(E39,'Dosis Mx'!$R$37:$X$54,1,FALSE),'Dosis Mx'!$R$37:$X$54,6,FALSE),0) -> 0 | Z39: =IFERROR(VLOOKUP(VLOOKUP(E39,'Dosis Mx'!$R$55:$X$78,1,FALSE),'Dosis Mx'!$R$55:$X$78,6,FALSE),0) -> 0 | AA39: =+F39*(24/H39) -> #DIV/0!
A40: 38 | U40: =+V40*(W40+X40+Y40+Z40) -> 0 | W40: =IFERROR(VLOOKUP(VLOOKUP(E40,'Dosis Mx'!$R$1:$X$19,1,FALSE),'Dosis Mx'!$R$1:$X$19,6,FALSE),0) -> 0 | X40: =IFERROR(VLOOKUP(VLOOKUP(E40,'Dosis Mx'!$R$20:$X$36,1,FALSE),'Dosis Mx'!$R$20:$X$36,6,FALSE),0) -> 0 | Y40: =IFERROR(VLOOKUP(VLOOKUP(E40,'Dosis Mx'!$R$37:$X$54,1,FALSE),'Dosis Mx'!$R$37:$X$54,6,FALSE),0) -> 0 | Z40: =IFERROR(VLOOKUP(VLOOKUP(E40,'Dosis Mx'!$R$55:$X$78,1,FALSE),'Dosis Mx'!$R$55:$X$78,6,FALSE),0) -> 0 | AA40: =+F40*(24/H40) -> #DIV/0!
A41: 39 | U41: =+V41*(W41+X41+Y41+Z41) -> 0 | W41: =IFERROR(VLOOKUP(VLOOKUP(E41,'Dosis Mx'!$R$1:$X$19,1,FALSE),'Dosis Mx'!$R$1:$X$19,6,FALSE),0) -> 0 | X41: =IFERROR(VLOOKUP(VLOOKUP(E41,'Dosis Mx'!$R$20:$X$36,1,FALSE),'Dosis Mx'!$R$20:$X$36,6,FALSE),0) -> 0 | Y41: =IFERROR(VLOOKUP(VLOOKUP(E41,'Dosis Mx'!$R$37:$X$54,1,FALSE),'Dosis Mx'!$R$37:$X$54,6,FALSE),0) -> 0 | Z41: =IFERROR(VLOOKUP(VLOOKUP(E41,'Dosis Mx'!$R$55:$X$78,1,FALSE),'Dosis Mx'!$R$55:$X$78,6,FALSE),0) -> 0 | AA41: =+F41*(24/H41) -> #DIV/0!
A42: 40 | U42: =+V42*(W42+X42+Y42+Z42) -> 0 | W42: =IFERROR(VLOOKUP(VLOOKUP(E42,'Dosis Mx'!$R$1:$X$19,1,FALSE),'Dosis Mx'!$R$1:$X$19,6,FALSE),0) -> 0 | X42: =IFERROR(VLOOKUP(VLOOKUP(E42,'Dosis Mx'!$R$20:$X$36,1,FALSE),'Dosis Mx'!$R$20:$X$36,6,FALSE),0) -> 0 | Y42: =IFERROR(VLOOKUP(VLOOKUP(E42,'Dosis Mx'!$R$37:$X$54,1,FALSE),'Dosis Mx'!$R$37:$X$54,6,FALSE),0) -> 0 | Z42: =IFERROR(VLOOKUP(VLOOKUP(E42,'Dosis Mx'!$R$55:$X$78,1,FALSE),'Dosis Mx'!$R$55:$X$78,6,FALSE),0) -> 0 | AA42: =+F42*(24/H42) -> #DIV/0!
A43: 41 | U43: =+V43*(W43+X43+Y43+Z43) -> 0 | W43: =IFERROR(VLOOKUP(VLOOKUP(E43,'Dosis Mx'!$R$1:$X$19,1,FALSE),'Dosis Mx'!$R$1:$X$19,6,FALSE),0) -> 0 | X43: =IFERROR(VLOOKUP(VLOOKUP(E43,'Dosis Mx'!$R$20:$X$36,1,FALSE),'Dosis Mx'!$R$20:$X$36,6,FALSE),0) -> 0 | Y43: =IFERROR(VLOOKUP(VLOOKUP(E43,'Dosis Mx'!$R$37:$X$54,1,FALSE),'Dosis Mx'!$R$37:$X$54,6,FALSE),0) -> 0 | Z43: =IFERROR(VLOOKUP(VLOOKUP(E43,'Dosis Mx'!$R$55:$X$78,1,FALSE),'Dosis Mx'!$R$55:$X$78,6,FALSE),0) -> 0 | AA43: =+F43*(24/H43) -> #DIV/0!
A44: 42 | U44: =+V44*(W44+X44+Y44+Z44) -> 0 | W44: =IFERROR(VLOOKUP(VLOOKUP(E44,'Dosis Mx'!$R$1:$X$19,1,FALSE),'Dosis Mx'!$R$1:$X$19,6,FALSE),0) -> 0 | X44: =IFERROR(VLOOKUP(VLOOKUP(E44,'Dosis Mx'!$R$20:$X$36,1,FALSE),'Dosis Mx'!$R$20:$X$36,6,FALSE),0) -> 0 | Y44: =IFERROR(VLOOKUP(VLOOKUP(E44,'Dosis Mx'!$R$37:$X$54,1,FALSE),'Dosis Mx'!$R$37:$X$54,6,FALSE),0) -> 0 | Z44: =IFERROR(VLOOKUP(VLOOKUP(E44,'Dosis Mx'!$R$55:$X$78,1,FALSE),'Dosis Mx'!$R$55:$X$78,6,FALSE),0) -> 0 | AA44: =+F44*(24/H44) -> #DIV/0!
A45: 43 | U45: =+V45*(W45+X45+Y45+Z45) -> 0 | W45: =IFERROR(VLOOKUP(VLOOKUP(E45,'Dosis Mx'!$R$1:$X$19,1,FALSE),'Dosis Mx'!$R$1:$X$19,6,FALSE),0) -> 0 | X45: =IFERROR(VLOOKUP(VLOOKUP(E45,'Dosis Mx'!$R$20:$X$36,1,FALSE),'Dosis Mx'!$R$20:$X$36,6,FALSE),0) -> 0 | Y45: =IFERROR(VLOOKUP(VLOOKUP(E45,'Dosis Mx'!$R$37:$X$54,1,FALSE),'Dosis Mx'!$R$37:$X$54,6,FALSE),0) -> 0 | Z45: =IFERROR(VLOOKUP(VLOOKUP(E45,'Dosis Mx'!$R$55:$X$78,1,FALSE),'Dosis Mx'!$R$55:$X$78,6,FALSE),0) -> 0 | AA45: =+F45*(24/H45) -> #DIV/0!
A46: 44 | U46: =+V46*(W46+X46+Y46+Z46) -> 0 | W46: =IFERROR(VLOOKUP(VLOOKUP(E46,'Dosis Mx'!$R$1:$X$19,1,FALSE),'Dosis Mx'!$R$1:$X$19,6,FALSE),0) -> 0 | X46: =IFERROR(VLOOKUP(VLOOKUP(E46,'Dosis Mx'!$R$20:$X$36,1,FALSE),'Dosis Mx'!$R$20:$X$36,6,FALSE),0) -> 0 | Y46: =IFERROR(VLOOKUP(VLOOKUP(E46,'Dosis Mx'!$R$37:$X$54,1,FALSE),'Dosis Mx'!$R$37:$X$54,6,FALSE),0) -> 0 | Z46: =IFERROR(VLOOKUP(VLOOKUP(E46,'Dosis Mx'!$R$55:$X$78,1,FALSE),'Dosis Mx'!$R$55:$X$78,6,FALSE),0) -> 0 | AA46: =+F46*(24/H46) -> #DIV/0!
A47: 45 | U47: =+V47*(W47+X47+Y47+Z47) -> 0 | W47: =IFERROR(VLOOKUP(VLOOKUP(E47,'Dosis Mx'!$R$1:$X$19,1,FALSE),'Dosis Mx'!$R$1:$X$19,6,FALSE),0) -> 0 | X47: =IFERROR(VLOOKUP(VLOOKUP(E47,'Dosis Mx'!$R$20:$X$36,1,FALSE),'Dosis Mx'!$R$20:$X$36,6,FALSE),0) -> 0 | Y47: =IFERROR(VLOOKUP(VLOOKUP(E47,'Dosis Mx'!$R$37:$X$54,1,FALSE),'Dosis Mx'!$R$37:$X$54,6,FALSE),0) -> 0 | Z47: =IFERROR(VLOOKUP(VLOOKUP(E47,'Dosis Mx'!$R$55:$X$78,1,FALSE),'Dosis Mx'!$R$55:$X$78,6,FALSE),0) -> 0 | AA47: =+F47*(24/H47) -> #DIV/0!
A48: 46 | U48: =+V48*(W48+X48+Y48+Z48) -> 0 | W48: =IFERROR(VLOOKUP(VLOOKUP(E48,'Dosis Mx'!$R$1:$X$19,1,FALSE),'Dosis Mx'!$R$1:$X$19,6,FALSE),0) -> 0 | X48: =IFERROR(VLOOKUP(VLOOKUP(E48,'Dosis Mx'!$R$20:$X$36,1,FALSE),'Dosis Mx'!$R$20:$X$36,6,FALSE),0) -> 0 | Y48: =IFERROR(VLOOKUP(VLOOKUP(E48,'Dosis Mx'!$R$37:$X$54,1,FALSE),'Dosis Mx'!$R$37:$X$54,6,FALSE),0) -> 0 | Z48: =IFERROR(VLOOKUP(VLOOKUP(E48,'Dosis Mx'!$R$55:$X$78,1,FALSE),'Dosis Mx'!$R$55:$X$78,6,FALSE),0) -> 0 | AA48: =+F48*(24/H48) -> #DIV/0!
A49: 47 | U49: =+V49*(W49+X49+Y49+Z49) -> 0 | W49: =IFERROR(VLOOKUP(VLOOKUP(E49,'Dosis Mx'!$R$1:$X$19,1,FALSE),'Dosis Mx'!$R$1:$X$19,6,FALSE),0) -> 0 | X49: =IFERROR(VLOOKUP(VLOOKUP(E49,'Dosis Mx'!$R$20:$X$36,1,FALSE),'Dosis Mx'!$R$20:$X$36,6,FALSE),0) -> 0 | Y49: =IFERROR(VLOOKUP(VLOOKUP(E49,'Dosis Mx'!$R$37:$X$54,1,FALSE),'Dosis Mx'!$R$37:$X$54,6,FALSE),0) -> 0 | Z49: =IFERROR(VLOOKUP(VLOOKUP(E49,'Dosis Mx'!$R$55:$X$78,1,FALSE),'Dosis Mx'!$R$55:$X$78,6,FALSE),0) -> 0 | AA49: =+F49*(24/H49) -> #DIV/0!
... A62: 60 | U62: =+V62*(W62+X62+Y62+Z62) -> 0 | W62: =IFERROR(VLOOKUP(VLOOKUP(E62,'Dosis Mx'!$R$1:$X$19,1,FALSE),'Dosis Mx'!$R$1:$X$19,6,FALSE),0) -> 0 | X62: =IFERROR(VLOOKUP(VLOOKUP(E62,'Dosis Mx'!$R$20:$X$36,1,FALSE),'Dosis Mx'!$R$20:$X$36,6,FALSE),0) -> 0 | Y62: =IFERROR(VLOOKUP(VLOOKUP(E62,'Dosis Mx'!$R$37:$X$54,1,FALSE),'Dosis Mx'!$R$37:$X$54,6,FALSE),0) -> 0 | Z62: =IFERROR(VLOOKUP(VLOOKUP(E62,'Dosis Mx'!$R$55:$X$78,1,FALSE),'Dosis Mx'!$R$55:$X$78,6,FALSE),0) -> 0 | AA62: =+F62*(24/H62) -> #DIV/0!

Sheet 24-10-2023
B1: FECHA | C1: 45223
A2: No | B2: Servicio | C2: Docidentidad | D2: Usuario | E2: Nombre | F2: Dosis | G2: Medidadosis | H2: Frecuencia | I2: Unidadfrecuencia | J2: Tto Empirico | K2: Tto Dirigido | L2: cultivo | M2: Suspender | N2: Cambiar | R2: Observacionesorden | S2: Codigo Diagnostico | T2: Diagnostico | U2: Dosis | V2: Peso(kg) | W2: ITU | X2: ITB | Y2: NEUMONIA | Z2: MENINGITIS | AA2: Dosis recetada
N3: Escalar | O3: Desescalar | P3: RXN adversa | Q3: Por dosis
A4: 1 | B4: 601-1 | C4: 1077652699 | D4: HEINNI KARINA CHAMARRA OBISPO | E4: Nistatina 100.000 U/ml Suspension Oral Frasco X 60 ml | F4: 100000 | G4: 15 | H4: 8 | I4: H | J4: I | L4: NA | S4: Q250 | T4: CONDUCTO ARTERIOSO PERSISTENTE | U4: =+V4*(W4+X4+Y4+Z4) -> 0 | V4: 5.2 | W4: =IFERROR(VLOOKUP(VLOOKUP(E4,'Dosis Mx'!$R$1:$X$19,1,FALSE),'Dosis Mx'!$R$1:$X$19,6,FALSE),0) -> 0 | X4: =IFERROR(VLOOKUP(VLOOKUP(E4,'Dosis Mx'!$R$20:$X$36,1,FALSE),'Dosis Mx'!$R$20:$X$36,6,FALSE),0) -> 0 | Y4: =IFERROR(VLOOKUP(VLOOKUP(E4,'Dosis Mx'!$R$37:$X$54,1,FALSE),'Dosis Mx'!$R$37:$X$54,6,FALSE),0) -> 0 | Z4: =IFERROR(VLOOKUP(VLOOKUP(E4,'Dosis Mx'!$R$55:$X$78,1,FALSE),'Dosis Mx'!$R$55:$X$78,6,FALSE),0) -> 0 | AA4: =+F4*(24/H4) -> 300000 | AB4: 5
A5: 2 | B5: 601-1 | C5: 1077652699 | D5: HEINNI KARINA CHAMARRA OBISPO | E5: Ceftriaxona (Sal Sodica) 1000 mg Polvo para Inyeccion | F5: 400 | G5: MG | H5: 24 | I5: H | J5: I | L5: NA | S5: Q250 | T5: CONDUCTO ARTERIOSO PERSISTENTE | U5: =+V5*(W5+X5+Y5+Z5) -> 2470 | V5: 5.2 | W5: =IFERROR(VLOOKUP(VLOOKUP(E5,'Dosis Mx'!$R$1:$X$19,1,FALSE),'Dosis Mx'!$R$1:$X$19,6,FALSE),0) -> 300 | X5: =IFERROR(VLOOKUP(VLOOKUP(E5,'Dosis Mx'!$R$20:$X$36,1,FALSE),'Dosis Mx'!$R$20:$X$36,6,FALSE),0) -> 0 | Y5: =IFERROR(VLOOKUP(VLOOKUP(E5,'Dosis Mx'!$R$37:$X$54,1,FALSE),'Dosis Mx'!$R$37:$X$54,6,FALSE),0) -> 75 | Z5: =IFERROR(VLOOKUP(VLOOKUP(E5,'Dosis Mx'!$R$55:$X$78,1,FALSE),'Dosis Mx'!$R$55:$X$78,6,FALSE),0) -> 100 | AA5: =+F5*(24/H5) -> 400 | AB5: 6 | AC5: 35
A6: 3 | B6: 601-3 | C6: 1036266814 | D6: EMMANUEL MORALES CASTAÑO | E6: AMPIcilina Sodica/SULBactam Sodico 1000/500mg Polvo para iny (Ped) | F6: 500 | G6: MG | H6: 6 | I6: H | J6: I | L6: NA | S6: H650 | T6: OTITIS MEDIA AGUDA SEROSA | U6: =+V6*(W6+X6+Y6+Z6) -> 2140 | V6: 10.7 | W6: =IFERROR(VLOOKUP(VLOOKUP(E6,'Dosis Mx'!$R$1:$X$19,1,FALSE),'Dosis Mx'!$R$1:$X$19,6,FALSE),0) -> 0 | X6: =IFERROR(VLOOKUP(VLOOKUP(E6,'Dosis Mx'!$R$20:$X$36,1,FALSE),'Dosis Mx'!$R$20:$X$36,6,FALSE),0) -> 0 | Y6: =IFERROR(VLOOKUP(VLOOKUP(E6,'Dosis Mx'!$R$37:$X$54,1,FALSE),'Dosis Mx'!$R$37:$X$54,6,FALSE),0) -> 200 | Z6: =IFERROR(VLOOKUP(VLOOKUP(E6,'Dosis Mx'!$R$55:$X$78,1,FALSE),'Dosis Mx'!$R$55:$X$78,6,FALSE),0) -> 0 | AA6: =+F6*(24/H6) -> 2000 | AB6: 7
A7: 4 | B7: 601-4 | C7: 1013365120 | D7: DYLAN ALEXANDER HENAO CARTAGENA | E7: AMPIcilina (Sal Sodica) x 1000 mg Polvo para Inyeccion | F7: 830 | G7: MG | H7: 6 | I7: H | J7: I | L7: NA | S7: J159 | T7: NEUMONIA BACTERIANA, NO ESPECIFICADA | U7: =+V7*(W7+X7+Y7+Z7) -> 7425 | V7: 16.5 | W7: =IFERROR(VLOOKUP(VLOOKUP(E7,'Dosis Mx'!$R$1:$X$19,1,FALSE),'Dosis Mx'!$R$1:$X$19,6,FALSE),0) -> 0 | X7: =IFERROR(VLOOKUP(VLOOKUP(E7,'Dosis Mx'!$R$20:$X$36,1,FALSE),'Dosis Mx'!$R$20:$X$36,6,FALSE),0) -> 0 | Y7: =IFERROR(VLOOKUP(VLOOKUP(E7,'Dosis Mx'!$R$37:$X$54,1,FALSE),'Dosis Mx'!$R$37:$X$54,6,FALSE),0) -> 200 | Z7: =IFERROR(VLOOKUP(VLOOKUP(E7,'Dosis Mx'!$R$55:$X$78,1,FALSE),'Dosis Mx'!$R$55:$X$78,6,FALSE),0) -> 250 | AA7: =+F7*(24/H7) -> 3320 | AB7: UCI | AC7: 8
A8: 5 | B8: 601-5 | C8: 1023541184 | D8: SUSANA RAMIREZ MARTINEZ | E8: AMPIcilina (Sal Sodica) x 1000 mg Polvo para Inyeccion | F8: 850 | G8: MG | H8: 6 | I8: H | J8: I | L8: NA | S8: J159 | T8: NEUMONIA BACTERIANA, NO ESPECIFICADA | U8: =+V8*(W8+X8+Y8+Z8) -> 8010 | V8: 17.8 | W8: =IFERROR(VLOOKUP(VLOOKUP(E8,'Dosis Mx'!$R$1:$X$19,1,FALSE),'Dosis Mx'!$R$1:$X$19,6,FALSE),0) -> 0 | X8: =IFERROR(VLOOKUP(VLOOKUP(E8,'Dosis Mx'!$R$20:$X$36,1,FALSE),'Dosis Mx'!$R$20:$X$36,6,FALSE),0) -> 0 | Y8: =IFERROR(VLOOKUP(VLOOKUP(E8,'Dosis Mx'!$R$37:$X$54,1,FALSE),'Dosis Mx'!$R$37:$X$54,6,FALSE),0) -> 200 | Z8: =IFERROR(VLOOKUP(VLOOKUP(E8,'Dosis Mx'!$R$55:$X$78,1,FALSE),'Dosis Mx'!$R$55:$X$78,6,FALSE),0) -> 250 | AA8: =+F8*(24/H8) -> 3400 | AB8: URGENCIAS
A9: 6 | B9: 601-6 | C9: 1131206016 | D9: DOMINIC MACEA SISTIAGA | E9: Ceftriaxona (Sal Sodica) 1000 mg Polvo para Inyeccion | F9: 500 | G9: MG | H9: 24 | I9: H | J9: I | M9: X | S9: J219 | T9: BRONQUIOLITIS AGUDA, NO ESPECIFICADA | U9: =+V9*(W9+X9+Y9+Z9) -> 2897.5 | V9: 6.1 | W9: =IFERROR(VLOOKUP(VLOOKUP(E9,'Dosis Mx'!$R$1:$X$19,1,FALSE),'Dosis Mx'!$R$1:$X$19,6,FALSE),0) -> 300 | X9: =IFERROR(VLOOKUP(VLOOKUP(E9,'Dosis Mx'!$R$20:$X$36,1,FALSE),'Dosis Mx'!$R$20:$X$36,6,FALSE),0) -> 0 | Y9: =IFERROR(VLOOKUP(VLOOKUP(E9,'Dosis Mx'!$R$37:$X$54,1,FALSE),'Dosis Mx'!$R$37:$X$54,6,FALSE),0) -> 75 | Z9: =IFERROR(VLOOKUP(VLOOKUP(E9,'Dosis Mx'!$R$55:$X$78,1,FALSE),'Dosis Mx'!$R$55:$X$78,6,FALSE),0) -> 100 | AA9: =+F9*(24/H9) -> 500
A10: 7 | B10: 602-1 | C10: 1023640333 | D10: EMILY GUADALUPE VASQUEZ GOMEZ | E10: AMPIcilina Sodica/SULBactam Sodico 1000/500mg Polvo para iny (Ped) | F10: 800 | G10: MG | H10: 6 | I10: H | J10: I | L10: NA | S10: J189 | T10: NEUMONIA, NO ESPECIFICADA | U10: =+V10*(W10+X10+Y10+Z10) -> 3200 | V10: 16 | W10: =IFERROR(VLOOKUP(VLOOKUP(E10,'Dosis Mx'!$R$1:$X$19,1,FALSE),'Dosis Mx'!$R$1:$X$19,6,FALSE),0) -> 0 | X10: =IFERROR(VLOOKUP(VLOOKUP(E10,'Dosis Mx'!$R$20:$X$36,1,FALSE),'Dosis Mx'!$R$20:$X$36,6,FALSE),0) -> 0 | Y10: =IFERROR(VLOOKUP(VLOOKUP(E10,'Dosis Mx'!$R$37:$X$54,1,FALSE),'Dosis Mx'!$R$37:$X$54,6,FALSE),0) -> 200 | Z10: =IFERROR(VLOOKUP(VLOOKUP(E10,'Dosis Mx'!$R$55:$X$78,1,FALSE),'Dosis Mx'!$R$55:$X$78,6,FALSE),0) -> 0 | AA10: =+F10*(24/H10) -> 3200
A11: 8 | B11: 602-2 | C11: 1092958131 | D11: JAYLYN DANITZA SANTANDER ACEVEDO | E11: AZITromicina200mg/5 ml (4%)Polvo para reconstituirx15ml | F11: 320 | G11: MG | H11: 24 | I11: H | J11: I | L11: NA | S11: J22X | T11: INFECCION AGUDA NO ESPECIFICADA DE LAS VIAS RESPIRATORIAS INFERIORES | U11: =+V11*(W11+X11+Y11+Z11) -> 262.5 | V11: 35 | W11: =IFERROR(VLOOKUP(VLOOKUP(E11,'Dosis Mx'!$R$1:$X$19,1,FALSE),'Dosis Mx'!$R$1:$X$19,6,FALSE),0) -> 0 | X11: =IFERROR(VLOOKUP(VLOOKUP(E11,'Dosis Mx'!$R$20:$X$36,1,FALSE),'Dosis Mx'!$R$20:$X$36,6,FALSE),0) -> 0 | Y11: =IFERROR(VLOOKUP(VLOOKUP(E11,'Dosis Mx'!$R$37:$X$54,1,FALSE),'Dosis Mx'!$R$37:$X$54,6,FALSE),0) -> 7.5 | Z11: =IFERROR(VLOOKUP(VLOOKUP(E11,'Dosis Mx'!$R$55:$X$78,1,FALSE),'Dosis Mx'!$R$55:$X$78,6,FALSE),0) -> 0 | AA11: =+F11*(24/H11) -> 320
A12: 9 | B12: 602-6 | C12: 1025672317 | D12: ISABELLA CARDONA PAREJA | E12: AZITromicina200mg/5 ml (4%)Polvo para reconstituirx15ml | F12: 230 | G12: MG | H12: 24 | I12: H | J12: I | S12: J46X | T12: ESTADO ASMATICO | U12: =+V12*(W12+X12+Y12+Z12) -> 172.5 | V12: 23 | W12: =IFERROR(VLOOKUP(VLOOKUP(E12,'Dosis Mx'!$R$1:$X$19,1,FALSE),'Dosis Mx'!$R$1:$X$19,6,FALSE),0) -> 0 | X12: =IFERROR(VLOOKUP(VLOOKUP(E12,'Dosis Mx'!$R$20:$X$36,1,FALSE),'Dosis Mx'!$R$20:$X$36,6,FALSE),0) -> 0 | Y12: =IFERROR(VLOOKUP(VLOOKUP(E12,'Dosis Mx'!$R$37:$X$54,1,FALSE),'Dosis Mx'!$R$37:$X$54,6,FALSE),0) -> 7.5 | Z12: =IFERROR(VLOOKUP(VLOOKUP(E12,'Dosis Mx'!$R$55:$X$78,1,FALSE),'Dosis Mx'!$R$55:$X$78,6,FALSE),0) -> 0 | AA12: =+F12*(24/H12) -> 230
A13: 10 | B13: 603-4 | C13: 1011407824 | D13: CRISTIAN ALEJANDRO VARGAS TORRES | E13: AMPIcilina Sodica/SULBactam Sodico 1000/500mg Polvo para iny (Ped) | F13: 1300 | G13: MG | H13: 6 | I13: H | J13: I | S13: J22X | T13: INFECCION AGUDA NO ESPECIFICADA DE LAS VIAS RESPIRATORIAS INFERIORES | U13: =+V13*(W13+X13+Y13+Z13) -> 5900 | V13: 29.5 | W13: =IFERROR(VLOOKUP(VLOOKUP(E13,'Dosis Mx'!$R$1:$X$19,1,FALSE),'Dosis Mx'!$R$1:$X$19,6,FALSE),0) -> 0 | X13: =IFERROR(VLOOKUP(VLOOKUP(E13,'Dosis Mx'!$R$20:$X$36,1,FALSE),'Dosis Mx'!$R$20:$X$36,6,FALSE),0) -> 0 | Y13: =IFERROR(VLOOKUP(VLOOKUP(E13,'Dosis Mx'!$R$37:$X$54,1,FALSE),'Dosis Mx'!$R$37:$X$54,6,FALSE),0) -> 200 | Z13: =IFERROR(VLOOKUP(VLOOKUP(E13,'Dosis Mx'!$R$55:$X$78,1,FALSE),'Dosis Mx'!$R$55:$X$78,6,FALSE),0) -> 0 | AA13: =+F13*(24/H13) -> 5200
A14: 11 | B14: 603-6 | C14: 1034931139 | D14: ISAAC RODRIGUEZ MOLINA | E14: AMPIcilina 500 mg Polvo para Inyeccion | F14: 400 | G14: MG | H14: 6 | I14: H | J14: NI | M14: X | S14: J22X | T14: INFECCION AGUDA NO ESPECIFICADA DE LAS VIAS RESPIRATORIAS INFERIORES | U14: =+V14*(W14+X14+Y14+Z14) -> 3735 | V14: 8.3 | W14: =IFERROR(VLOOKUP(VLOOKUP(E14,'Dosis Mx'!$R$1:$X$19,1,FALSE),'Dosis Mx'!$R$1:$X$19,6,FALSE),0) -> 0 | X14: =IFERROR(VLOOKUP(VLOOKUP(E14,'Dosis Mx'!$R$20:$X$36,1,FALSE),'Dosis Mx'!$R$20:$X$36,6,FALSE),0) -> 0 | Y14: =IFERROR(VLOOKUP(VLOOKUP(E14,'Dosis Mx'!$R$37:$X$54,1,FALSE),'Dosis Mx'!$R$37:$X$54,6,FALSE),0) -> 200 | Z14: =IFERROR(VLOOKUP(VLOOKUP(E14,'Dosis Mx'!$R$55:$X$78,1,FALSE),'Dosis Mx'!$R$55:$X$78,6,FALSE),0) -> 250 | AA14: =+F14*(24/H14) -> 1600
A15: 12 | B15: 604-1 | C15: 1195217782 | D15: LIAM CHAVARRIA CHAVEZ | E15: Cefazolina 1000 mg Polvo para Inyeccion | F15: 420 | G15: MG | H15: 8 | I15: H | J15: I | M15: X | S15: J050 | T15: LARINGITIS OBSTRUCTIVA, AGUDA -CRUP- | U15: =+V15*(W15+X15+Y15+Z15) -> 1250 | V15: 12.5 | W15: =IFERROR(VLOOKUP(VLOOKUP(E15,'Dosis Mx'!$R$1:$X$19,1,FALSE),'Dosis Mx'!$R$1:$X$19,6,FALSE),0) -> 0 | X15: =IFERROR(VLOOKUP(VLOOKUP(E15,'Dosis Mx'!$R$20:$X$36,1,FALSE),'Dosis Mx'!$R$20:$X$36,6,FALSE),0) -> 100 | Y15: =IFERROR(VLOOKUP(VLOOKUP(E15,'Dosis Mx'!$R$37:$X$54,1,FALSE),'Dosis Mx'!$R$37:$X$54,6,FALSE),0) -> 0 | Z15: =IFERROR(VLOOKUP(VLOOKUP(E15,'Dosis Mx'!$R$55:$X$78,1,FALSE),'Dosis Mx'!$R$55:$X$78,6,FALSE),0) -> 0 | AA15: =+F15*(24/H15) -> 1260
A16: 13 | B16: 604-2 | C16: 1131204396 | D16: YANG ALEXANDER BETANCUR SUAREZ | E16: AMPIcilina 500 mg Polvo para Inyeccion | F16: 430 | G16: MG | H16: 6 | I16: H | J16: NI | M16: X | S16: J159 | T16: NEUMONIA BACTERIANA, NO ESPECIFICADA | U16: =+V16*(W16+X16+Y16+Z16) -> 3870 | V16: 8.6 | W16: =IFERROR(VLOOKUP(VLOOKUP(E16,'Dosis Mx'!$R$1:$X$19,1,FALSE),'Dosis Mx'!$R$1:$X$19,6,FALSE),0) -> 0 | X16: =IFERROR(VLOOKUP(VLOOKUP(E16,'Dosis Mx'!$R$20:$X$36,1,FALSE),'Dosis Mx'!$R$20:$X$36,6,FALSE),0) -> 0 | Y16: =IFERROR(VLOOKUP(VLOOKUP(E16,'Dosis Mx'!$R$37:$X$54,1,FALSE),'Dosis Mx'!$R$37:$X$54,6,FALSE),0) -> 200 | Z16: =IFERROR(VLOOKUP(VLOOKUP(E16,'Dosis Mx'!$R$55:$X$78,1,FALSE),'Dosis Mx'!$R$55:$X$78,6,FALSE),0) -> 250 | AA16: =+F16*(24/H16) -> 1720
A17: 14 | B17: 604-3 | C17: 1013381216 | D17: EMILY LOPERA MURILLO | E17: AMIKacina (Sulfato) 100 mg/2 ml Solucion Inyectable | F17: 82 | G17: MG | H17: 24 | I17: H | K17: I | L17: X | R17: CAMBIO CEFAZOLINA | S17: N390 | T17: INFECCION DE VIAS URINARIAS, SITIO NO ESPECIFICADO | U17: =+V17*(W17+X17+Y17+Z17) -> 178.75 | V17: 5.5 | W17: =IFERROR(VLOOKUP(VLOOKUP(E17,'Dosis Mx'!$R$1:$X$19,1,FALSE),'Dosis Mx'!$R$1:$X$19,6,FALSE),0) -> 15 | X17: =IFERROR(VLOOKUP(VLOOKUP(E17,'Dosis Mx'!$R$20:$X$36,1,FALSE),'Dosis Mx'!$R$20:$X$36,6,FALSE),0) -> 0 | Y17: =IFERROR(VLOOKUP(VLOOKUP(E17,'Dosis Mx'!$R$37:$X$54,1,FALSE),'Dosis Mx'!$R$37:$X$54,6,FALSE),0) -> 0 | Z17: =IFERROR(VLOOKUP(VLOOKUP(E17,'Dosis Mx'!$R$55:$X$78,1,FALSE),'Dosis Mx'!$R$55:$X$78,6,FALSE),0) -> 17.5 | AA17: =+F17*(24/H17) -> 82
A18: 15 | B18: 604-4 | C18: 1023666392 | D18: HELLEN MONSALVE TEJADA | E18: AMPIcilina Sodica/SULBactam Sodico 1000/500mg Polvo para iny (Ped) | F18: 350 | G18: MG | H18: 6 | I18: H | S18: J019 | T18: SINUSITIS AGUDA, NO ESPECIFICADA | U18: =+V18*(W18+X18+Y18+Z18) -> 1400 | V18: 7 | W18: =IFERROR(VLOOKUP(VLOOKUP(E18,'Dosis Mx'!$R$1:$X$19,1,FALSE),'Dosis Mx'!$R$1:$X$19,6,FALSE),0) -> 0 | X18: =IFERROR(VLOOKUP(VLOOKUP(E18,'Dosis Mx'!$R$20:$X$36,1,FALSE),'Dosis Mx'!$R$20:$X$36,6,FALSE),0) -> 0 | Y18: =IFERROR(VLOOKUP(VLOOKUP(E18,'Dosis Mx'!$R$37:$X$54,1,FALSE),'Dosis Mx'!$R$37:$X$54,6,FALSE),0) -> 200 | Z18: =IFERROR(VLOOKUP(VLOOKUP(E18,'Dosis Mx'!$R$55:$X$78,1,FALSE),'Dosis Mx'!$R$55:$X$78,6,FALSE),0) -> 0 | AA18: =+F18*(24/H18) -> 1400
A19: 16 | B19: 604-5 | C19: 1034928164 | D19: ISABELLA LONDOÑO SUAREZ | E19: AMPIcilina Sodica/SULBactam Sodico 1000/500mg Polvo para iny (Ped) | F19: 750 | G19: MG | H19: 6 | I19: H | S19: J189 | T19: NEUMONIA, NO ESPECIFICADA | U19: =+V19*(W19+X19+Y19+Z19) -> 3000 | V19: 15 | W19: =IFERROR(VLOOKUP(VLOOKUP(E19,'Dosis Mx'!$R$1:$X$19,1,FALSE),'Dosis Mx'!$R$1:$X$19,6,FALSE),0) -> 0 | X19: =IFERROR(VLOOKUP(VLOOKUP(E19,'Dosis Mx'!$R$20:$X$36,1,FALSE),'Dosis Mx'!$R$20:$X$36,6,FALSE),0) -> 0 | Y19: =IFERROR(VLOOKUP(VLOOKUP(E19,'Dosis Mx'!$R$37:$X$54,1,FALSE),'Dosis Mx'!$R$37:$X$54,6,FALSE),0) -> 200 | Z19: =IFERROR(VLOOKUP(VLOOKUP(E19,'Dosis Mx'!$R$55:$X$78,1,FALSE),'Dosis Mx'!$R$55:$X$78,6,FALSE),0) -> 0 | AA19: =+F19*(24/H19) -> 3000
A20: 17 | B20: 604-6 | C20: 1023650756 | D20: ISABELLA PALACIOS PEREA | E20: AZITromicina200mg/5 ml (4%)Polvo para reconstituirx15ml | F20: 235 | G20: MG | H20: 24 | I20: H | S20: J46X | T20: ESTADO ASMATICO | U20: =+V20*(W20+X20+Y20+Z20) -> 176.25 | V20: 23.5 | W20: =IFERROR(VLOOKUP(VLOOKUP(E20,'Dosis Mx'!$R$1:$X$19,1,FALSE),'Dosis Mx'!$R$1:$X$19,6,FALSE),0) -> 0 | X20: =IFERROR(VLOOKUP(VLOOKUP(E20,'Dosis Mx'!$R$20:$X$36,1,FALSE),'Dosis Mx'!$R$20:$X$36,6,FALSE),0) -> 0 | Y20: =IFERROR(VLOOKUP(VLOOKUP(E20,'Dosis Mx'!$R$37:$X$54,1,FALSE),'Dosis Mx'!$R$37:$X$54,6,FALSE),0) -> 7.5 | Z20: =IFERROR(VLOOKUP(VLOOKUP(E20,'Dosis Mx'!$R$55:$X$78,1,FALSE),'Dosis Mx'!$R$55:$X$78,6,FALSE),0) -> 0 | AA20: =+F20*(24/H20) -> 235
A21: 18 | B21: 605-2 | C21: 1033826347 | D21: SAHARA VALENTINA AVILA RESTREPO | E21: AMPIcilina (Sal Sodica) x 1000 mg Polvo para Inyeccion | F21: 900 | G21: MG | H21: 6 | I21: H | R21: ALTA | S21: J159 | T21: NEUMONIA BACTERIANA, NO ESPECIFICADA | U21: =+V21*(W21+X21+Y21+Z21) -> 8100 | V21: 18 | W21: =IFERROR(VLOOKUP(VLOOKUP(E21,'Dosis Mx'!$R$1:$X$19,1,FALSE),'Dosis Mx'!$R$1:$X$19,6,FALSE),0) -> 0 | X21: =IFERROR(VLOOKUP(VLOOKUP(E21,'Dosis Mx'!$R$20:$X$36,1,FALSE),'Dosis Mx'!$R$20:$X$36,6,FALSE),0) -> 0 | Y21: =IFERROR(VLOOKUP(VLOOKUP(E21,'Dosis Mx'!$R$37:$X$54,1,FALSE),'Dosis Mx'!$R$37:$X$54,6,FALSE),0) -> 200 | Z21: =IFERROR(VLOOKUP(VLOOKUP(E21,'Dosis Mx'!$R$55:$X$78,1,FALSE),'Dosis Mx'!$R$55:$X$78,6,FALSE),0) -> 250 | AA21: =+F21*(24/H21) -> 3600
A22: 19 | B22: 605-4 | C22: 1036962230 | D22: LUIS CRISTOBAL AGUIRRE AREIZA | E22: AMPIcilina Sodica/SULBactam Sodico 1000/500mg Polvo para iny (Ped) | F22: 950 | G22: MG | H22: 6 | I22: H | J22: I | S22: J189 | T22: NEUMONIA, NO ESPECIFICADA | U22: =+V22*(W22+X22+Y22+Z22) -> 3800 | V22: 19 | W22: =IFERROR(VLOOKUP(VLOOKUP(E22,'Dosis Mx'!$R$1:$X$19,1,FALSE),'Dosis Mx'!$R$1:$X$19,6,FALSE),0) -> 0 | X22: =IFERROR(VLOOKUP(VLOOKUP(E22,'Dosis Mx'!$R$20:$X$36,1,FALSE),'Dosis Mx'!$R$20:$X$36,6,FALSE),0) -> 0 | Y22: =IFERROR(VLOOKUP(VLOOKUP(E22,'Dosis Mx'!$R$37:$X$54,1,FALSE),'Dosis Mx'!$R$37:$X$54,6,FALSE),0) -> 200 | Z22: =IFERROR(VLOOKUP(VLOOKUP(E22,'Dosis Mx'!$R$55:$X$78,1,FALSE),'Dosis Mx'!$R$55:$X$78,6,FALSE),0) -> 0 | AA22: =+F22*(24/H22) -> 3800
A23: 20 | B23: 605-5 | C23: 1041460260 | D23: VALENTINA ALVARAN JIMENEZ | E23: AMPIcilina (Sal Sodica) x 1000 mg Polvo para Inyeccion | F23: 2000 | G23: MG | H23: 6 | I23: H | J23: I | L23: NO | S23: J189 | T23: NEUMONIA, NO ESPECIFICADA | U23: =+V23*(W23+X23+Y23+Z23) -> 23400 | V23: 52 | W23: =IFERROR(VLOOKUP(VLOOKUP(E23,'Dosis Mx'!$R$1:$X$19,1,FALSE),'Dosis Mx'!$R$1:$X$19,6,FALSE),0) -> 0 | X23: =IFERROR(VLOOKUP(VLOOKUP(E23,'Dosis Mx'!$R$20:$X$36,1,FALSE),'Dosis Mx'!$R$20:$X$36,6,FALSE),0) -> 0 | Y23: =IFERROR(VLOOKUP(VLOOKUP(E23,'Dosis Mx'!$R$37:$X$54,1,FALSE),'Dosis Mx'!$R$37:$X$54,6,FALSE),0) -> 200 | Z23: =IFERROR(VLOOKUP(VLOOKUP(E23,'Dosis Mx'!$R$55:$X$78,1,FALSE),'Dosis Mx'!$R$55:$X$78,6,FALSE),0) -> 250 | AA23: =+F23*(24/H23) -> 8000
A24: 21 | B24: 605-5 | C24: 1041460260 | D24: VALENTINA ALVARAN JIMENEZ | E24: AZITromicina 500 mg Tableta | F24: 500 | G24: MG | H24: 24 | I24: H | J24: I | L24: NO | S24: J189 | T24: NEUMONIA, NO ESPECIFICADA | U24: =+V24*(W24+X24+Y24+Z24) -> 390 | V24: 52 | W24: =IFERROR(VLOOKUP(VLOOKUP(E24,'Dosis Mx'!$R$1:$X$19,1,FALSE),'Dosis Mx'!$R$1:$X$19,6,FALSE),0) -> 0 | X24: =IFERROR(VLOOKUP(VLOOKUP(E24,'Dosis Mx'!$R$20:$X$36,1,FALSE),'Dosis Mx'!$R$20:$X$36,6,FALSE),0) -> 0 | Y24: =IFERROR(VLOOKUP(VLOOKUP(E24,'Dosis Mx'!$R$37:$X$54,1,FALSE),'Dosis Mx'!$R$37:$X$54,6,FALSE),0) -> 7.5 | Z24: =IFERROR(VLOOKUP(VLOOKUP(E24,'Dosis Mx'!$R$55:$X$78,1,FALSE),'Dosis Mx'!$R$55:$X$78,6,FALSE),0) -> 0 | AA24: =+F24*(24/H24) -> 500
A25: 22 | B25: 606-4 | C25: 1039478496 | D25: QUENEDI ALEJANDRO BAILARIN DUARTE | E25: AMPIcilina (Sal Sodica) x 1000 mg Polvo para Inyeccion | F25: 1700 | G25: MG | H25: 6 | I25: H | J25: NI | L25: NA | M25: X | S25: N009 | T25: SINDROME NEFRITICO AGUDO, NO ESPECIFICADA | U25: =+V25*(W25+X25+Y25+Z25) -> 15030 | V25: 33.4 | W25: =IFERROR(VLOOKUP(VLOOKUP(E25,'Dosis Mx'!$R$1:$X$19,1,FALSE),'Dosis Mx'!$R$1:$X$19,6,FALSE),0) -> 0 | X25: =IFERROR(VLOOKUP(VLOOKUP(E25,'Dosis Mx'!$R$20:$X$36,1,FALSE),'Dosis Mx'!$R$20:$X$36,6,FALSE),0) -> 0 | Y25: =IFERROR(VLOOKUP(VLOOKUP(E25,'Dosis Mx'!$R$37:$X$54,1,FALSE),'Dosis Mx'!$R$37:$X$54,6,FALSE),0) -> 200 | Z25: =IFERROR(VLOOKUP(VLOOKUP(E25,'Dosis Mx'!$R$55:$X$78,1,FALSE),'Dosis Mx'!$R$55:$X$78,6,FALSE),0) -> 250 | AA25: =+F25*(24/H25) -> 6800
A26: 23 | B26: 606-6 | C26: 6518714 | D26: BENJAMIN RAUL HERNANDEZ GARCIA | E26: AZITromicina200mg/5 ml (4%)Polvo para reconstituirx15ml | F26: 150 | G26: MG | H26: 24 | I26: H | J26: NI | L26: NA | M26: X | S26: J46X | T26: ESTADO ASMATICO | U26: =+V26*(W26+X26+Y26+Z26) -> 110.25 | V26: 14.7 | W26: =IFERROR(VLOOKUP(VLOOKUP(E26,'Dosis Mx'!$R$1:$X$19,1,FALSE),'Dosis Mx'!$R$1:$X$19,6,FALSE),0) -> 0 | X26: =IFERROR(VLOOKUP(VLOOKUP(E26,'Dosis Mx'!$R$20:$X$36,1,FALSE),'Dosis Mx'!$R$20:$X$36,6,FALSE),0) -> 0 | Y26: =IFERROR(VLOOKUP(VLOOKUP(E26,'Dosis Mx'!$R$37:$X$54,1,FALSE),'Dosis Mx'!$R$37:$X$54,6,FALSE),0) -> 7.5 | Z26: =IFERROR(VLOOKUP(VLOOKUP(E26,'Dosis Mx'!$R$55:$X$78,1,FALSE),'Dosis Mx'!$R$55:$X$78,6,FALSE),0) -> 0 | AA26: =+F26*(24/H26) -> 150
A27: 24 | B27: Aisl 600 | C27: 1038145231 | D27: MARTIN ALEJANDRO LONDOÑO JARAMILLO | E27: AMPIcilina Sodica/SULBactam Sodico 1000/500mg Polvo para iny (Ped) | F27: 800 | G27: MG | H27: 6 | I27: H | J27: I | S27: R599 | T27: ADENOMEGALIA, NO ESPECIFICADA | U27: =+V27*(W27+X27+Y27+Z27) -> 3200 | V27: 16 | W27: =IFERROR(VLOOKUP(VLOOKUP(E27,'Dosis Mx'!$R$1:$X$19,1,FALSE),'Dosis Mx'!$R$1:$X$19,6,FALSE),0) -> 0 | X27: =IFERROR(VLOOKUP(VLOOKUP(E27,'Dosis Mx'!$R$20:$X$36,1,FALSE),'Dosis Mx'!$R$20:$X$36,6,FALSE),0) -> 0 | Y27: =IFERROR(VLOOKUP(VLOOKUP(E27,'Dosis Mx'!$R$37:$X$54,1,FALSE),'Dosis Mx'!$R$37:$X$54,6,FALSE),0) -> 200 | Z27: =IFERROR(VLOOKUP(VLOOKUP(E27,'Dosis Mx'!$R$55:$X$78,1,FALSE),'Dosis Mx'!$R$55:$X$78,6,FALSE),0) -> 0 | AA27: =+F27*(24/H27) -> 3200
A28: 25 | B28: UCE 03 | C28: 1044936783 | D28: SAIFER DAVID SIMANCAS PAJARO | E28: AZITromicina200mg/5 ml (4%)Polvo para reconstituirx15ml | F28: 300 | G28: MG | H28: 24 | I28: H | J28: I | S28: J159 | T28: NEUMONIA BACTERIANA, NO ESPECIFICADA | U28: =+V28*(W28+X28+Y28+Z28) -> 232.5 | V28: 31 | W28: =IFERROR(VLOOKUP(VLOOKUP(E28,'Dosis Mx'!$R$1:$X$19,1,FALSE),'Dosis Mx'!$R$1:$X$19,6,FALSE),0) -> 0 | X28: =IFERROR(VLOOKUP(VLOOKUP(E28,'Dosis Mx'!$R$20:$X$36,1,FALSE),'Dosis Mx'!$R$20:$X$36,6,FALSE),0) -> 0 | Y28: =IFERROR(VLOOKUP(VLOOKUP(E28,'Dosis Mx'!$R$37:$X$54,1,FALSE),'Dosis Mx'!$R$37:$X$54,6,FALSE),0) -> 7.5 | Z28: =IFERROR(VLOOKUP(VLOOKUP(E28,'Dosis Mx'!$R$55:$X$78,1,FALSE),'Dosis Mx'!$R$55:$X$78,6,FALSE),0) -> 0 | AA28: =+F28*(24/H28) -> 300
A29: 26 | B29: UCE 06 | C29: 1155216942 | D29: KAROL DAYANA POSSO ORTIZ | E29: Oxacilina (Sal Sodica) 1000 mg Polvo para Inyeccion | F29: 2000 | G29: MG | H29: 6 | I29: H | J29: I | S29: A972 | T29: DENGUE SEVERO | U29: =+V29*(W29+X29+Y29+Z29) -> 18000 | V29: 45 | W29: =IFERROR(VLOOKUP(VLOOKUP(E29,'Dosis Mx'!$R$1:$X$19,1,FALSE),'Dosis Mx'!$R$1:$X$19,6,FALSE),0) -> 0 | X29: =IFERROR(VLOOKUP(VLOOKUP(E29,'Dosis Mx'!$R$20:$X$36,1,FALSE),'Dosis Mx'!$R$20:$X$36,6,FALSE),0) -> 200 | Y29: =IFERROR(VLOOKUP(VLOOKUP(E29,'Dosis Mx'!$R$37:$X$54,1,FALSE),'Dosis Mx'!$R$37:$X$54,6,FALSE),0) -> 0 | Z29: =IFERROR(VLOOKUP(VLOOKUP(E29,'Dosis Mx'!$R$55:$X$78,1,FALSE),'Dosis Mx'!$R$55:$X$78,6,FALSE),0) -> 200 | AA29: =+F29*(24/H29) -> 8000
A30: 27 | B30: UCE 06 | C30: 1155216942 | D30: KAROL DAYANA POSSO ORTIZ | E30: Ceftriaxona (Sal Sodica) 1000 mg Polvo para Inyeccion | F30: 2000 | G30: MG | H30: 24 | I30: H | J30: I | M30: X | S30: A972 | T30: DENGUE SEVERO | U30: =+V30*(W30+X30+Y30+Z30) -> 21375 | V30: 45 | W30: =IFERROR(VLOOKUP(VLOOKUP(E30,'Dosis Mx'!$R$1:$X$19,1,FALSE),'Dosis Mx'!$R$1:$X$19,6,FALSE),0) -> 300 | X30: =IFERROR(VLOOKUP(VLOOKUP(E30,'Dosis Mx'!$R$20:$X$36,1,FALSE),'Dosis Mx'!$R$20:$X$36,6,FALSE),0) -> 0 | Y30: =IFERROR(VLOOKUP(VLOOKUP(E30,'Dosis Mx'!$R$37:$X$54,1,FALSE),'Dosis Mx'!$R$37:$X$54,6,FALSE),0) -> 75 | Z30: =IFERROR(VLOOKUP(VLOOKUP(E30,'Dosis Mx'!$R$55:$X$78,1,FALSE),'Dosis Mx'!$R$55:$X$78,6,FALSE),0) -> 100 | AA30: =+F30*(24/H30) -> 2000
A31: 28 | B31: UCI 08 | C31: 1015189102 | D31: JUAN MANUEL MONTOYA RODRIGUEZ | E31: Ceftriaxona (Sal Sodica) 1000 mg Polvo para Inyeccion | F31: 2000 | G31: MG | H31: 24 | I31: H | K31: I | L31: X | S31: A279 | T31: LEPTOSPIROSIS, NO ESPECIFICADA | U31: =+V31*(W31+X31+Y31+Z31) -> 26600 | V31: 56 | W31: =IFERROR(VLOOKUP(VLOOKUP(E31,'Dosis Mx'!$R$1:$X$19,1,FALSE),'Dosis Mx'!$R$1:$X$19,6,FALSE),0) -> 300 | X31: =IFERROR(VLOOKUP(VLOOKUP(E31,'Dosis Mx'!$R$20:$X$36,1,FALSE),'Dosis Mx'!$R$20:$X$36,6,FALSE),0) -> 0 | Y31: =IFERROR(VLOOKUP(VLOOKUP(E31,'Dosis Mx'!$R$37:$X$54,1,FALSE),'Dosis Mx'!$R$37:$X$54,6,FALSE),0) -> 75 | Z31: =IFERROR(VLOOKUP(VLOOKUP(E31,'Dosis Mx'!$R$55:$X$78,1,FALSE),'Dosis Mx'!$R$55:$X$78,6,FALSE),0) -> 100 | AA31: =+F31*(24/H31) -> 2000
A32: 29 | U32: =+V32*(W32+X32+Y32+Z32) -> 0 | W32: =IFERROR(VLOOKUP(VLOOKUP(E32,'Dosis Mx'!$R$1:$X$19,1,FALSE),'Dosis Mx'!$R$1:$X$19,6,FALSE),0) -> 0 | X32: =IFERROR(VLOOKUP(VLOOKUP(E32,'Dosis Mx'!$R$20:$X$36,1,FALSE),'Dosis Mx'!$R$20:$X$36,6,FALSE),0) -> 0 | Y32: =IFERROR(VLOOKUP(VLOOKUP(E32,'Dosis Mx'!$R$37:$X$54,1,FALSE),'Dosis Mx'!$R$37:$X$54,6,FALSE),0) -> 0 | Z32: =IFERROR(VLOOKUP(VLOOKUP(E32,'Dosis Mx'!$R$55:$X$78,1,FALSE),'Dosis Mx'!$R$55:$X$78,6,FALSE),0) -> 0 | AA32: =+F32*(24/H32) -> #DIV/0!
A33: No | B33: Servicio | C33: Docidentidad | D33: Usuario | E33: Nombre | F33: Dosis | G33: Medidadosis | H33: Frecuencia | I33: Unidadfrecuencia | J33: Tto Empirico | K33: Tto Dirigido | L33: cultivo | M33: Suspender | N33: Cambiar | R33: Observacionesorden | S33: Codigo Diagnostico | T33: Diagnostico | U33: Dosis | V33: Peso(kg) | W33: ITU | X33: ITB | Y33: NEUMONIA | Z33: MENINGITIS | AA33: Dosis recetada
N34: Escalar | O34: Desescalar | P34: RXN adversa | Q34: Por dosis
A35: 30 | U35: =+V35*(W35+X35+Y35+Z35) -> 0 | W35: =IFERROR(VLOOKUP(VLOOKUP(E35,'Dosis Mx'!$R$1:$X$19,1,FALSE),'Dosis Mx'!$R$1:$X$19,6,FALSE),0) -> 0 | X35: =IFERROR(VLOOKUP(VLOOKUP(E35,'Dosis Mx'!$R$20:$X$36,1,FALSE),'Dosis Mx'!$R$20:$X$36,6,FALSE),0) -> 0 | Y35: =IFERROR(VLOOKUP(VLOOKUP(E35,'Dosis Mx'!$R$37:$X$54,1,FALSE),'Dosis Mx'!$R$37:$X$54,6,FALSE),0) -> 0 | Z35: =IFERROR(VLOOKUP(VLOOKUP(E35,'Dosis Mx'!$R$55:$X$78,1,FALSE),'Dosis Mx'!$R$55:$X$78,6,FALSE),0) -> 0 | AA35: =+F35*(24/H35) -> #DIV/0!
A36: 31 | U36: =+V36*(W36+X36+Y36+Z36) -> 0 | W36: =IFERROR(VLOOKUP(VLOOKUP(E36,'Dosis Mx'!$R$1:$X$19,1,FALSE),'Dosis Mx'!$R$1:$X$19,6,FALSE),0) -> 0 | X36: =IFERROR(VLOOKUP(VLOOKUP(E36,'Dosis Mx'!$R$20:$X$36,1,FALSE),'Dosis Mx'!$R$20:$X$36,6,FALSE),0) -> 0 | Y36: =IFERROR(VLOOKUP(VLOOKUP(E36,'Dosis Mx'!$R$37:$X$54,1,FALSE),'Dosis Mx'!$R$37:$X$54,6,FALSE),0) -> 0 | Z36: =IFERROR(VLOOKUP(VLOOKUP(E36,'Dosis Mx'!$R$55:$X$78,1,FALSE),'Dosis Mx'!$R$55:$X$78,6,FALSE),0) -> 0 | AA36: =+F36*(24/H36) -> #DIV/0!
A37: 32 | U37: =+V37*(W37+X37+Y37+Z37) -> 0 | W37: =IFERROR(VLOOKUP(VLOOKUP(E37,'Dosis Mx'!$R$1:$X$19,1,FALSE),'Dosis Mx'!$R$1:$X$19,6,FALSE),0) -> 0 | X37: =IFERROR(VLOOKUP(VLOOKUP(E37,'Dosis Mx'!$R$20:$X$36,1,FALSE),'Dosis Mx'!$R$20:$X$36,6,FALSE),0) -> 0 | Y37: =IFERROR(VLOOKUP(VLOOKUP(E37,'Dosis Mx'!$R$37:$X$54,1,FALSE),'Dosis Mx'!$R$37:$X$54,6,FALSE),0) -> 0 | Z37: =IFERROR(VLOOKUP(VLOOKUP(E37,'Dosis Mx'!$R$55:$X$78,1,FALSE),'Dosis Mx'!$R$55:$X$78,6,FALSE),0) -> 0 | AA37: =+F37*(24/H37) -> #DIV/0!
A38: 33 | U38: =+V38*(W38+X38+Y38+Z38) -> 0 | W38: =IFERROR(VLOOKUP(VLOOKUP(E38,'Dosis Mx'!$R$1:$X$19,1,FALSE),'Dosis Mx'!$R$1:$X$19,6,FALSE),0) -> 0 | X38: =IFERROR(VLOOKUP(VLOOKUP(E38,'Dosis Mx'!$R$20:$X$36,1,FALSE),'Dosis Mx'!$R$20:$X$36,6,FALSE),0) -> 0 | Y38: =IFERROR(VLOOKUP(VLOOKUP(E38,'Dosis Mx'!$R$37:$X$54,1,FALSE),'Dosis Mx'!$R$37:$X$54,6,FALSE),0) -> 0 | Z38: =IFERROR(VLOOKUP(VLOOKUP(E38,'Dosis Mx'!$R$55:$X$78,1,FALSE),'Dosis Mx'!$R$55:$X$78,6,FALSE),0) -> 0 | AA38: =+F38*(24/H38) -> #DIV/0!
A39: 34 | U39: =+V39*(W39+X39+Y39+Z39) -> 0 | W39: =IFERROR(VLOOKUP(VLOOKUP(E39,'Dosis Mx'!$R$1:$X$19,1,FALSE),'Dosis Mx'!$R$1:$X$19,6,FALSE),0) -> 0 | X39: =IFERROR(VLOOKUP(VLOOKUP(E39,'Dosis Mx'!$R$20:$X$36,1,FALSE),'Dosis Mx'!$R$20:$X$36,6,FALSE),0) -> 0 | Y39: =IFERROR(VLOOKUP(VLOOKUP(E39,'Dosis Mx'!$R$37:$X$54,1,FALSE),'Dosis Mx'!$R$37:$X$54,6,FALSE),0) -> 0 | Z39: =IFERROR(VLOOKUP(VLOOKUP(E39,'Dosis Mx'!$R$55:$X$78,1,FALSE),'Dosis Mx'!$R$55:$X$78,6,FALSE),0) -> 0 | AA39: =+F39*(24/H39) -> #DIV/0!
A40: 35 | U40: =+V40*(W40+X40+Y40+Z40) -> 0 | W40: =IFERROR(VLOOKUP(VLOOKUP(E40,'Dosis Mx'!$R$1:$X$19,1,FALSE),'Dosis Mx'!$R$1:$X$19,6,FALSE),0) -> 0 | X40: =IFERROR(VLOOKUP(VLOOKUP(E40,'Dosis Mx'!$R$20:$X$36,1,FALSE),'Dosis Mx'!$R$20:$X$36,6,FALSE),0) -> 0 | Y40: =IFERROR(VLOOKUP(VLOOKUP(E40,'Dosis Mx'!$R$37:$X$54,1,FALSE),'Dosis Mx'!$R$37:$X$54,6,FALSE),0) -> 0 | Z40: =IFERROR(VLOOKUP(VLOOKUP(E40,'Dosis Mx'!$R$55:$X$78,1,FALSE),'Dosis Mx'!$R$55:$X$78,6,FALSE),0) -> 0 | AA40: =+F40*(24/H40) -> #DIV/0!
A41: 36 | U41: =+V41*(W41+X41+Y41+Z41) -> 0 | W41: =IFERROR(VLOOKUP(VLOOKUP(E41,'Dosis Mx'!$R$1:$X$19,1,FALSE),'Dosis Mx'!$R$1:$X$19,6,FALSE),0) -> 0 | X41: =IFERROR(VLOOKUP(VLOOKUP(E41,'Dosis Mx'!$R$20:$X$36,1,FALSE),'Dosis Mx'!$R$20:$X$36,6,FALSE),0) -> 0 | Y41: =IFERROR(VLOOKUP(VLOOKUP(E41,'Dosis Mx'!$R$37:$X$54,1,FALSE),'Dosis Mx'!$R$37:$X$54,6,FALSE),0) -> 0 | Z41: =IFERROR(VLOOKUP(VLOOKUP(E41,'Dosis Mx'!$R$55:$X$78,1,FALSE),'Dosis Mx'!$R$55:$X$78,6,FALSE),0) -> 0 | AA41: =+F41*(24/H41) -> #DIV/0!
A42: 37 | U42: =+V42*(W42+X42+Y42+Z42) -> 0 | W42: =IFERROR(VLOOKUP(VLOOKUP(E42,'Dosis Mx'!$R$1:$X$19,1,FALSE),'Dosis Mx'!$R$1:$X$19,6,FALSE),0) -> 0 | X42: =IFERROR(VLOOKUP(VLOOKUP(E42,'Dosis Mx'!$R$20:$X$36,1,FALSE),'Dosis Mx'!$R$20:$X$36,6,FALSE),0) -> 0 | Y42: =IFERROR(VLOOKUP(VLOOKUP(E42,'Dosis Mx'!$R$37:$X$54,1,FALSE),'Dosis Mx'!$R$37:$X$54,6,FALSE),0) -> 0 | Z42: =IFERROR(VLOOKUP(VLOOKUP(E42,'Dosis Mx'!$R$55:$X$78,1,FALSE),'Dosis Mx'!$R$55:$X$78,6,FALSE),0) -> 0 | AA42: =+F42*(24/H42) -> #DIV/0!
A43: 38 | U43: =+V43*(W43+X43+Y43+Z43) -> 0 | W43: =IFERROR(VLOOKUP(VLOOKUP(E43,'Dosis Mx'!$R$1:$X$19,1,FALSE),'Dosis Mx'!$R$1:$X$19,6,FALSE),0) -> 0 | X43: =IFERROR(VLOOKUP(VLOOKUP(E43,'Dosis Mx'!$R$20:$X$36,1,FALSE),'Dosis Mx'!$R$20:$X$36,6,FALSE),0) -> 0 | Y43: =IFERROR(VLOOKUP(VLOOKUP(E43,'Dosis Mx'!$R$37:$X$54,1,FALSE),'Dosis Mx'!$R$37:$X$54,6,FALSE),0) -> 0 | Z43: =IFERROR(VLOOKUP(VLOOKUP(E43,'Dosis Mx'!$R$55:$X$78,1,FALSE),'Dosis Mx'!$R$55:$X$78,6,FALSE),0) -> 0 | AA43: =+F43*(24/H43) -> #DIV/0!
A44: 39 | U44: =+V44*(W44+X44+Y44+Z44) -> 0 | W44: =IFERROR(VLOOKUP(VLOOKUP(E44,'Dosis Mx'!$R$1:$X$19,1,FALSE),'Dosis Mx'!$R$1:$X$19,6,FALSE),0) -> 0 | X44: =IFERROR(VLOOKUP(VLOOKUP(E44,'Dosis Mx'!$R$20:$X$36,1,FALSE),'Dosis Mx'!$R$20:$X$36,6,FALSE),0) -> 0 | Y44: =IFERROR(VLOOKUP(VLOOKUP(E44,'Dosis Mx'!$R$37:$X$54,1,FALSE),'Dosis Mx'!$R$37:$X$54,6,FALSE),0) -> 0 | Z44: =IFERROR(VLOOKUP(VLOOKUP(E44,'Dosis Mx'!$R$55:$X$78,1,FALSE),'Dosis Mx'!$R$55:$X$78,6,FALSE),0) -> 0 | AA44: =+F44*(24/H44) -> #DIV/0!
A45: 40 | U45: =+V45*(W45+X45+Y45+Z45) -> 0 | W45: =IFERROR(VLOOKUP(VLOOKUP(E45,'Dosis Mx'!$R$1:$X$19,1,FALSE),'Dosis Mx'!$R$1:$X$19,6,FALSE),0) -> 0 | X45: =IFERROR(VLOOKUP(VLOOKUP(E45,'Dosis Mx'!$R$20:$X$36,1,FALSE),'Dosis Mx'!$R$20:$X$36,6,FALSE),0) -> 0 | Y45: =IFERROR(VLOOKUP(VLOOKUP(E45,'Dosis Mx'!$R$37:$X$54,1,FALSE),'Dosis Mx'!$R$37:$X$54,6,FALSE),0) -> 0 | Z45: =IFERROR(VLOOKUP(VLOOKUP(E45,'Dosis Mx'!$R$55:$X$78,1,FALSE),'Dosis Mx'!$R$55:$X$78,6,FALSE),0) -> 0 | AA45: =+F45*(24/H45) -> #DIV/0!
A46: 41 | U46: =+V46*(W46+X46+Y46+Z46) -> 0 | W46: =IFERROR(VLOOKUP(VLOOKUP(E46,'Dosis Mx'!$R$1:$X$19,1,FALSE),'Dosis Mx'!$R$1:$X$19,6,FALSE),0) -> 0 | X46: =IFERROR(VLOOKUP(VLOOKUP(E46,'Dosis Mx'!$R$20:$X$36,1,FALSE),'Dosis Mx'!$R$20:$X$36,6,FALSE),0) -> 0 | Y46: =IFERROR(VLOOKUP(VLOOKUP(E46,'Dosis Mx'!$R$37:$X$54,1,FALSE),'Dosis Mx'!$R$37:$X$54,6,FALSE),0) -> 0 | Z46: =IFERROR(VLOOKUP(VLOOKUP(E46,'Dosis Mx'!$R$55:$X$78,1,FALSE),'Dosis Mx'!$R$55:$X$78,6,FALSE),0) -> 0 | AA46: =+F46*(24/H46) -> #DIV/0!
... A63: 58 | U63: =+V63*(W63+X63+Y63+Z63) -> 0 | W63: =IFERROR(VLOOKUP(VLOOKUP(E63,'Dosis Mx'!$R$1:$X$19,1,FALSE),'Dosis Mx'!$R$1:$X$19,6,FALSE),0) -> 0 | X63: =IFERROR(VLOOKUP(VLOOKUP(E63,'Dosis Mx'!$R$20:$X$36,1,FALSE),'Dosis Mx'!$R$20:$X$36,6,FALSE),0) -> 0 | Y63: =IFERROR(VLOOKUP(VLOOKUP(E63,'Dosis Mx'!$R$37:$X$54,1,FALSE),'Dosis Mx'!$R$37:$X$54,6,FALSE),0) -> 0 | Z63: =IFERROR(VLOOKUP(VLOOKUP(E63,'Dosis Mx'!$R$55:$X$78,1,FALSE),'Dosis Mx'!$R$55:$X$78,6,FALSE),0) -> 0 | AA63: =+F63*(24/H63) -> #DIV/0!

Sheet 27-10-2023
B1: FECHA | C1: 45226
A2: No | B2: Servicio | C2: Docidentidad | D2: Usuario | E2: Nombre | F2: Dosis | G2: Medidadosis | H2: Frecuencia | I2: Unidadfrecuencia | J2: Tto Empirico | K2: Tto Dirigido | L2: cultivo | M2: Suspender | N2: Cambiar | R2: Observacionesorden | S2: Codigo Diagnostico | T2: Diagnostico | U2: Dosis | V2: Peso(kg) | W2: ITU | X2: ITB | Y2: NEUMONIA | Z2: MENINGITIS | AA2: Dosis recetada
N3: Escalar | O3: Desescalar | P3: RXN adversa | Q3: Por dosis
A4: 1 | U4: =+V4*(W4+X4+Y4+Z4) -> 0 | W4: =IFERROR(VLOOKUP(VLOOKUP(E4,'Dosis Mx'!$R$1:$X$19,1,FALSE),'Dosis Mx'!$R$1:$X$19,6,FALSE),0) -> 0 | X4: =IFERROR(VLOOKUP(VLOOKUP(E4,'Dosis Mx'!$R$20:$X$36,1,FALSE),'Dosis Mx'!$R$20:$X$36,6,FALSE),0) -> 0 | Y4: =IFERROR(VLOOKUP(VLOOKUP(E4,'Dosis Mx'!$R$37:$X$54,1,FALSE),'Dosis Mx'!$R$37:$X$54,6,FALSE),0) -> 0 | Z4: =IFERROR(VLOOKUP(VLOOKUP(E4,'Dosis Mx'!$R$55:$X$78,1,FALSE),'Dosis Mx'!$R$55:$X$78,6,FALSE),0) -> 0 | AA4: =+F4*(24/H4) -> #DIV/0! | AB4: 5
A5: 2 | U5: =+V5*(W5+X5+Y5+Z5) -> 0 | W5: =IFERROR(VLOOKUP(VLOOKUP(E5,'Dosis Mx'!$R$1:$X$19,1,FALSE),'Dosis Mx'!$R$1:$X$19,6,FALSE),0) -> 0 | X5: =IFERROR(VLOOKUP(VLOOKUP(E5,'Dosis Mx'!$R$20:$X$36,1,FALSE),'Dosis Mx'!$R$20:$X$36,6,FALSE),0) -> 0 | Y5: =IFERROR(VLOOKUP(VLOOKUP(E5,'Dosis Mx'!$R$37:$X$54,1,FALSE),'Dosis Mx'!$R$37:$X$54,6,FALSE),0) -> 0 | Z5: =IFERROR(VLOOKUP(VLOOKUP(E5,'Dosis Mx'!$R$55:$X$78,1,FALSE),'Dosis Mx'!$R$55:$X$78,6,FALSE),0) -> 0 | AA5: =+F5*(24/H5) -> #DIV/0! | AB5: 6
A6: 3 | U6: =+V6*(W6+X6+Y6+Z6) -> 0 | W6: =IFERROR(VLOOKUP(VLOOKUP(E6,'Dosis Mx'!$R$1:$X$19,1,FALSE),'Dosis Mx'!$R$1:$X$19,6,FALSE),0) -> 0 | X6: =IFERROR(VLOOKUP(VLOOKUP(E6,'Dosis Mx'!$R$20:$X$36,1,FALSE),'Dosis Mx'!$R$20:$X$36,6,FALSE),0) -> 0 | Y6: =IFERROR(VLOOKUP(VLOOKUP(E6,'Dosis Mx'!$R$37:$X$54,1,FALSE),'Dosis Mx'!$R$37:$X$54,6,FALSE),0) -> 0 | Z6: =IFERROR(VLOOKUP(VLOOKUP(E6,'Dosis Mx'!$R$55:$X$78,1,FALSE),'Dosis Mx'!$R$55:$X$78,6,FALSE),0) -> 0 | AA6: =+F6*(24/H6) -> #DIV/0! | AB6: 7
A7: 4 | U7: =+V7*(W7+X7+Y7+Z7) -> 0 | W7: =IFERROR(VLOOKUP(VLOOKUP(E7,'Dosis Mx'!$R$1:$X$19,1,FALSE),'Dosis Mx'!$R$1:$X$19,6,FALSE),0) -> 0 | X7: =IFERROR(VLOOKUP(VLOOKUP(E7,'Dosis Mx'!$R$20:$X$36,1,FALSE),'Dosis Mx'!$R$20:$X$36,6,FALSE),0) -> 0 | Y7: =IFERROR(VLOOKUP(VLOOKUP(E7,'Dosis Mx'!$R$37:$X$54,1,FALSE),'Dosis Mx'!$R$37:$X$54,6,FALSE),0) -> 0 | Z7: =IFERROR(VLOOKUP(VLOOKUP(E7,'Dosis Mx'!$R$55:$X$78,1,FALSE),'Dosis Mx'!$R$55:$X$78,6,FALSE),0) -> 0 | AA7: =+F7*(24/H7) -> #DIV/0! | AB7: UCI
A8: 5 | U8: =+V8*(W8+X8+Y8+Z8) -> 0 | W8: =IFERROR(VLOOKUP(VLOOKUP(E8,'Dosis Mx'!$R$1:$X$19,1,FALSE),'Dosis Mx'!$R$1:$X$19,6,FALSE),0) -> 0 | X8: =IFERROR(VLOOKUP(VLOOKUP(E8,'Dosis Mx'!$R$20:$X$36,1,FALSE),'Dosis Mx'!$R$20:$X$36,6,FALSE),0) -> 0 | Y8: =IFERROR(VLOOKUP(VLOOKUP(E8,'Dosis Mx'!$R$37:$X$54,1,FALSE),'Dosis Mx'!$R$37:$X$54,6,FALSE),0) -> 0 | Z8: =IFERROR(VLOOKUP(VLOOKUP(E8,'Dosis Mx'!$R$55:$X$78,1,FALSE),'Dosis Mx'!$R$55:$X$78,6,FALSE),0) -> 0 | AA8: =+F8*(24/H8) -> #DIV/0! | AB8: URGENCIAS
A9: 6 | U9: =+V9*(W9+X9+Y9+Z9) -> 0 | W9: =IFERROR(VLOOKUP(VLOOKUP(E9,'Dosis Mx'!$R$1:$X$19,1,FALSE),'Dosis Mx'!$R$1:$X$19,6,FALSE),0) -> 0 | X9: =IFERROR(VLOOKUP(VLOOKUP(E9,'Dosis Mx'!$R$20:$X$36,1,FALSE),'Dosis Mx'!$R$20:$X$36,6,FALSE),0) -> 0 | Y9: =IFERROR(VLOOKUP(VLOOKUP(E9,'Dosis Mx'!$R$37:$X$54,1,FALSE),'Dosis Mx'!$R$37:$X$54,6,FALSE),0) -> 0 | Z9: =IFERROR(VLOOKUP(VLOOKUP(E9,'Dosis Mx'!$R$55:$X$78,1,FALSE),'Dosis Mx'!$R$55:$X$78,6,FALSE),0) -> 0 | AA9: =+F9*(24/H9) -> #DIV/0!
A10: 7 | U10: =+V10*(W10+X10+Y10+Z10) -> 0 | W10: =IFERROR(VLOOKUP(VLOOKUP(E10,'Dosis Mx'!$R$1:$X$19,1,FALSE),'Dosis Mx'!$R$1:$X$19,6,FALSE),0) -> 0 | X10: =IFERROR(VLOOKUP(VLOOKUP(E10,'Dosis Mx'!$R$20:$X$36,1,FALSE),'Dosis Mx'!$R$20:$X$36,6,FALSE),0) -> 0 | Y10: =IFERROR(VLOOKUP(VLOOKUP(E10,'Dosis Mx'!$R$37:$X$54,1,FALSE),'Dosis Mx'!$R$37:$X$54,6,FALSE),0) -> 0 | Z10: =IFERROR(VLOOKUP(VLOOKUP(E10,'Dosis Mx'!$R$55:$X$78,1,FALSE),'Dosis Mx'!$R$55:$X$78,6,FALSE),0) -> 0 | AA10: =+F10*(24/H10) -> #DIV/0!
A11: 8 | U11: =+V11*(W11+X11+Y11+Z11) -> 0 | W11: =IFERROR(VLOOKUP(VLOOKUP(E11,'Dosis Mx'!$R$1:$X$19,1,FALSE),'Dosis Mx'!$R$1:$X$19,6,FALSE),0) -> 0 | X11: =IFERROR(VLOOKUP(VLOOKUP(E11,'Dosis Mx'!$R$20:$X$36,1,FALSE),'Dosis Mx'!$R$20:$X$36,6,FALSE),0) -> 0 | Y11: =IFERROR(VLOOKUP(VLOOKUP(E11,'Dosis Mx'!$R$37:$X$54,1,FALSE),'Dosis Mx'!$R$37:$X$54,6,FALSE),0) -> 0 | Z11: =IFERROR(VLOOKUP(VLOOKUP(E11,'Dosis Mx'!$R$55:$X$78,1,FALSE),'Dosis Mx'!$R$55:$X$78,6,FALSE),0) -> 0 | AA11: =+F11*(24/H11) -> #DIV/0!
A12: 9 | U12: =+V12*(W12+X12+Y12+Z12) -> 0 | W12: =IFERROR(VLOOKUP(VLOOKUP(E12,'Dosis Mx'!$R$1:$X$19,1,FALSE),'Dosis Mx'!$R$1:$X$19,6,FALSE),0) -> 0 | X12: =IFERROR(VLOOKUP(VLOOKUP(E12,'Dosis Mx'!$R$20:$X$36,1,FALSE),'Dosis Mx'!$R$20:$X$36,6,FALSE),0) -> 0 | Y12: =IFERROR(VLOOKUP(VLOOKUP(E12,'Dosis Mx'!$R$37:$X$54,1,FALSE),'Dosis Mx'!$R$37:$X$54,6,FALSE),0) -> 0 | Z12: =IFERROR(VLOOKUP(VLOOKUP(E12,'Dosis Mx'!$R$55:$X$78,1,FALSE),'Dosis Mx'!$R$55:$X$78,6,FALSE),0) -> 0 | AA12: =+F12*(24/H12) -> #DIV/0!
A13: 10 | U13: =+V13*(W13+X13+Y13+Z13) -> 0 | W13: =IFERROR(VLOOKUP(VLOOKUP(E13,'Dosis Mx'!$R$1:$X$19,1,FALSE),'Dosis Mx'!$R$1:$X$19,6,FALSE),0) -> 0 | X13: =IFERROR(VLOOKUP(VLOOKUP(E13,'Dosis Mx'!$R$20:$X$36,1,FALSE),'Dosis Mx'!$R$20:$X$36,6,FALSE),0) -> 0 | Y13: =IFERROR(VLOOKUP(VLOOKUP(E13,'Dosis Mx'!$R$37:$X$54,1,FALSE),'Dosis Mx'!$R$37:$X$54,6,FALSE),0) -> 0 | Z13: =IFERROR(VLOOKUP(VLOOKUP(E13,'Dosis Mx'!$R$55:$X$78,1,FALSE),'Dosis Mx'!$R$55:$X$78,6,FALSE),0) -> 0 | AA13: =+F13*(24/H13) -> #DIV/0!
A14: 11 | U14: =+V14*(W14+X14+Y14+Z14) -> 0 | W14: =IFERROR(VLOOKUP(VLOOKUP(E14,'Dosis Mx'!$R$1:$X$19,1,FALSE),'Dosis Mx'!$R$1:$X$19,6,FALSE),0) -> 0 | X14: =IFERROR(VLOOKUP(VLOOKUP(E14,'Dosis Mx'!$R$20:$X$36,1,FALSE),'Dosis Mx'!$R$20:$X$36,6,FALSE),0) -> 0 | Y14: =IFERROR(VLOOKUP(VLOOKUP(E14,'Dosis Mx'!$R$37:$X$54,1,FALSE),'Dosis Mx'!$R$37:$X$54,6,FALSE),0) -> 0 | Z14: =IFERROR(VLOOKUP(VLOOKUP(E14,'Dosis Mx'!$R$55:$X$78,1,FALSE),'Dosis Mx'!$R$55:$X$78,6,FALSE),0) -> 0 | AA14: =+F14*(24/H14) -> #DIV/0!
A15: 12 | U15: =+V15*(W15+X15+Y15+Z15) -> 0 | W15: =IFERROR(VLOOKUP(VLOOKUP(E15,'Dosis Mx'!$R$1:$X$19,1,FALSE),'Dosis Mx'!$R$1:$X$19,6,FALSE),0) -> 0 | X15: =IFERROR(VLOOKUP(VLOOKUP(E15,'Dosis Mx'!$R$20:$X$36,1,FALSE),'Dosis Mx'!$R$20:$X$36,6,FALSE),0) -> 0 | Y15: =IFERROR(VLOOKUP(VLOOKUP(E15,'Dosis Mx'!$R$37:$X$54,1,FALSE),'Dosis Mx'!$R$37:$X$54,6,FALSE),0) -> 0 | Z15: =IFERROR(VLOOKUP(VLOOKUP(E15,'Dosis Mx'!$R$55:$X$78,1,FALSE),'Dosis Mx'!$R$55:$X$78,6,FALSE),0) -> 0 | AA15: =+F15*(24/H15) -> #DIV/0!
A16: 13 | U16: =+V16*(W16+X16+Y16+Z16) -> 0 | W16: =IFERROR(VLOOKUP(VLOOKUP(E16,'Dosis Mx'!$R$1:$X$19,1,FALSE),'Dosis Mx'!$R$1:$X$19,6,FALSE),0) -> 0 | X16: =IFERROR(VLOOKUP(VLOOKUP(E16,'Dosis Mx'!$R$20:$X$36,1,FALSE),'Dosis Mx'!$R$20:$X$36,6,FALSE),0) -> 0 | Y16: =IFERROR(VLOOKUP(VLOOKUP(E16,'Dosis Mx'!$R$37:$X$54,1,FALSE),'Dosis Mx'!$R$37:$X$54,6,FALSE),0) -> 0 | Z16: =IFERROR(VLOOKUP(VLOOKUP(E16,'Dosis Mx'!$R$55:$X$78,1,FALSE),'Dosis Mx'!$R$55:$X$78,6,FALSE),0) -> 0 | AA16: =+F16*(24/H16) -> #DIV/0!
A17: 14 | U17: =+V17*(W17+X17+Y17+Z17) -> 0 | W17: =IFERROR(VLOOKUP(VLOOKUP(E17,'Dosis Mx'!$R$1:$X$19,1,FALSE),'Dosis Mx'!$R$1:$X$19,6,FALSE),0) -> 0 | X17: =IFERROR(VLOOKUP(VLOOKUP(E17,'Dosis Mx'!$R$20:$X$36,1,FALSE),'Dosis Mx'!$R$20:$X$36,6,FALSE),0) -> 0 | Y17: =IFERROR(VLOOKUP(VLOOKUP(E17,'Dosis Mx'!$R$37:$X$54,1,FALSE),'Dosis Mx'!$R$37:$X$54,6,FALSE),0) -> 0 | Z17: =IFERROR(VLOOKUP(VLOOKUP(E17,'Dosis Mx'!$R$55:$X$78,1,FALSE),'Dosis Mx'!$R$55:$X$78,6,FALSE),0) -> 0 | AA17: =+F17*(24/H17) -> #DIV/0!
A18: 15 | U18: =+V18*(W18+X18+Y18+Z18) -> 0 | W18: =IFERROR(VLOOKUP(VLOOKUP(E18,'Dosis Mx'!$R$1:$X$19,1,FALSE),'Dosis Mx'!$R$1:$X$19,6,FALSE),0) -> 0 | X18: =IFERROR(VLOOKUP(VLOOKUP(E18,'Dosis Mx'!$R$20:$X$36,1,FALSE),'Dosis Mx'!$R$20:$X$36,6,FALSE),0) -> 0 | Y18: =IFERROR(VLOOKUP(VLOOKUP(E18,'Dosis Mx'!$R$37:$X$54,1,FALSE),'Dosis Mx'!$R$37:$X$54,6,FALSE),0) -> 0 | Z18: =IFERROR(VLOOKUP(VLOOKUP(E18,'Dosis Mx'!$R$55:$X$78,1,FALSE),'Dosis Mx'!$R$55:$X$78,6,FALSE),0) -> 0 | AA18: =+F18*(24/H18) -> #DIV/0!
A19: 16 | U19: =+V19*(W19+X19+Y19+Z19) -> 0 | W19: =IFERROR(VLOOKUP(VLOOKUP(E19,'Dosis Mx'!$R$1:$X$19,1,FALSE),'Dosis Mx'!$R$1:$X$19,6,FALSE),0) -> 0 | X19: =IFERROR(VLOOKUP(VLOOKUP(E19,'Dosis Mx'!$R$20:$X$36,1,FALSE),'Dosis Mx'!$R$20:$X$36,6,FALSE),0) -> 0 | Y19: =IFERROR(VLOOKUP(VLOOKUP(E19,'Dosis Mx'!$R$37:$X$54,1,FALSE),'Dosis Mx'!$R$37:$X$54,6,FALSE),0) -> 0 | Z19: =IFERROR(VLOOKUP(VLOOKUP(E19,'Dosis Mx'!$R$55:$X$78,1,FALSE),'Dosis Mx'!$R$55:$X$78,6,FALSE),0) -> 0 | AA19: =+F19*(24/H19) -> #DIV/0!
A20: 17 | U20: =+V20*(W20+X20+Y20+Z20) -> 0 | W20: =IFERROR(VLOOKUP(VLOOKUP(E20,'Dosis Mx'!$R$1:$X$19,1,FALSE),'Dosis Mx'!$R$1:$X$19,6,FALSE),0) -> 0 | X20: =IFERROR(VLOOKUP(VLOOKUP(E20,'Dosis Mx'!$R$20:$X$36,1,FALSE),'Dosis Mx'!$R$20:$X$36,6,FALSE),0) -> 0 | Y20: =IFERROR(VLOOKUP(VLOOKUP(E20,'Dosis Mx'!$R$37:$X$54,1,FALSE),'Dosis Mx'!$R$37:$X$54,6,FALSE),0) -> 0 | Z20: =IFERROR(VLOOKUP(VLOOKUP(E20,'Dosis Mx'!$R$55:$X$78,1,FALSE),'Dosis Mx'!$R$55:$X$78,6,FALSE),0) -> 0 | AA20: =+F20*(24/H20) -> #DIV/0!
... A32: 29 | U32: =+V32*(W32+X32+Y32+Z32) -> 0 | W32: =IFERROR(VLOOKUP(VLOOKUP(E32,'Dosis Mx'!$R$1:$X$19,1,FALSE),'Dosis Mx'!$R$1:$X$19,6,FALSE),0) -> 0 | X32: =IFERROR(VLOOKUP(VLOOKUP(E32,'Dosis Mx'!$R$20:$X$36,1,FALSE),'Dosis Mx'!$R$20:$X$36,6,FALSE),0) -> 0 | Y32: =IFERROR(VLOOKUP(VLOOKUP(E32,'Dosis Mx'!$R$37:$X$54,1,FALSE),'Dosis Mx'!$R$37:$X$54,6,FALSE),0) -> 0 | Z32: =IFERROR(VLOOKUP(VLOOKUP(E32,'Dosis Mx'!$R$55:$X$78,1,FALSE),'Dosis Mx'!$R$55:$X$78,6,FALSE),0) -> 0 | AA32: =+F32*(24/H32) -> #DIV/0!
A33: No | B33: Servicio | C33: Docidentidad | D33: Usuario | E33: Nombre | F33: Dosis | G33: Medidadosis | H33: Frecuencia | I33: Unidadfrecuencia | J33: Tto Empirico | K33: Tto Dirigido | L33: cultivo | M33: Suspender | N33: Cambiar | R33: Observacionesorden | S33: Codigo Diagnostico | T33: Diagnostico | U33: Dosis | V33: Peso(kg) | W33: ITU | X33: ITB | Y33: NEUMONIA | Z33: MENINGITIS | AA33: Dosis recetada
N34: Escalar | O34: Desescalar | P34: RXN adversa | Q34: Por dosis
A35: 30 | U35: =+V35*(W35+X35+Y35+Z35) -> 0 | W35: =IFERROR(VLOOKUP(VLOOKUP(E35,'Dosis Mx'!$R$1:$X$19,1,FALSE),'Dosis Mx'!$R$1:$X$19,6,FALSE),0) -> 0 | X35: =IFERROR(VLOOKUP(VLOOKUP(E35,'Dosis Mx'!$R$20:$X$36,1,FALSE),'Dosis Mx'!$R$20:$X$36,6,FALSE),0) -> 0 | Y35: =IFERROR(VLOOKUP(VLOOKUP(E35,'Dosis Mx'!$R$37:$X$54,1,FALSE),'Dosis Mx'!$R$37:$X$54,6,FALSE),0) -> 0 | Z35: =IFERROR(VLOOKUP(VLOOKUP(E35,'Dosis Mx'!$R$55:$X$78,1,FALSE),'Dosis Mx'!$R$55:$X$78,6,FALSE),0) -> 0 | AA35: =+F35*(24/H35) -> #DIV/0!
A36: 31 | U36: =+V36*(W36+X36+Y36+Z36) -> 0 | W36: =IFERROR(VLOOKUP(VLOOKUP(E36,'Dosis Mx'!$R$1:$X$19,1,FALSE),'Dosis Mx'!$R$1:$X$19,6,FALSE),0) -> 0 | X36: =IFERROR(VLOOKUP(VLOOKUP(E36,'Dosis Mx'!$R$20:$X$36,1,FALSE),'Dosis Mx'!$R$20:$X$36,6,FALSE),0) -> 0 | Y36: =IFERROR(VLOOKUP(VLOOKUP(E36,'Dosis Mx'!$R$37:$X$54,1,FALSE),'Dosis Mx'!$R$37:$X$54,6,FALSE),0) -> 0 | Z36: =IFERROR(VLOOKUP(VLOOKUP(E36,'Dosis Mx'!$R$55:$X$78,1,FALSE),'Dosis Mx'!$R$55:$X$78,6,FALSE),0) -> 0 | AA36: =+F36*(24/H36) -> #DIV/0!
A37: 32 | U37: =+V37*(W37+X37+Y37+Z37) -> 0 | W37: =IFERROR(VLOOKUP(VLOOKUP(E37,'Dosis Mx'!$R$1:$X$19,1,FALSE),'Dosis Mx'!$R$1:$X$19,6,FALSE),0) -> 0 | X37: =IFERROR(VLOOKUP(VLOOKUP(E37,'Dosis Mx'!$R$20:$X$36,1,FALSE),'Dosis Mx'!$R$20:$X$36,6,FALSE),0) -> 0 | Y37: =IFERROR(VLOOKUP(VLOOKUP(E37,'Dosis Mx'!$R$37:$X$54,1,FALSE),'Dosis Mx'!$R$37:$X$54,6,FALSE),0) -> 0 | Z37: =IFERROR(VLOOKUP(VLOOKUP(E37,'Dosis Mx'!$R$55:$X$78,1,FALSE),'Dosis Mx'!$R$55:$X$78,6,FALSE),0) -> 0 | AA37: =+F37*(24/H37) -> #DIV/0!
A38: 33 | U38: =+V38*(W38+X38+Y38+Z38) -> 0 | W38: =IFERROR(VLOOKUP(VLOOKUP(E38,'Dosis Mx'!$R$1:$X$19,1,FALSE),'Dosis Mx'!$R$1:$X$19,6,FALSE),0) -> 0 | X38: =IFERROR(VLOOKUP(VLOOKUP(E38,'Dosis Mx'!$R$20:$X$36,1,FALSE),'Dosis Mx'!$R$20:$X$36,6,FALSE),0) -> 0 | Y38: =IFERROR(VLOOKUP(VLOOKUP(E38,'Dosis Mx'!$R$37:$X$54,1,FALSE),'Dosis Mx'!$R$37:$X$54,6,FALSE),0) -> 0 | Z38: =IFERROR(VLOOKUP(VLOOKUP(E38,'Dosis Mx'!$R$55:$X$78,1,FALSE),'Dosis Mx'!$R$55:$X$78,6,FALSE),0) -> 0 | AA38: =+F38*(24/H38) -> #DIV/0!
A39: 34 | U39: =+V39*(W39+X39+Y39+Z39) -> 0 | W39: =IFERROR(VLOOKUP(VLOOKUP(E39,'Dosis Mx'!$R$1:$X$19,1,FALSE),'Dosis Mx'!$R$1:$X$19,6,FALSE),0) -> 0 | X39: =IFERROR(VLOOKUP(VLOOKUP(E39,'Dosis Mx'!$R$20:$X$36,1,FALSE),'Dosis Mx'!$R$20:$X$36,6,FALSE),0) -> 0 | Y39: =IFERROR(VLOOKUP(VLOOKUP(E39,'Dosis Mx'!$R$37:$X$54,1,FALSE),'Dosis Mx'!$R$37:$X$54,6,FALSE),0) -> 0 | Z39: =IFERROR(VLOOKUP(VLOOKUP(E39,'Dosis Mx'!$R$55:$X$78,1,FALSE),'Dosis Mx'!$R$55:$X$78,6,FALSE),0) -> 0 | AA39: =+F39*(24/H39) -> #DIV/0!
A40: 35 | U40: =+V40*(W40+X40+Y40+Z40) -> 0 | W40: =IFERROR(VLOOKUP(VLOOKUP(E40,'Dosis Mx'!$R$1:$X$19,1,FALSE),'Dosis Mx'!$R$1:$X$19,6,FALSE),0) -> 0 | X40: =IFERROR(VLOOKUP(VLOOKUP(E40,'Dosis Mx'!$R$20:$X$36,1,FALSE),'Dosis Mx'!$R$20:$X$36,6,FALSE),0) -> 0 | Y40: =IFERROR(VLOOKUP(VLOOKUP(E40,'Dosis Mx'!$R$37:$X$54,1,FALSE),'Dosis Mx'!$R$37:$X$54,6,FALSE),0) -> 0 | Z40: =IFERROR(VLOOKUP(VLOOKUP(E40,'Dosis Mx'!$R$55:$X$78,1,FALSE),'Dosis Mx'!$R$55:$X$78,6,FALSE),0) -> 0 | AA40: =+F40*(24/H40) -> #DIV/0!
A41: 36 | U41: =+V41*(W41+X41+Y41+Z41) -> 0 | W41: =IFERROR(VLOOKUP(VLOOKUP(E41,'Dosis Mx'!$R$1:$X$19,1,FALSE),'Dosis Mx'!$R$1:$X$19,6,FALSE),0) -> 0 | X41: =IFERROR(VLOOKUP(VLOOKUP(E41,'Dosis Mx'!$R$20:$X$36,1,FALSE),'Dosis Mx'!$R$20:$X$36,6,FALSE),0) -> 0 | Y41: =IFERROR(VLOOKUP(VLOOKUP(E41,'Dosis Mx'!$R$37:$X$54,1,FALSE),'Dosis Mx'!$R$37:$X$54,6,FALSE),0) -> 0 | Z41: =IFERROR(VLOOKUP(VLOOKUP(E41,'Dosis Mx'!$R$55:$X$78,1,FALSE),'Dosis Mx'!$R$55:$X$78,6,FALSE),0) -> 0 | AA41: =+F41*(24/H41) -> #DIV/0!
A42: 37 | U42: =+V42*(W42+X42+Y42+Z42) -> 0 | W42: =IFERROR(VLOOKUP(VLOOKUP(E42,'Dosis Mx'!$R$1:$X$19,1,FALSE),'Dosis Mx'!$R$1:$X$19,6,FALSE),0) -> 0 | X42: =IFERROR(VLOOKUP(VLOOKUP(E42,'Dosis Mx'!$R$20:$X$36,1,FALSE),'Dosis Mx'!$R$20:$X$36,6,FALSE),0) -> 0 | Y42: =IFERROR(VLOOKUP(VLOOKUP(E42,'Dosis Mx'!$R$37:$X$54,1,FALSE),'Dosis Mx'!$R$37:$X$54,6,FALSE),0) -> 0 | Z42: =IFERROR(VLOOKUP(VLOOKUP(E42,'Dosis Mx'!$R$55:$X$78,1,FALSE),'Dosis Mx'!$R$55:$X$78,6,FALSE),0) -> 0 | AA42: =+F42*(24/H42) -> #DIV/0!
A43: 38 | U43: =+V43*(W43+X43+Y43+Z43) -> 0 | W43: =IFERROR(VLOOKUP(VLOOKUP(E43,'Dosis Mx'!$R$1:$X$19,1,FALSE),'Dosis Mx'!$R$1:$X$19,6,FALSE),0) -> 0 | X43: =IFERROR(VLOOKUP(VLOOKUP(E43,'Dosis Mx'!$R$20:$X$36,1,FALSE),'Dosis Mx'!$R$20:$X$36,6,FALSE),0) -> 0 | Y43: =IFERROR(VLOOKUP(VLOOKUP(E43,'Dosis Mx'!$R$37:$X$54,1,FALSE),'Dosis Mx'!$R$37:$X$54,6,FALSE),0) -> 0 | Z43: =IFERROR(VLOOKUP(VLOOKUP(E43,'Dosis Mx'!$R$55:$X$78,1,FALSE),'Dosis Mx'!$R$55:$X$78,6,FALSE),0) -> 0 | AA43: =+F43*(24/H43) -> #DIV/0!
A44: 39 | U44: =+V44*(W44+X44+Y44+Z44) -> 0 | W44: =IFERROR(VLOOKUP(VLOOKUP(E44,'Dosis Mx'!$R$1:$X$19,1,FALSE),'Dosis Mx'!$R$1:$X$19,6,FALSE),0) -> 0 | X44: =IFERROR(VLOOKUP(VLOOKUP(E44,'Dosis Mx'!$R$20:$X$36,1,FALSE),'Dosis Mx'!$R$20:$X$36,6,FALSE),0) -> 0 | Y44: =IFERROR(VLOOKUP(VLOOKUP(E44,'Dosis Mx'!$R$37:$X$54,1,FALSE),'Dosis Mx'!$R$37:$X$54,6,FALSE),0) -> 0 | Z44: =IFERROR(VLOOKUP(VLOOKUP(E44,'Dosis Mx'!$R$55:$X$78,1,FALSE),'Dosis Mx'!$R$55:$X$78,6,FALSE),0) -> 0 | AA44: =+F44*(24/H44) -> #DIV/0!
A45: 40 | U45: =+V45*(W45+X45+Y45+Z45) -> 0 | W45: =IFERROR(VLOOKUP(VLOOKUP(E45,'Dosis Mx'!$R$1:$X$19,1,FALSE),'Dosis Mx'!$R$1:$X$19,6,FALSE),0) -> 0 | X45: =IFERROR(VLOOKUP(VLOOKUP(E45,'Dosis Mx'!$R$20:$X$36,1,FALSE),'Dosis Mx'!$R$20:$X$36,6,FALSE),0) -> 0 | Y45: =IFERROR(VLOOKUP(VLOOKUP(E45,'Dosis Mx'!$R$37:$X$54,1,FALSE),'Dosis Mx'!$R$37:$X$54,6,FALSE),0) -> 0 | Z45: =IFERROR(VLOOKUP(VLOOKUP(E45,'Dosis Mx'!$R$55:$X$78,1,FALSE),'Dosis Mx'!$R$55:$X$78,6,FALSE),0) -> 0 | AA45: =+F45*(24/H45) -> #DIV/0!
A46: 41 | U46: =+V46*(W46+X46+Y46+Z46) -> 0 | W46: =IFERROR(VLOOKUP(VLOOKUP(E46,'Dosis Mx'!$R$1:$X$19,1,FALSE),'Dosis Mx'!$R$1:$X$19,6,FALSE),0) -> 0 | X46: =IFERROR(VLOOKUP(VLOOKUP(E46,'Dosis Mx'!$R$20:$X$36,1,FALSE),'Dosis Mx'!$R$20:$X$36,6,FALSE),0) -> 0 | Y46: =IFERROR(VLOOKUP(VLOOKUP(E46,'Dosis Mx'!$R$37:$X$54,1,FALSE),'Dosis Mx'!$R$37:$X$54,6,FALSE),0) -> 0 | Z46: =IFERROR(VLOOKUP(VLOOKUP(E46,'Dosis Mx'!$R$55:$X$78,1,FALSE),'Dosis Mx'!$R$55:$X$78,6,FALSE),0) -> 0 | AA46: =+F46*(24/H46) -> #DIV/0!
... A63: 58 | U63: =+V63*(W63+X63+Y63+Z63) -> 0 | W63: =IFERROR(VLOOKUP(VLOOKUP(E63,'Dosis Mx'!$R$1:$X$19,1,FALSE),'Dosis Mx'!$R$1:$X$19,6,FALSE),0) -> 0 | X63: =IFERROR(VLOOKUP(VLOOKUP(E63,'Dosis Mx'!$R$20:$X$36,1,FALSE),'Dosis Mx'!$R$20:$X$36,6,FALSE),0) -> 0 | Y63: =IFERROR(VLOOKUP(VLOOKUP(E63,'Dosis Mx'!$R$37:$X$54,1,FALSE),'Dosis Mx'!$R$37:$X$54,6,FALSE),0) -> 0 | Z63: =IFERROR(VLOOKUP(VLOOKUP(E63,'Dosis Mx'!$R$55:$X$78,1,FALSE),'Dosis Mx'!$R$55:$X$78,6,FALSE),0) -> 0 | AA63: =+F63*(24/H63) -> #DIV/0!

Sheet COMPILADO
A1: Piso | B1: Servicio | C1: Docidentidad | D1: Usuario | E1: Nombre | F1: Dosis | G1: Medidadosis | H1: Frecuencia | I1: Unidadfrecuencia | J1: Tto Empirico | K1: Tto Dirigido | L1: Cultivo | M1: Suspender | N1: Cambiar | R1: Observaciones orden | S1: Codigo Diagnostico | T1: Diagnostico
N2: Escalar | O2: Desescalar | P2: RXN adversa | Q2: Por dosis
A3: URGENCIAS | B3: ObsAisl 1 | C3: 23099110655662 | D3: HIJO DE EMILSE PAOLA OSORIO | E3: Oxacilina (Sal Sodica) 1000 mg Polvo para Inyeccion | F3: 100 | G3: MG | H3: 8 | I3: H | J3: I | L3: X | S3: L032 | T3: CELULITIS DE LA CARA
A4: UCI | B4: UCE 03 | C4: 1041633640 | D4: ANGELA MARIA POSADA GONZALEZ | E4: AZITromicina200mg/5 ml (4%)Polvo para reconstituirx15ml | F4: 500 | G4: MG | H4: 24 | I4: H | J4: I | L4: X | S4: I272 | T4: OTRAS HIPERTENSIONES PULMONARES SECUNDARIAS
A5: UCI | B5: UCE 03 | C5: 1041633640 | D5: ANGELA MARIA POSADA GONZALEZ | E5: AMPIcilina Sodica/SULBactam Sodico 1000/500mg Polvo para iny (Ped) | F5: 2000 | G5: MG | H5: 6 | I5: H | J5: I | L5: X | S5: I272 | T5: OTRAS HIPERTENSIONES PULMONARES SECUNDARIAS
A6: UCI | B6: UCE 07 | C6: 1026004290 | D6: MARIA JOSE CASTAÑO MARIN | E6: AMPIcilina (Sal Sodica) x 1000 mg Polvo para Inyeccion | F6: 245 | G6: MG | H6: 6 | I6: H | R6: ALTA | S6: J219 | T6: BRONQUIOLITIS AGUDA, NO ESPECIFICADA
A7: UCI | B7: UCE 08AISL | C7: 1023639296 | D7: MICHEL GRAJALES | E7: AMPIcilina Sodica/SULBactam Sodico 1000/500mg Polvo para iny (Ped) | F7: 1250 | G7: MG | H7: 6 | I7: H | J7: I | S7: J690 | T7: NEUMONITIS DEBIDA A ASPIRACION DE ALIMENTO O VOMITO
A8: UCI | B8: UCI 01 | C8: 1247049299 | D8: ANALIZ VICTORIA GONZALEZ FUENTES | E8: AMPIcilina Sodica/SULBactam Sodico 1000/500mg Polvo para iny (Ped) | F8: 280 | G8: MG | H8: 6 | I8: H | J8: NI | L8: X | M8: X | S8: J219 | T8: BRONQUIOLITIS AGUDA, NO ESPECIFICADA
A9: UCI | B9: UCI 01 | C9: 1247049299 | D9: ANALIZ VICTORIA GONZALEZ FUENTES | E9: AZITromicina200mg/5 ml (4%)Polvo para reconstituirx15ml | F9: 45 | G9: MG | H9: 24 | I9: H | J9: NI | L9: X | M9: X | S9: J219 | T9: BRONQUIOLITIS AGUDA, NO ESPECIFICADA
A10: UCI | B10: UCI 02 | C10: 1011420925 | D10: ALAN CAMILO MUÑOZ ZAPATA | E10: AMPIcilina Sodica/SULBactam Sodico 1000/500mg Polvo para iny (Ped) | F10: 450 | G10: MG | H10: 6 | I10: H | J10: I | R10: 5 DÍAS | S10: J219 | T10: BRONQUIOLITIS AGUDA, NO ESPECIFICADA
A11: UCI | B11: UCI 04 | C11: 1031944635 | D11: IKER YULIAN DAVID MARTINEZ | E11: Cefepime 1000 mg Polvo para inyeccion | F11: 200 | G11: MG | H11: 8 | I11: H | J11: I | L11: X | N11: X | R11: 7 DÍAS | S11: I272 | T11: OTRAS HIPERTENSIONES PULMONARES SECUNDARIAS
A12: UCI | B12: UCI 05 | C12: 1023544374 | D12: SANTIAGO GONZALEZ OSORIO | E12: Vancomicina (Clorhidrato) 500 mg Polvo para Inyeccion | F12: 190 | G12: MG | H12: 6 | I12: H | J12: I | L12: X | M12: X | S12: Q213 | T12: TETRALOGIA DE FALLOT
A13: UCI | B13: UCI 05 | C13: 1023544374 | D13: SANTIAGO GONZALEZ OSORIO | E13: Ceftriaxona (Sal Sodica) 1000 mg Polvo para Inyeccion | F13: 640 | G13: MG | H13: 12 | I13: H | J13: I | L13: X | Q13: X | R13: C/24 HORAS 75MG | S13: Q213 | T13: TETRALOGIA DE FALLOT
A14: UCI | B14: UCI 06 | C14: 1078474669 | D14: CATALINA GONZALEZ TUNAY | E14: Vancomicina (Clorhidrato) 500 mg Polvo para Inyeccion | F14: 90 | G14: MG | H14: 6 | I14: H | J14: I | L14: X | M14: X | R14: ANALISIS TB | S14: J158 | T14: OTRAS NEUMONIAS BACTERIANAS
A15: CUI | B15: UCI 06 | C15: 1078474669 | D15: CATALINA GONZALEZ TUNAY | E15: Ceftriaxona (Sal Sodica) 1000 mg Polvo para Inyeccion | F15: 300 | G15: MG | H15: 12 | I15: H | J15: I | Q15: X | R15: C/24 HORAS 75MG | S15: J158 | T15: OTRAS NEUMONIAS BACTERIANAS
A16: 5 | B16: 501-4 | C16: 1038550461 | D16: ADHARA GALEANO | E16: Clindamicina (Fosfato) 600 mg /4ml Solucion Inyectable | F16: 70 | G16: MG | H16: 6 | I16: H | J16: I | S16: L029 | T16: ABSCESO CUTANEO, FURUNCULO Y ANTRAX DE SITIO NO ESPECIFICADO
A17: 5 | B17: 502-3 | C17: 1129604154 | D17: LUCIANA LEAL TANGARIFE | E17: Nistatina 100.000 U/ml Suspension Oral Frasco X 60 ml | F17: 5 | G17: 15 | H17: 6 | I17: H | J17: NI | M17: X | S17: K121 | T17: OTRAS FORMAS DE ESTOMATITIS
A18: 5 | B18: 502-4 | C18: 1018279481 | D18: CHLOE HENAO VILLEGAS | E18: AMIKacina (Sulfato) 100 mg/2 ml Solucion Inyectable | F18: 135 | G18: MG | H18: 24 | I18: H | J18: I | L18: X | S18: N390 | T18: INFECCION DE VIAS URINARIAS, SITIO NO ESPECIFICADO
A19: 5 | B19: 502-5 | C19: 1022170611 | D19: LIAM DAVID GONZALEZ MARRUGO | E19: AMIKacina (Sulfato) 100 mg/2 ml Solucion Inyectable | F19: 150 | G19: MG | H19: 24 | I19: H | J19: I | L19: X | S19: F445 | T19: CONVULSIONES DISOCIATIVAS
A20: 5 | B20: 503-5 | C20: 1039380512 | D20: SARAY MARTINEZ MAYA | E20: AMIKacina (Sulfato) 500 mg/2 ml Solucion Inyectable | F20: 240 | G20: MG | H20: 24 | I20: H | J20: I | L20: X | S20: N390 | T20: INFECCION DE VIAS URINARIAS, SITIO NO ESPECIFICADO
A21: 5 | B21: 506-1 | C21: 1034927181 | D21: JULIETA GARCIA RODRIGUEZ | E21: AMIKacina (Sulfato) 500 mg/2 ml Solucion Inyectable | F21: 240 | G21: MG | H21: 24 | I21: H | R21: ALTA, CEFALEXINA 7 DÍAS | S21: N390 | T21: INFECCION DE VIAS URINARIAS, SITIO NO ESPECIFICADO
A22: 5 | B22: 506-2 | C22: 1039912668 | D22: ANGELESS SOFIA QUINTERO CAMARGO | E22: AMIKacina (Sulfato) 100 mg/2 ml Solucion Inyectable | F22: 147 | G22: MG | H22: 24 | I22: H | J22: I | L22: X | S22: N390 | T22: INFECCION DE VIAS URINARIAS, SITIO NO ESPECIFICADO
A23: 5 | B23: Aisl 500 | C23: 1023526248 | D23: MARIANA LOPEZ MUNERA | E23: AMPIcilina Sodica/SULBactam Sodico 1000/500mg Polvo para iny (Ped) | F23: 2000 | G23: MG | H23: 6 | I23: H | J23: NI | L23: X | S23: R509 | T23: FIEBRE, NO ESPECIFICADA
A24: 7 | B24: 708-3 | C24: 1039050469 | D24: JEHILYN HENAO BERMUDEZ | E24: AMIKacina (Sulfato) 100 mg/2 ml Solucion Inyectable | F24: 200 | G24: MG | H24: 24 | I24: H | J24: I | S24: N390 | T24: INFECCION DE VIAS URINARIAS, SITIO NO ESPECIFICADO
A25: 7 | B25: 708-4 | C25: 1015071491 | D25: MARIA STEFANNY QUINTERO HENAO | E25: Ciprofloxacina (Clorhidrato) 100 mg/10 ml Sln Inyectable | F25: 320 | G25: MG | H25: 8 | I25: H | J25: I | L25: X | S25: N390 | T25: INFECCION DE VIAS URINARIAS, SITIO NO ESPECIFICADO
A26: 7 | B26: 708-6 | C26: 1025677881 | D26: MIA ANDRADES MURILLO | E26: AMIKacina (Sulfato) 500 mg/2 ml Solucion Inyectable | F26: 165 | G26: MG | H26: 24 | I26: H | J26: I | R26: ALTA | S26: N390 | T26: INFECCION DE VIAS URINARIAS, SITIO NO ESPECIFICADO
A27: 7 | B27: 709-1 | C27: 1023665226 | D27: ANTHONY BLANCO GELEZ | E27: AMPIcilina Sodica/SULBactam Sodico 1000/500mg Polvo para iny (Ped) | F27: 400 | G27: MG | H27: 6 | I27: H | J27: I | M27: X | R27: ALTA | S27: A499 | T27: INFECCION BACTERIANA, NO ESPECIFICADA
A28: 7 | B28: 709-4 | C28: 1011420656 | D28: JULIETA MARULANDA RODRIGUEZ | E28: Cefazolina 1000 mg Polvo para Inyeccion | F28: 250 | G28: MG | H28: 6 | I28: H | J28: I | S28: L040 | T28: LINFADENITIS AGUDA DE CARA, CABEZA Y CUELLO
A29: 7 | B29: 709-6 | C29: 1078692967 | D29: THARA MARIAM PEÑA ANGULO | E29: Clindamicina (Fosfato) 600 mg /4ml Solucion Inyectable | F29: 160 | G29: MG | H29: 6 | I29: H | J29: I | S29: M255 | T29: DOLOR EN ARTICULACION
A30: 7 | B30: 710-1 | C30: 1023556882 | D30: NICOLAS MONTOYA BEDOYA | E30: AMPIcilina Sodica/SULBactam Sodico 1000/500mg Polvo para iny (Ped) | F30: 800 | G30: MG | H30: 6 | I30: H | J30: I | S30: R509 | T30: FIEBRE, NO ESPECIFICADA
A31: 7 | B31: 710-5 | C31: 1042095438 | D31: DARIANA MILAGROS YEPES VERGARA | E31: Clindamicina (Fosfato) 600 mg /4ml Solucion Inyectable | F31: 90 | G31: MG | H31: 6 | I31: H | J31: I | S31: L024 | T31: ABSCESO CUTANEO, FURUNCULO Y ANTRAX DE MIEMBRO
A32: 7 | B32: Aisl 701 | C32: 1017284099 | D32: ASHLY JIREH CASTILLO SANCHEZ | E32: AZITromicina200mg/5 ml (4%)Polvo para reconstituirx15ml | F32: 47 | G32: MG | H32: 24 | I32: H | J32: I | S32: R509 | T32: FIEBRE, NO ESPECIFICADA
A33: 7 | B33: Aisl 702 | C33: VEN005084 | D33: DIEGO RAFAEL MORALES FLAMEZ | E33: Ceftriaxona (Sal Sodica) 1000 mg Polvo para Inyeccion | F33: 390 | G33: MG | H33: 12 | I33: H | J33: I | S33: N179 | T33: INSUFICIENCIA RENAL AGUDA, NO ESPECIFICADA
A34: 7 | B34: Aisl 703 | C34: 1011420925 | D34: ALAN CAMILO MUÑOZ ZAPATA | E34: AMPIcilina Sodica/SULBactam Sodico 1000/500mg Polvo para iny (Ped) | F34: 450 | G34: MG | H34: 6 | I34: H | J34: I | S34: J219 | T34: BRONQUIOLITIS AGUDA, NO ESPECIFICADA
A35: 7 | B35: Aisl 705 | C35: 1031948923 | D35: MATEO VALENCIA VASQUEZ | E35: Ciprofloxacina (Clorhidrato) 100 mg/10 ml Sln Inyectable | F35: 90 | G35: MG | H35: 12 | I35: H | J35: I | L35: X | S35: A090 | T35: OTRAS GASTROENTERITIS Y COLITIS DE ORIGEN INFECCIOSO
A36: 7 | B36: Aisl 706 | C36: 1040262325 | D36: VICTOR ALFONSO FLOREZ AGUDELO | E36: Fluconazol 50 mg/5 ml Polvo para Suspension Frasco X 20 ml | F36: 85 | G36: MG | H36: 24 | I36: H | J36: I | R36: PROFILACTICO | S36: L080 | T36: PIODERMA
A37: 7 | B37: Aisl 707 | C37: 23099110655662 | D37: HIJO DE EMILSE PAOLA OSORIO | E37: Oxacilina (Sal Sodica) 1000 mg Polvo para Inyeccion | F37: 135 | G37: MG | H37: 6 | I37: H | R37: ALTA | S37: L032 | T37: CELULITIS DE LA CARA
A38: 6 | B38: 601-1 | C38: 1077652699 | D38: HEINNI KARINA CHAMARRA OBISPO | E38: Nistatina 100.000 U/ml Suspension Oral Frasco X 60 ml | F38: 100000 | G38: 15 | H38: 8 | I38: H | J38: I | L38: NA | S38: Q250 | T38: CONDUCTO ARTERIOSO PERSISTENTE
A39: 6 | B39: 601-1 | C39: 1077652699 | D39: HEINNI KARINA CHAMARRA OBISPO | E39: Ceftriaxona (Sal Sodica) 1000 mg Polvo para Inyeccion | F39: 400 | G39: MG | H39: 24 | I39: H | J39: I | L39: NA | S39: Q250 | T39: CONDUCTO ARTERIOSO PERSISTENTE
A40: 6 | B40: 601-3 | C40: 1036266814 | D40: EMMANUEL MORALES CASTAÑO | E40: AMPIcilina Sodica/SULBactam Sodico 1000/500mg Polvo para iny (Ped) | F40: 500 | G40: MG | H40: 6 | I40: H | J40: I | L40: NA | S40: H650 | T40: OTITIS MEDIA AGUDA SEROSA
A41: 6 | B41: 601-4 | C41: 1013365120 | D41: DYLAN ALEXANDER HENAO CARTAGENA | E41: AMPIcilina (Sal Sodica) x 1000 mg Polvo para Inyeccion | F41: 830 | G41: MG | H41: 6 | I41: H | J41: I | L41: NA | S41: J159 | T41: NEUMONIA BACTERIANA, NO ESPECIFICADA
A42: 6 | B42: 601-5 | C42: 1023541184 | D42: SUSANA RAMIREZ MARTINEZ | E42: AMPIcilina (Sal Sodica) x 1000 mg Polvo para Inyeccion | F42: 850 | G42: MG | H42: 6 | I42: H | J42: I | L42: NA | S42: J159 | T42: NEUMONIA BACTERIANA, NO ESPECIFICADA
A43: 6 | B43: 601-6 | C43: 1131206016 | D43: DOMINIC MACEA SISTIAGA | E43: Ceftriaxona (Sal Sodica) 1000 mg Polvo para Inyeccion | F43: 500 | G43: MG | H43: 24 | I43: H | J43: I | M43: X | S43: J219 | T43: BRONQUIOLITIS AGUDA, NO ESPECIFICADA
A44: 6 | B44: 602-1 | C44: 1023640333 | D44: EMILY GUADALUPE VASQUEZ GOMEZ | E44: AMPIcilina Sodica/SULBactam Sodico 1000/500mg Polvo para iny (Ped) | F44: 800 | G44: MG | H44: 6 | I44: H | J44: I | L44: NA | S44: J189 | T44: NEUMONIA, NO ESPECIFICADA
A45: 6 | B45: 602-2 | C45: 1092958131 | D45: JAYLYN DANITZA SANTANDER ACEVEDO | E45: AZITromicina200mg/5 ml (4%)Polvo para reconstituirx15ml | F45: 320 | G45: MG | H45: 24 | I45: H | J45: I | L45: NA | S45: J22X | T45: INFECCION AGUDA NO ESPECIFICADA DE LAS VIAS RESPIRATORIAS INFERIORES
A46: 6 | B46: 602-6 | C46: 1025672317 | D46: ISABELLA CARDONA PAREJA | E46: AZITromicina200mg/5 ml (4%)Polvo para reconstituirx15ml | F46: 230 | G46: MG | H46: 24 | I46: H | J46: I | S46: J46X | T46: ESTADO ASMATICO
A47: 6 | B47: 603-4 | C47: 1011407824 | D47: CRISTIAN ALEJANDRO VARGAS TORRES | E47: AMPIcilina Sodica/SULBactam Sodico 1000/500mg Polvo para iny (Ped) | F47: 1300 | G47: MG | H47: 6 | I47: H | J47: I | S47: J22X | T47: INFECCION AGUDA NO ESPECIFICADA DE LAS VIAS RESPIRATORIAS INFERIORES
A48: 6 | B48: 603-6 | C48: 1034931139 | D48: ISAAC RODRIGUEZ MOLINA | E48: AMPIcilina 500 mg Polvo para Inyeccion | F48: 400 | G48: MG | H48: 6 | I48: H | J48: NI | M48: X | S48: J22X | T48: INFECCION AGUDA NO ESPECIFICADA DE LAS VIAS RESPIRATORIAS INFERIORES
A49: 6 | B49: 604-1 | C49: 1195217782 | D49: LIAM CHAVARRIA CHAVEZ | E49: Cefazolina 1000 mg Polvo para Inyeccion | F49: 420 | G49: MG | H49: 8 | I49: H | J49: I | M49: X | S49: J050 | T49: LARINGITIS OBSTRUCTIVA, AGUDA -CRUP-
A50: 6 | B50: 604-2 | C50: 1131204396 | D50: YANG ALEXANDER BETANCUR SUAREZ | E50: AMPIcilina 500 mg Polvo para Inyeccion | F50: 430 | G50: MG | H50: 6 | I50: H | J50: NI | M50: X | S50: J159 | T50: NEUMONIA BACTERIANA, NO ESPECIFICADA
A51: 6 | B51: 604-3 | C51: 1013381216 | D51: EMILY LOPERA MURILLO | E51: AMIKacina (Sulfato) 100 mg/2 ml Solucion Inyectable | F51: 82 | G51: MG | H51: 24 | I51: H | K51: I | L51: X | R51: CAMBIO CEFAZOLINA | S51: N390 | T51: INFECCION DE VIAS URINARIAS, SITIO NO ESPECIFICADO
A52: 6 | B52: 605-2 | C52: 1033826347 | D52: SAHARA VALENTINA AVILA RESTREPO | E52: AMPIcilina (Sal Sodica) x 1000 mg Polvo para Inyeccion | F52: 900 | G52: MG | H52: 6 | I52: H | R52: ALTA | S52: J159 | T52: NEUMONIA BACTERIANA, NO ESPECIFICADA
A53: 6 | B53: 605-4 | C53: 1036962230 | D53: LUIS CRISTOBAL AGUIRRE AREIZA | E53: AMPIcilina Sodica/SULBactam Sodico 1000/500mg Polvo para iny (Ped) | F53: 950 | G53: MG | H53: 6 | I53: H | J53: I | S53: J189 | T53: NEUMONIA, NO ESPECIFICADA
A54: 6 | B54: 605-5 | C54: 1041460260 | D54: VALENTINA ALVARAN JIMENEZ | E54: AMPIcilina (Sal Sodica) x 1000 mg Polvo para Inyeccion | F54: 2000 | G54: MG | H54: 6 | I54: H | J54: I | L54: NO | S54: J189 | T54: NEUMONIA, NO ESPECIFICADA
A55: 6 | B55: 605-5 | C55: 1041460260 | D55: VALENTINA ALVARAN JIMENEZ | E55: AZITromicina 500 mg Tableta | F55: 500 | G55: MG | H55: 24 | I55: H | J55: I | L55: NO | S55: J189 | T55: NEUMONIA, NO ESPECIFICADA
A56: 6 | B56: 606-4 | C56: 1039478496 | D56: QUENEDI ALEJANDRO BAILARIN DUARTE | E56: AMPIcilina (Sal Sodica) x 1000 mg Polvo para Inyeccion | F56: 1700 | G56: MG | H56: 6 | I56: H | J56: NI | L56: NA | M56: X | S56: N009 | T56: SINDROME NEFRITICO AGUDO, NO ESPECIFICADA
A57: 6 | B57: 606-6 | C57: 6518714 | D57: BENJAMIN RAUL HERNANDEZ GARCIA | E57: AZITromicina200mg/5 ml (4%)Polvo para reconstituirx15ml | F57: 150 | G57: MG | H57: 24 | I57: H | J57: NI | L57: NA | M57: X | S57: J46X | T57: ESTADO ASMATICO
A58: 6 | B58: Aisl 600 | C58: 1038145231 | D58: MARTIN ALEJANDRO LONDOÑO JARAMILLO | E58: AMPIcilina Sodica/SULBactam Sodico 1000/500mg Polvo para iny (Ped) | F58: 800 | G58: MG | H58: 6 | I58: H | J58: I | S58: R599 | T58: ADENOMEGALIA, NO ESPECIFICADA
A59: UCI | B59: UCE 03 | C59: 1044936783 | D59: SAIFER DAVID SIMANCAS PAJARO | E59: AZITromicina200mg/5 ml (4%)Polvo para reconstituirx15ml | F59: 300 | G59: MG | H59: 24 | I59: H | J59: I | S59: J159 | T59: NEUMONIA BACTERIANA, NO ESPECIFICADA
A60: UCI | B60: UCE 06 | C60: 1155216942 | D60: KAROL DAYANA POSSO ORTIZ | E60: Oxacilina (Sal Sodica) 1000 mg Polvo para Inyeccion | F60: 2000 | G60: MG | H60: 6 | I60: H | J60: I | S60: A972 | T60: DENGUE SEVERO
A61: UCI | B61: UCE 06 | C61: 1155216942 | D61: KAROL DAYANA POSSO ORTIZ | E61: Ceftriaxona (Sal Sodica) 1000 mg Polvo para Inyeccion | F61: 2000 | G61: MG | H61: 24 | I61: H | J61: I | M61: X | S61: A972 | T61: DENGUE SEVERO
A62: UCI | B62: UCI 08 | C62: 1015189102 | D62: JUAN MANUEL MONTOYA RODRIGUEZ | E62: Ceftriaxona (Sal Sodica) 1000 mg Polvo para Inyeccion | F62: 2000 | G62: MG | H62: 24 | I62: H | K62: I | L62: X | S62: A279 | T62: LEPTOSPIROSIS, NO ESPECIFICADA

Sheet Resumen
J1: Cambio
A2: Servicio | B2: Censo | C2: Pacientes con Antibiótico | D2: Total antibióticos | E2: % Uso | F2: INDICADO | G2: NO INDICADO | H2: % Uso inadecuado | I2: Suspensión | J2: Escalar | K2: Desescalar | L2: Reacción adversa | M2: Por Dosis | N2: Total intervenciones | O2: % Intervenciones | P2: Antibióticos restringidos | Q2: =+LISTA!A20 -> ACIclovir 250 mg Polvo para Inyeccion (REG) VIAL | R2: =+LISTA!A21 -> ACIclovir 200 mg Tableta TABLETA | S2: =+LISTA!A22 -> AMIKacina (Sulfato) 100 mg/2 ml Solucion Inyectable | T2: =+LISTA!A23 -> AMIKacina (Sulfato) 500 mg/2 ml Solucion Inyectable | U2: =+LISTA!A24 -> AMOXicilina 250 mg/5 ml (5%) Suspension Oral Frasco x 45 ml | V2: =+LISTA!A25 -> AMOXicilina / Ac CLAVulanico 500/125 mg Tableta TABLETA | W2: =+LISTA!A26 -> AMPIcilina 500 mg Polvo para Inyeccion | X2: =+LISTA!A27 -> AMPIcilina (Sal Sodica) x 1000 mg Polvo para Inyeccion | Y2: =+LISTA!A28 -> AMPIcilina Sodica/SULBactam Sodico 1000/500mg Polvo para iny (Ped) | Z2: =+LISTA!A29 -> Artemeter + Lumenfantrine (20 + 120) (SP) mg Tableta TABLETA | AA2: =+LISTA!A30 -> AZITromicina200mg/5 ml (4%)Polvo para reconstituirx15ml | AB2: =+LISTA!A31 -> Aztreonam 1000 mg polvo para inyeccion | AC2: =+LISTA!A32 -> Caspofungina 50 mg Polvo para Inyeccion (REG) VIAL | AD2: =+LISTA!A33 -> Caspofungina 70 mg Polvo para Inyeccion (REG) VIAL | AE2: =+LISTA!A34 -> Cefalexina 500 mg Capsula | AF2: =+LISTA!A35 -> Cefazolina 1000 mg Polvo para Inyeccion | AG2: =+LISTA!A36 -> Cefepime 1000 mg Polvo para inyeccion | AH2: =+LISTA!A37 -> Cefotaxime 1000 mg Polvo para inyeccion VIAL | AI2: =+LISTA!A38 -> Ceftazidima 1000 mg polvo para inyeccion VIAL | AJ2: =+LISTA!A39 -> Ceftazidima/ Avibactam 2000 mg/500 mg polvo para inyeccion AMPOLLA | AK2: =+LISTA!A40 -> Ceftriaxona (Sal Sodica) 1000 mg Polvo para Inyeccion | AL2: =+LISTA!A41 -> Cefuroxima Axetilo 250mg/5ml Susp Oral Fco x 70ml (REG) FRASCO | AM2: =+LISTA!A42 -> Ciprofloxacina (Clorhidrato) 100 mg/10 ml Sln Inyectable | AN2: =+LISTA!A43 -> Claritromicina 500 mg Tableta (REG) TABLETA | AO2: =+LISTA!A44 -> Claritromicina 500 mg Polvo para Inyeccion VIAL | AP2: =+LISTA!A45 -> Claritromicina 250 mg/5 ml(5%) Susp.Oral Frasco x 50 ml FRASCO | AQ2: =+LISTA!A46 -> Clindamicina (Fosfato) 600 mg /4ml Solucion Inyectable | AR2: =+LISTA!A47 -> Cloroquina Fosfato 250mg equivalente Cloroquina Base 150 mg (SP) TABLETA | AS2: =+LISTA!A48 -> Cloroquina Fosfato 250mg equivalente Cloroquina Base 150 mg Tableta TABLETA | AT2: =+LISTA!A49 -> Dicloxacilina 250 mg/5 ml (5%) Susp. Oral Frasco x 80 ml FRASCO | AU2: =+LISTA!A50 -> Dicloxacilina 500 mg Capsula CAPSULA | AV2: =+LISTA!A51 -> Doxiciclina 100 mg Capsula CAPSULA | AW2: =+LISTA!A52 -> Eritromicina 250 mg/5 ml (5%) Suspension Oral Frasco X 60 ml FRASCO | AX2: =+LISTA!A53 -> Eritromicina 500 mg Tableta TABLETA | AY2: =+LISTA!A54 -> Eritropoyetina humana recombinante4000UI ampolla (REG) AMPOLLA | AZ2: =+LISTA!A55 -> Fluconazol 2 mg/ml Solucion Inyectable Ampolla x 100 ml VIAL | BA2: =+LISTA!A56 -> Fluconazol 50 mg/5 ml Polvo para Suspension Frasco X 20 ml FRASCO | BB2: =+LISTA!A57 -> Gentamicina 20 mg/2 ml Solucion Inyectable AMPOLLA | BC2: =+LISTA!A58 -> Gentamicina 3 mg/ml (0.3%) Sln. Oftalmica Frasco x 5 ml FRASCO | BD2: =+LISTA!A59 -> Gentamicina 40 mg/1 ml Solucion Inyectable AMPOLLA | BE2: =+LISTA!A60 -> Gentamicina 80 mg/2 ml Solucion Inyectable AMPOLLA | BF2: =+LISTA!A61 -> HRZE (Rifam+Isonia+Piraz+Etamb 150/75/400/275) (SP) mg Tableta TABLETA | BG2: =+LISTA!A62 -> Lamivudina 150 mg Tableta TABLETA | BH2: =+LISTA!A63 -> Lamivudina 10 mg/ml Solucion Oral Frasco X 240 ml FRASCO | BI2: =+LISTA!A64 -> Lamivudina - Zidovudina (150 - 300) mg Tableta TABLETA | BJ2: =+LISTA!A65 -> Linezolid 2 mg/ml Sln Inyectable x 300 ml (REG) BOLSA | BK2: =+LISTA!A66 -> Linezolid 600 mg Tableta (REG) TABLETA | BL2: =+LISTA!A67 -> LOPinavir - RITonavir (200 +50) mg Tableta (REG) TABLETA | BM2: =+LISTA!A68 -> LOPinavir - RITonavir (400-100) mg/5 ml Sol Oral 160ml (REG) FRASCO | BN2: =+LISTA!A69 -> Meropenem 500 mg Polvo para Inyeccion (REG) | BO2: =+LISTA!A70 -> Meropenem (REG) 1000 mg Polvo para Inyeccion VIAL | BP2: =+LISTA!A71 -> Metronidazol 250 mg/5 ml Suspension Oral Frasco X 120 ml FRASCO | BQ2: =+LISTA!A72 -> Metronidazol 500 mg Solucion Inyectable UNIDAD | BR2: =+LISTA!A73 -> Metronidazol 500 mg Tableta TABLETA | BS2: =+LISTA!A74 -> Oseltamivir 75 mg Capsula (REG) (SP) CAPSULA | BT2: =+LISTA!A75 -> Oxacilina (Sal Sodica) 1000 mg Polvo para Inyeccion | BU2: =+LISTA!A76 -> PENIcilina G BENZAtinica 1.200.000 U Polvo para INYeccion VIAL | BV2: =+LISTA!A77 -> PENIcilina G SODica 1.000.000 U Polvo para INYeccion VIAL | BW2: =+LISTA!A78 -> Piperacilina - Tazobactam 4500 mg Polvo para Inyeccion VIAL | BX2: =+LISTA!A79 -> PRIMaquina (Fosfato) 15 mg TABleta (SP) TABLETA | BY2: =+LISTA!A80 -> PRIMaquina (Fosfato) 5 mg TABleta (SP) TABLETA | BZ2: =+LISTA!A81 -> TRIMEtoprim 160 mg SULFAmetoxazol 800 mg TABleta | CA2: =+LISTA!A82 -> Vancomicina (Clorhidrato) 500 mg Polvo para Inyeccion | CB2: =+LISTA!A83 -> Zidovudina 10 mg/ml Solucion Oral Frasco X 240 ml FRASCO | CC2: =+LISTA!A84 -> Zidovudina 300 mg Tableta TABLETA | CD2: =+LISTA!A85 -> Nitrofurantoina 100 mg Capsula CAPSULA | CE2: =+LISTA!A86 -> Nitrofurantoina 50 mg Capsula CAPSULA | CF2: =+LISTA!A87 -> Nitroglicerina 50 mg/10 ml (0.5%) Solucion Inyectable VIAL
A3: 5 PISO | B3: =+COUNTIF(COMPILADO!$A$2:$A$165,5) -> 8 | C3: =IFERROR(('10-10-2023'!AC4+'13-10-2023'!AC4+'17-10-2023'!AC4+'20-10-2023'!AC4+'24-10-2023'!AC4+'27-10-2023'!AB4),0) -> 36 | D3: =B3 -> 8 | E3: =IFERROR((B3/C3),0) -> 0.22222222 | F3: =COUNTIFS(COMPILADO!$A$2:$A$165,5,COMPILADO!$J$2:$J$165,"I") -> 5 | G3: =COUNTIFS(COMPILADO!$A$2:$A$165,5,COMPILADO!$J$2:$J$165,"NI") -> 2 | H3: =IFERROR((G3/D3),0) -> 0.25 | I3: =COUNTIFS(COMPILADO!$A$2:$A$165,5,COMPILADO!$M$2:$M$165,"X") -> 1 | J3: =COUNTIFS(COMPILADO!$A$2:$A$165,5,COMPILADO!$N$2:$N$165,"X") -> 0 | K3: =COUNTIFS(COMPILADO!$A$2:$A$165,5,COMPILADO!$O$2:$O$165,"X") -> 0 | L3: =COUNTIFS(COMPILADO!$A$2:$A$165,5,COMPILADO!$P$2:$P$165,"X") -> 0 | M3: =COUNTIFS(COMPILADO!$A$2:$A$165,5,COMPILADO!$Q$2:$Q$165,"X") -> 0 | N3: =SUM(I3:M3) -> 1 | O3: {=SUM(I3:M3/D3)} -> 0.125 | P3: =SUM(AC3+AD3+AG3+AM3+BF3+BG3+BH3+BI3+BJ3+BK3+BL3+BM3+BN3+BO3+BW3+CA3+CB3+CC3) -> 0 | Q3: =COUNTIFS(COMPILADO!$A$2:$A$165,5,COMPILADO!$E$2:$E$165,Q2) -> 0 | R3: =COUNTIFS(COMPILADO!$A$2:$A$165,5,COMPILADO!$E$2:$E$165,R2) -> 0 | S3: =COUNTIFS(COMPILADO!$A$2:$A$165,5,COMPILADO!$E$2:$E$165,S2) -> 3 | T3: =COUNTIFS(COMPILADO!$A$2:$A$165,5,COMPILADO!$E$2:$E$165,T2) -> 2 | U3: =COUNTIFS(COMPILADO!$A$2:$A$165,5,COMPILADO!$E$2:$E$165,U2) -> 0 | V3: =COUNTIFS(COMPILADO!$A$2:$A$165,5,COMPILADO!$E$2:$E$165,V2) -> 0 | W3: =COUNTIFS(COMPILADO!$A$2:$A$165,5,COMPILADO!$E$2:$E$165,W2) -> 0 | X3: =COUNTIFS(COMPILADO!$A$2:$A$165,5,COMPILADO!$E$2:$E$165,X2) -> 0 | ... CF3: =COUNTIFS(COMPILADO!$A$2:$A$165,5,COMPILADO!$E$2:$E$165,CF2) -> 0
A4: 6 PISO | B4: =+COUNTIF(COMPILADO!$A$2:$A$165,6) -> 21 | C4: =IFERROR(('10-10-2023'!AC5+'13-10-2023'!AC5+'17-10-2023'!AC5+'20-10-2023'!AC5+'24-10-2023'!AC5+'27-10-2023'!AB5),0) -> 53 | D4: =B4 -> 21 | E4: =IFERROR((B4/C4),0) -> 0.39622642 | F4: =COUNTIFS(COMPILADO!$A$2:$A$165,6,COMPILADO!$J$2:$J$165,"I") -> 15 | G4: =COUNTIFS(COMPILADO!$A$2:$A$165,6,COMPILADO!$J$2:$J$165,"NI") -> 4 | H4: =IFERROR((G4/D4),0) -> 0.19047619 | I4: =COUNTIFS(COMPILADO!$A$2:$A$165,6,COMPILADO!$M$2:$M$165,"X") -> 6 | J4: =COUNTIFS(COMPILADO!$A$2:$A$165,6,COMPILADO!$N$2:$N$165,"X") -> 0 | K4: =COUNTIFS(COMPILADO!$A$2:$A$165,6,COMPILADO!$O$2:$O$165,"X") -> 0 | L4: =COUNTIFS(COMPILADO!$A$2:$A$165,6,COMPILADO!$P$2:$P$165,"X") -> 0 | M4: =COUNTIFS(COMPILADO!$A$2:$A$165,6,COMPILADO!$Q$2:$Q$165,"X") -> 0 | N4: =SUM(I4:M4) -> 6 | O4: {=SUM(I4:M4/D4)} -> 0.28571429 | P4: =SUM(AC4+AD4+AG4+AM4+BF4+BG4+BH4+BI4+BJ4+BK4+BL4+BM4+BN4+BO4+BW4+CA4+CB4+CC4) -> 0 | Q4: =COUNTIFS(COMPILADO!$A$2:$A$165,6,COMPILADO!$E$2:$E$165,Q2) -> 0 | R4: =COUNTIFS(COMPILADO!$A$2:$A$165,6,COMPILADO!$E$2:$E$165,R2) -> 0 | S4: =COUNTIFS(COMPILADO!$A$2:$A$165,6,COMPILADO!$E$2:$E$165,S2) -> 1 | T4: =COUNTIFS(COMPILADO!$A$2:$A$165,6,COMPILADO!$E$2:$E$165,T2) -> 0 | U4: =COUNTIFS(COMPILADO!$A$2:$A$165,6,COMPILADO!$E$2:$E$165,U2) -> 0 | V4: =COUNTIFS(COMPILADO!$A$2:$A$165,6,COMPILADO!$E$2:$E$165,V2) -> 0 | W4: =COUNTIFS(COMPILADO!$A$2:$A$165,6,COMPILADO!$E$2:$E$165,W2) -> 2 | X4: =COUNTIFS(COMPILADO!$A$2:$A$165,6,COMPILADO!$E$2:$E$165,X2) -> 5 | ... CF4: =COUNTIFS(COMPILADO!$A$2:$A$165,6,COMPILADO!$E$2:$E$165,CF2) -> 0
A5: 7 PISO | B5: =+COUNTIF(COMPILADO!$A$2:$A$165,7) -> 14 | C5: =IFERROR(('10-10-2023'!AC7+'13-10-2023'!AC7+'17-10-2023'!AC7+'20-10-2023'!AC7+'24-10-2023'!AC7+'27-10-2023'!AB7),0) -> 0 | D5: =B5 -> 14 | E5: =IFERROR((B5/C5),0) -> 0 | F5: =COUNTIFS(COMPILADO!$A$2:$A$165,7,COMPILADO!$J$2:$J$165,"I") -> 13 | G5: =COUNTIFS(COMPILADO!$A$2:$A$165,7,COMPILADO!$J$2:$J$165,"NI") -> 0 | H5: =IFERROR((G5/D5),0) -> 0 | I5: =COUNTIFS(COMPILADO!$A$2:$A$165,7,COMPILADO!$M$2:$M$165,"X") -> 1 | J5: =COUNTIFS(COMPILADO!$A$2:$A$165,7,COMPILADO!$N$2:$N$165,"X") -> 0 | K5: =COUNTIFS(COMPILADO!$A$2:$A$165,7,COMPILADO!$O$2:$O$165,"X") -> 0 | L5: =COUNTIFS(COMPILADO!$A$2:$A$165,7,COMPILADO!$P$2:$P$165,"X") -> 0 | M5: =COUNTIFS(COMPILADO!$A$2:$A$165,7,COMPILADO!$Q$2:$Q$165,"X") -> 0 | N5: =SUM(I5:M5) -> 1 | O5: {=SUM(I5:M5/D5)} -> 0.071428571 | P5: =SUM(AC5+AD5+AG5+AM5+BF5+BG5+BH5+BI5+BJ5+BK5+BL5+BM5+BN5+BO5+BW5+CA5+CB5+CC5) -> 2 | Q5: =COUNTIFS(COMPILADO!$A$2:$A$165,7,COMPILADO!$E$2:$E$165,Q2) -> 0 | R5: =COUNTIFS(COMPILADO!$A$2:$A$165,7,COMPILADO!$E$2:$E$165,R2) -> 0 | S5: =COUNTIFS(COMPILADO!$A$2:$A$165,7,COMPILADO!$E$2:$E$165,S2) -> 1 | T5: =COUNTIFS(COMPILADO!$A$2:$A$165,7,COMPILADO!$E$2:$E$165,T2) -> 1 | U5: =COUNTIFS(COMPILADO!$A$2:$A$165,7,COMPILADO!$E$2:$E$165,U2) -> 0 | V5: =COUNTIFS(COMPILADO!$A$2:$A$165,7,COMPILADO!$E$2:$E$165,V2) -> 0 | W5: =COUNTIFS(COMPILADO!$A$2:$A$165,7,COMPILADO!$E$2:$E$165,W2) -> 0 | X5: =COUNTIFS(COMPILADO!$A$2:$A$165,7,COMPILADO!$E$2:$E$165,X2) -> 0 | ... CF5: =COUNTIFS(COMPILADO!$A$2:$A$165,7,COMPILADO!$E$2:$E$165,CF2) -> 0
A6: UCI | B6: =+COUNTIF(COMPILADO!$A$2:$A$165,"UCI") -> 15 | C6: =IFERROR(('10-10-2023'!AC7+'13-10-2023'!AC7+'17-10-2023'!AC7+'20-10-2023'!AC7+'24-10-2023'!AC7+'27-10-2023'!AB7),) -> 0 | D6: =B6 -> 15 | E6: =IFERROR((B6/C6),0) -> 0 | F6: =COUNTIFS(COMPILADO!$A$2:$A$165,"UCI",COMPILADO!$J$2:$J$165,"I") -> 11 | G6: =COUNTIFS(COMPILADO!$A$2:$A$165,"UCI",COMPILADO!$J$2:$J$165,"NI") -> 2 | H6: =IFERROR((G6/D6),0) -> 0.13333333 | I6: =COUNTIFS(COMPILADO!$A$2:$A$165,"UCI",COMPILADO!$M$2:$M$165,"X") -> 5 | J6: =COUNTIFS(COMPILADO!$A$2:$A$165,"UCI",COMPILADO!$N$2:$N$165,"X") -> 1 | K6: =COUNTIFS(COMPILADO!$A$2:$A$165,"UCI",COMPILADO!$O$2:$O$165,"X") -> 0 | L6: =COUNTIFS(COMPILADO!$A$2:$A$165,"UCI",COMPILADO!$P$2:$P$165,"X") -> 0 | M6: =COUNTIFS(COMPILADO!$A$2:$A$165,"UCI",COMPILADO!$Q$2:$Q$165,"X") -> 1 | N6: =SUM(I6:M6) -> 7 | O6: {=SUM(I6:M6/D6)} -> 0.46666667 | P6: =SUM(AC6+AD6+AG6+AM6+BF6+BG6+BH6+BI6+BJ6+BK6+BL6+BM6+BN6+BO6+BW6+CA6+CB6+CC6) -> 3 | Q6: =COUNTIFS(COMPILADO!$A$2:$A$165,"UCI",COMPILADO!$E$2:$E$165,Q2) -> 0 | R6: =COUNTIFS(COMPILADO!$A$2:$A$165,"UCI",COMPILADO!$E$2:$E$165,R2) -> 0 | S6: =COUNTIFS(COMPILADO!$A$2:$A$165,"UCI",COMPILADO!$E$2:$E$165,S2) -> 0 | T6: =COUNTIFS(COMPILADO!$A$2:$A$165,"UCI",COMPILADO!$E$2:$E$165,T2) -> 0 | U6: =COUNTIFS(COMPILADO!$A$2:$A$165,"UCI",COMPILADO!$E$2:$E$165,U2) -> 0 | V6: =COUNTIFS(COMPILADO!$A$2:$A$165,"UCI",COMPILADO!$E$2:$E$165,V2) -> 0 | W6: =COUNTIFS(COMPILADO!$A$2:$A$165,"UCI",COMPILADO!$E$2:$E$165,W2) -> 0 | X6: =COUNTIFS(COMPILADO!$A$2:$A$165,"UCI",COMPILADO!$E$2:$E$165,X2) -> 1 | ... CF6: =COUNTIFS(COMPILADO!$A$2:$A$165,"UCI",COMPILADO!$E$2:$E$165,CF2) -> 0
A7: URGENCIAS | B7: =+COUNTIF(COMPILADO!$A$2:$A$165,"URGENCIAS") -> 1 | C7: =IFERROR(('10-10-2023'!AC8+'13-10-2023'!AC8+'17-10-2023'!AC8+'20-10-2023'!AC8+'24-10-2023'!AC8+'27-10-2023'!AB8),0) -> 0 | D7: =B7 -> 1 | E7: =IFERROR((B7/C7),0) -> 0 | F7: =COUNTIFS(COMPILADO!$A$2:$A$165,"URGENCIAS",COMPILADO!$J$2:$J$165,"I") -> 1 | G7: =COUNTIFS(COMPILADO!$A$2:$A$165,"URGENCIAS",COMPILADO!$J$2:$J$165,"NI") -> 0 | H7: =IFERROR((G7/D7),0) -> 0 | I7: =COUNTIFS(COMPILADO!$A$2:$A$165,"URGENCIAS",COMPILADO!$M$2:$M$165,"X") -> 0 | J7: =COUNTIFS(COMPILADO!$A$2:$A$165,"URGENCIAS",COMPILADO!$N$2:$N$165,"X") -> 0 | K7: =COUNTIFS(COMPILADO!$A$2:$A$165,"URGENCIAS",COMPILADO!$O$2:$O$165,"X") -> 0 | L7: =COUNTIFS(COMPILADO!$A$2:$A$165,"URGENCIAS",COMPILADO!$P$2:$P$165,"X") -> 0 | M7: =COUNTIFS(COMPILADO!$A$2:$A$165,"URGENCIAS",COMPILADO!$Q$2:$Q$165,"X") -> 0 | N7: =SUM(I7:M7) -> 0 | O7: {=SUM(I7:M7/D7)} -> 0 | P7: =SUM(AC7+AD7+AG7+AM7+BF7+BG7+BH7+BI7+BJ7+BK7+BL7+BM7+BN7+BO7+BW7+CA7+CB7+CC7) -> 0 | Q7: =COUNTIFS(COMPILADO!$A$2:$A$165,"URGENCIAS",COMPILADO!$E$2:$E$165,Q2) -> 0 | R7: =COUNTIFS(COMPILADO!$A$2:$A$165,"URGENCIAS",COMPILADO!$E$2:$E$165,R2) -> 0 | S7: =COUNTIFS(COMPILADO!$A$2:$A$165,"URGENCIAS",COMPILADO!$E$2:$E$165,S2) -> 0 | T7: =COUNTIFS(COMPILADO!$A$2:$A$165,"URGENCIAS",COMPILADO!$E$2:$E$165,T2) -> 0 | U7: =COUNTIFS(COMPILADO!$A$2:$A$165,"URGENCIAS",COMPILADO!$E$2:$E$165,U2) -> 0 | V7: =COUNTIFS(COMPILADO!$A$2:$A$165,"URGENCIAS",COMPILADO!$E$2:$E$165,V2) -> 0 | W7: =COUNTIFS(COMPILADO!$A$2:$A$165,"URGENCIAS",COMPILADO!$E$2:$E$165,W2) -> 0 | X7: =COUNTIFS(COMPILADO!$A$2:$A$165,"URGENCIAS",COMPILADO!$E$2:$E$165,X2) -> 0 | ... CF7: =COUNTIFS(COMPILADO!$A$2:$A$165,"URGENCIAS",COMPILADO!$E$2:$E$165,CF2) -> 0

Sheet LISTA
A1: PISO
A2: 4 PISO
A3: 5 PISO
A4: 6 PISO
A5: 7 PISO
A6: UCE
A7: UCI
A8: URGENCIAS
A19: ANTIMICROBIANO | B19: CRITERIO | C19: RESTRINGIDO | D19: HOMOLOGO
A20: ACIclovir 250 mg Polvo para Inyeccion (REG) VIAL | B20: SI | C20: NO | D20: 1
A21: ACIclovir 200 mg Tableta TABLETA | B21: SI | C21: NO | D21: 1
A22: AMIKacina (Sulfato) 100 mg/2 ml Solucion Inyectable | B22: SI | C22: NO | D22: 2
A23: AMIKacina (Sulfato) 500 mg/2 ml Solucion Inyectable | B23: SI | C23: NO | D23: 2
A24: AMOXicilina 250 mg/5 ml (5%) Suspension Oral Frasco x 45 ml | B24: SI | C24: NO | D24: 3
A25: AMOXicilina / Ac CLAVulanico 500/125 mg Tableta TABLETA | B25: SI | C25: NO | D25: 4
A26: AMPIcilina 500 mg Polvo para Inyeccion | B26: SI | C26: NO | D26: 5
A27: AMPIcilina (Sal Sodica) x 1000 mg Polvo para Inyeccion | B27: SI | C27: NO | D27: 5
A28: AMPIcilina Sodica/SULBactam Sodico 1000/500mg Polvo para iny (Ped) | B28: SI | C28: NO | D28: 6
A29: Artemeter + Lumenfantrine (20 + 120) (SP) mg Tableta TABLETA | B29: SI | C29: NO | D29: 7
A30: AZITromicina200mg/5 ml (4%)Polvo para reconstituirx15ml | B30: SI | C30: NO | D30: 8
A31: Aztreonam 1000 mg polvo para inyeccion | B31: SI | C31: SI | D31: 9
... A87: Nitroglicerina 50 mg/10 ml (0.5%) Solucion Inyectable VIAL | B87: SI | C87: NO | D87: 43
B88: SI | D88: 44
B89: SI | D89: 45
B90: SI | D90: 46
B91: SI | D91: 47
B92: SI | D92: 48
B93: SI | D93: 49
B94: SI | D94: 50
B95: SI | D95: 51
B96: SI | D96: 52
B97: SI | D97: 53
B98: SI | D98: 54
B99: SI | D99: 55
... B181: SI | D181: 137
A183: GUIA | B183: PREGUNTAS
A184: 1 | B184: TOS? | C184: =CHOOSE(3,B184,B185,B186,B187) -> MOCOS? | D184: 219
A185: 2 | B185: FIEBRE? | C185: =CHOOSE(3,B185,B186,B187,B188) -> J219 NEUMONI
A186: 3 | B186: MOCOS? | C186: =CHOOSE(3,B186,B187,B188,B189) -> 0
A187: 4 | B187: J219 NEUMONI | C187: =CHOOSE(3,B187,B188,B189,B190) -> 0
A216: CODIGO CIE10
A217: A000 | B217: COLERA DEBIDO A VIBRIO CHOLERAE 01, BIOTIPO CHOLERAE
A218: A001 | B218: COLERA DEBIDO A VIBRIO CHOLERAE 01, BIOTIPO EL TOR
A219: A00199 | B219: COLERA ASIATICO
A220: A009 | B220: COLERA, NO ESPECIFICADO
A221: A010 | B221: FIEBRE TIFOIDEA
A222: A011 | B222: FIEBRE PARATIFOIDEA A
A223: A012 | B223: FIEBRE PARATIFOIDEA B
A224: A013 | B224: FIEBRE PARATIFOIDEA C
A225: A014 | B225: FIEBRE PARATIFOIDEA, NO ESPECIFICADA
A226: A020 | B226: ENTERITIS DEBIDA A SALMONELLA
A227: A021 | B227: SEPSIS DEBIDA A SALMONELLA
A228: A022 | B228: INFECCIONES LOCALIZADAS DEBIDAS A SALMONELLA
... A12793: Z999 | B12793: DEPENDENCIA DE MAQUINA Y DISPOSITIVO CAPACITANTE, NO ESPECIFICADA

Sheet Dosis Mx
A1: 1 | B1: AMIKacina (Sulfato) 500 mg/2 ml Solucion Inyectable | C1: 15 | D1: 0 | E1: =+C1 -> 15 | F1: mg | G1: 1 | H1: kg | I1: 0 | J1: 24 | K1: 500 | L1: 0 | N1: 15 | O1: 0 | R1: AMIKacina (Sulfato) 500 mg/2 ml Solucion Inyectable | S1: ITU | T1: IV | U1: 15 | V1: 0 | W1: =U1 -> 15 | X1: 24 | Z1: Amikacina | AA1: IV | AB1: 15 | AC1: 24 | AI1: ITU | AJ1: Amikacina | AK1: IV | AL1: 10 | AM1: 15 | AN1: 0 | AO1: 24
A2: 2 | B2: AMIKacina (Sulfato) 100 mg/2 ml Solucion Inyectable | C2: 15 | D2: 0 | E2: =+C2 -> 15 | F2: mg | G2: 1 | H2: kg | I2: 0 | J2: 24 | K2: 500 | L2: 0 | N2: 15 | O2: 0 | R2: AMIKacina (Sulfato) 100 mg/2 ml Solucion Inyectable | S2: ITU | T2: IV | U2: 15 | V2: 0 | W2: =U2 -> 15 | X2: 24 | Z2: Gentamicina | AA2: IV | AB2: 7.5 | AC2: 24 | AI2: ITU | AJ2: Amoxicilina Clavulanato | AK2: Oral | AL2: 40 | AN2: 0 | AO2: 8 | AQ2: Amoxicilina Clavulanato | AR2: Oral | AS2: 25 | AT2: 12 | AV2: Amoxicilina | AW2: Vía oral | AX2: 90 | AY2: 8
A3: 3 | B3: AMOXicilina 250 mg/5 ml (5%) Suspension Oral Frasco x 45 ml | C3: 90 | D3: 0 | E3: 90 | F3: mg | G3: 1 | H3: kg | I3: 8 | J3: 12 | K3: 250 | L3: 0 | N3: 180 | O3: 0 | P3: OTITIS | R3: AMOXicilina 500 mg Capsula | S3: ITU | T3: Oral | U3: 7,5 | V3: 0 | W3: =U3 -> 7,5 | X3: 24 | Z3: Ceftriaxona | AA3: IV | AB3: 75 | AC3: 24 | AV3: Azitromicina | AW3: Vía oral | AX3: 15 | AY3: 24
A4: 4 | B4: AMOXicilina 250 mg/5 ml (5%) Suspension Oral Frasco x 45 ml | C4: 90 | D4: 0 | E4: 90 | F4: mg | G4: 1 | H4: kg | I4: 8 | J4: 12 | K4: 250 | L4: 0 | N4: 180 | O4: 0 | P4: SINUSITIS | R4: AMOXicilina 250 mg/5 ml (5%) Suspension Oral Frasco x 45 ml | S4: ITU | T4: Oral | U4: 7,5 | V4: 0 | W4: =U4 -> 7,5 | X4: 24 | Z4: Cefepime | AA4: IV | AB4: 150 | AC4: 8 | AV4: Ampicilina | AW4: Via endovenosa | AX4: 150-200 mg/kg/dia | AY4: 6
A5: 5 | B5: AMOXicilina 250 mg/5 ml (5%) Suspension Oral Frasco x 45 ml | C5: 50 | D5: 0 | E5: 50 | F5: mg | G5: 1 | H5: kg | I5: 0 | J5: 24 | K5: 250 | L5: 0 | N5: 50 | O5: 0 | P5: NEUMONIA | R5: Aztreonam 1000 mg polvo para inyeccion | S5: ITU | T5: IV | U5: 75 | V5: 0 | W5: =U5 -> 75 | X5: 24 | Z5: Aztreonam | AA5: IV | AB5: 90 – 120 | AC5: 8 | AV5: Amp/sulbactam | AW5: Via endovenosa | AX5: 150-200 | AY5: 6
A6: 6 | B6: AMPIcilina 500 mg Polvo para Inyeccion | C6: 100 | D6: 200 | E6: =+(C6+D6)/2 -> 150 | F6: mg | G6: 1 | H6: kg | I6: 0 | J6: 6 | K6: 500 | L6: 0 | N6: 400 | O6: 800 | R6: Cefalexina 500 mg Capsula | S6: ITU | T6: Oral | U6: 150 | V6: 0 | W6: =U6 -> 150 | X6: 24 | Z6: Piperacilina tazobactam | AA6: IV | AB6: 300 – 400 | AC6: 6 – 8 | AI6: ITU | AJ6: Aztreonam | AK6: IV | AL6: 90 | AM6: 120 | AN6: 0 | AO6: 8
A7: 7 | B7: AMPIcilina (Sal Sodica) x 1000 mg Polvo para Inyeccion | C7: 100 | D7: 200 | E7: =+(C7+D7)/2 -> 150 | F7: mg | G7: 1 | H7: kg | I7: 0 | J7: 6 | K7: 1000 | L7: 0 | N7: 400 | O7: 800 | R7: Cefalexina 250 mg/5 ml (5%) Suspension Oral Frasco X 60 ml | S7: ITU | T7: Oral | U7: 150 | V7: 0 | W7: =U7 -> 150 | X7: 24 | Z7: Ciprofloxacina | AA7: Oral/IV | AB7: 20 – 30 | AC7: 8 – 12 | AI7: ITU | AJ7: Cefalexina | AK7: Oral | AL7: 50 | AM7: 100 | AN7: 0 | AO7: 6 | AQ7: Cefalexina | AR7: Oral | AS7: 25-50 | AT7: 6-8
A8: 8 | B8: AMPIcilina Sodica/SULBactam Sodico 1000/500mg Polvo para iny (Ped) | C8: 100 | D8: 200 | E8: =+(C8+D8)/2 -> 150 | F8: mg | G8: 1 | H8: kg | I8: 6 | J8: 8 | K8: 1000 | L8: 500 | N8: 400 | O8: 600 | R8: Cefepime 1000 mg Polvo para inyeccion | S8: ITU | T8: IV | U8: 90 | V8: 0 | W8: =U8 -> 90 | X8: 24 | Z8: Cefalexina | AA8: Oral | AB8: 50 – 100 | AC8: 6 | AQ8: Cefazolina | AR8: IV | AS8: 25 | AT8: 6
A9: 9 | B9: AZITromicina200mg/5 ml (4%)Polvo para reconstituirx15ml | E9: 200 | F9: mg | G9: 1 | H9: kg | K9: 200 | L9: 0 | R9: Ceftriaxona (Sal Sodica) 1000 mg Polvo para Inyeccion | S9: ITU | T9: IV | U9: 300 | V9: 0 | W9: =U9 -> 300 | X9: 24 | Z9: Amoxicilina Clavulanato | AA9: Oral | AB9: 50 | AC9: 8 | AI9: ITU | AJ9: Cefepime | AK9: IV | AL9: 150 | AM9: 0 | AN9: 0 | AO9: 8 | AQ9: Ceftarolina* | AR9: IV | AS9: 6-12 | AT9: 8
A10: 10 | B10: Aztreonam 1000 mg polvo para inyeccion | C10: 90 | D10: 120 | E10: =+C10 -> 90 | F10: mg | G10: 1 | H10: kg | I10: 6 | J10: 8 | K10: 1000 | L10: 0 | N10: 270 | O10: 360 | R10: Ciprofloxacina (Clorhidrato) 100 mg/10 ml Sln Inyectable | S10: ITU | T10: Oral/IV | U10: 20 | V10: 30 | W10: =+(U10+V10)/2 -> 25 | X10: 24 | Z10: Trimetoprim sulfametoxasol | AA10: Oral/IV | AB10: 10 | AC10: 12 | AV10: Cefotaxima | AW10: Via endovenosa | AX10: 150 | AY10: 8
A11: 11 | B11: Cefalexina 500 mg Capsula | C11: 25 | D11: 100 | E11: =+(C11+D11)/2 -> 62.5 | F11: mg | G11: 1 | H11: kg | I11: 0 | J11: 6 | K11: 500 | L11: 0 | N11: 100 | O11: 400 | R11: Ciprofloxacina (Clorhidrato) 500 mg de Base Tableta | S11: ITU | T11: Oral/IV | U11: 20 | V11: 30 | W11: =+(U11+V11)/2 -> 25 | X11: 24 | Z11: Nitrofurantoina | AA11: Oral | AB11: 5 – 7 | AC11: 6 | AI11: ITU | AJ11: Ceftriaxona | AK11: IV | AL11: 75 | AM11: 0 | AN11: 0 | AO11: 24 | AV11: Ceftriaxona | AW11: Via endovenosa | AX11: 50-100 | AY11: 24
A12: 12 | B12: Cefazolina 1000 mg Polvo para Inyeccion | C12: 25 | D12: 100 | E12: =+(C12+D12)/2 -> 62.5 | F12: mg | G12: 1 | H12: kg | I12: 0 | J12: 6 | K12: 1000 | L12: 0 | N12: 100 | O12: 400 | R12: Gentamicina 20 mg/2 ml Solucion Inyectable | S12: ITU | T12: IV | U12: 50 | V12: 0 | W12: =U12 -> 50 | X12: 24 | Z12: Cefalexina | AA12: Oral | AB12: 25 – 100 | AC12: 6 – 8 | AI12: ITU | AJ12: Ciprofloxacina | AK12: Oral/IV | AL12: 20 | AM12: 30 | AN12: 8 | AO12: 12
A13: 13 | B13: Cefepime 1000 mg Polvo para inyeccion | C13: 50 | D13: 0 | E13: =+C13 -> 50 | F13: mg | G13: 1 | H13: kg | I13: 8 | J13: 12 | K13: 1000 | L13: 0 | N13: 200 | O13: 100 | R13: Gentamicina 40 mg/1 ml Solucion Inyectable | S13: ITU | T13: IV | U13: 50 | V13: 0 | W13: =U13 -> 50 | X13: 24 | Z13: Doxiciclina | AA13: Oral | AB13: 100 – 200 | AC13: 6 – 8 | AQ13: Clindamicina | AR13: Ora/IV | AS13: 30-40 | AT13: 45144 | AV13: Clindamicina | AW13: Via endovenosa | AX13: 40 | AY13: 8
A14: 14 | B14: Cefotaxima | C14: 90 | D14: 180 | E14: =+(C14+D14)/2 -> 135 | F14: mg | G14: 1 | H14: kg | I14: 6 | J14: 8 | K14: 0 | L14: 0 | N14: 360 | O14: 540 | R14: Gentamicina 80 mg/2 ml Solucion Inyectable | S14: ITU | T14: IV | U14: 50 | V14: 0 | W14: =U14 -> 50 | X14: 24 | Z14: Amoxicilina Clavulanato | AA14: Oral | AB14: 50 | AC14: 12 | AQ14: Daptomicina* | AR14: IV | AS14: 45204 | AT14: 24
A15: 15 | B15: Ceftriaxona (Sal Sodica) 1000 mg Polvo para Inyeccion | C15: 50 | D15: 100 | E15: =+(C15+D15)/2 -> 75 | F15: mg | G15: 1 | H15: kg | I15: 0 | J15: 24 | K15: 1000 | L15: 0 | N15: 50 | O15: 100 | P15: Otros | R15: Nitrofurantoina 100 mg Capsula | S15: ITU | T15: Oral | U15: 50 | V15: 0 | W15: =U15 -> 50 | X15: 24 | Z15: Clindamicina | AA15: Ora/IV | AB15: 10 | AC15: 6 – 8 | AQ15: Doxiciclina | AR15: Oral | AS15: 25-50 | AT15: 45144
A16: 15 | B16: Ceftriaxona (Sal Sodica) 1000 mg Polvo para Inyeccion | C16: 50 | D16: 100 | E16: =+(C16+D16)/2 -> 75 | F16: mg | G16: 1 | H16: kg | I16: 0 | J16: 12 | K16: 1000 | L16: 0 | N16: 100 | O16: 200 | P16: MENINGITIS | R16: Nitrofurantoina 50 mg Capsula | S16: ITU | T16: Oral | U16: 50 | V16: 0 | W16: =U16 -> 50 | X16: 24 | Z16: Cefazolina | AA16: IV | AB16: 50 – 150 | AC16: 6 | AI16: ITU | AJ16: Gentamicina | AK16: IV | AL16: 7.5 | AM16: 0 | AN16: 0 | AO16: 24
A17: 16 | B17: Claritromicina | C17: 7.5 | D17: 0 | E17: =+C17 -> 7.5 | F17: mg | G17: 1 | H17: kg | I17: 0 | J17: 12 | K17: 0 | L17: 0 | N17: 15 | O17: 0 | R17: Piperacilina - Tazobactam 4500 mg Polvo para Inyeccion | S17: ITU | T17: IV | U17: 10 | V17: 0 | W17: =U17 -> 10 | X17: 24 | Z17: Trimetoprim sulfametoxazol | AA17: Oral/IV | AB17: 5 | AC17: 12 | AQ17: Linezolid* | AR17: IV/VO | AS17: 10 | AT17: 45268
A18: 17 | B18: Clindamicina (Fosfato) 600 mg /4ml Solucion Inyectable | C18: 10 | D18: 0 | E18: =+C18 -> 10 | F18: mg | G18: 1 | H18: kg | I18: 6 | J18: 8 | K18: 600 | L18: 0 | N18: 40 | O18: 30 | R18: TRIMEtoprim-SULFAmetoxazol (40-200)mg/5 ml SUSP | S18: ITU | T18: Oral/IV | U18: 5 | V18: 7 | W18: =+(U18+V18)/2 -> 6 | X18: 24 | Z18: Oxacilina | AA18: IV | AB18: 200 | AC18: 6 | AI18: ITU | AJ18: Nitrofurantoina | AK18: Oral | AL18: 5 | AM18: 7 | AN18: 0 | AO18: 6
A19: 18 | B19: Gentamicina | C19: 5 | D19: 0 | E19: 5 | F19: mg | G19: 1 | H19: kg | I19: 0 | J19: 24 | K19: 0 | L19: 0 | N19: 5 | O19: 0 | R19: Trimetoprim - Sulfametoxazol (80 - 400) mg/5ml Sol Iny | S19: ITU | T19: Oral/IV | U19: 5 | V19: 7 | W19: =+(U19+V19)/2 -> 6 | X19: 24 | Z19: Piperacilina tazobactam | AA19: IV | AB19: 300 – 400 | AC19: 6 – 8 | AV19: Oseltamivir | AW19: Vía oral | AX19: 4 | AY19: 12
A20: 19 | B20: Linezolid | C20: 10 | D20: 0 | E20: =+C20 -> 10 | F20: mg | G20: 1 | H20: kg | I20: 0 | J20: 8 | K20: 0 | L20: 0 | M20: >7días | N20: 30 | O20: 0 | R20: Cefalexina 500 mg Capsula | S20: ITB | T20: Oral | U20: 25 | V20: 100 | W20: =+(U20+V20)/2 -> 62.5 | X20: 24 | Z20: Vancomicina | AA20: IV | AB20: 60 | AC20: 6 | AQ20: Oxacilina | AR20: IV | AS20: 50 | AT20: 6
A21: 19 | B21: Linezolid | C21: 10 | D21: 0 | E21: =+C21 -> 10 | F21: mg | G21: 1 | H21: kg | I21: 0 | J21: 12 | K21: 0 | L21: 0 | M21: Neonatos | N21: 20 | O21: 0 | R21: Cefalexina 250 mg/5 ml (5%) Suspension Oral Frasco X 60 ml | S21: ITB | T21: Oral | U21: 25 | V21: 100 | W21: =+(U21+V21)/2 -> 62.5 | X21: 24 | Z21: Linezolid* | AA21: IV/VO | AB21: 20-30 | AC21: 8 – 12 | AV21: Penicilina G | AW21: Via endovenosa | AX21: 100.000-250.000 UI/kg/dia | AY21: 4-6 horas
A22: 19 | B22: Linezolid | C22: 400 | D22: 600 | E22: =+(C22+D22)/2 -> 500 | F22: mg | G22: 1 | H22: kg | I22: 0 | J22: 12 | K22: 0 | L22: 0 | M22: >12años | N22: 800 | O22: 1200 | R22: Doxiciclina 100 mg Capsula | S22: ITB | T22: Oral | U22: 100 | V22: 200 | W22: =+(U22+V22)/2 -> 150 | X22: 24 | Z22: Daptomicina* | AA22: IV | AB22: 5 – 10 | AC22: 24 | AI22: ITU | AJ22: Piperacilina tazobactam | AK22: IV | AL22: 300 | AM22: 400 | AN22: 6 | AO22: 8 | AQ22: Piperacilina tazobactam | AR22: IV | AS22: 75-100 | AT22: 6-8
A23: 20 | B23: Meropenem 500 mg Polvo para Inyeccion (REG) | C23: 60 | D23: 120 | E23: =+(C23+D23)/2 -> 90 | F23: mg | G23: 1 | H23: kg | I23: 0 | J23: 8 | K23: 500 | L23: 0 | N23: 180 | O23: 360 | R23: AMOXicilina 500 mg Capsula | S23: ITB | T23: Oral | U23: 50 | V23: 0 | W23: =U23 -> 50 | X23: 24 | Z23: Ceftarolina* | AA23: IV | AB23: 18 – 36 | AC23: 8 | AI23: ITU | AJ23: Trimetoprim sulfametoxasol | AK23: Oral/IV | AL23: 10 | AM23: 0 | AN23: 0 | AO23: 12 | AQ23: Trimetoprim sulfametoxazol | AR23: Oral/IV | AS23: 5 | AT23: 12
A24: 21 | B24: Metronidazol | C24: 10 | D24: 0 | E24: 10 | F24: mg | G24: 1 | H24: kg | I24: 0 | J24: 8 | K24: 0 | L24: 0 | N24: 0 | O24: 30 | R24: AMOXicilina 250 mg/5 ml (5%) Suspension Oral Frasco x 45 ml | S24: ITB | T24: Oral | U24: 50 | V24: 0 | W24: =U24 -> 50 | X24: 24 | Z24: Amoxicilina | AA24: Oral | AB24: 90 | AC24: 8 | AQ24: Vancomicina | AR24: IV | AS24: 15 | AT24: 6 | AV24: Vancomicina | AW24: Via endovenosa | AX24: 40-60 | AY24: 6-8 horas
A25: 22 | B25: Oxacilina (Sal Sodica) 1000 mg Polvo para Inyeccion | C25: 200 | D25: 0 | E25: =+C25 -> 200 | F25: mg | G25: 1 | H25: kg | I25: 0 | J25: 8 | K25: 1000 | L25: 0 | N25: 0 | O25: 600 | R25: Clindamicina (Fosfato) 600 mg /4ml Solucion Inyectable | S25: ITB | T25: Ora/IV | U25: 10 | V25: 0 | W25: =U25 -> 10 | X25: 24 | Z25: Azitromicina | AA25: Oral | AB25: 5 – 10 | AC25: 24
A26: 23 | B26: Piperacilina +Tazobactam | C26: 300 | D26: 400 | E26: =+(C26+D26)/2 -> 350 | F26: mg | G26: 1 | H26: kg | I26: 6 | J26: 8 | K26: 0 | L26: 0 | N26: 1200 | O26: 0 | R26: Cefazolina 1000 mg Polvo para Inyeccion | S26: ITB | T26: IV | U26: 50 | V26: 150 | W26: =+(U26+V26)/2 -> 100 | X26: 24 | Z26: Ampicilina | AA26: IV | AB26: 200 | AC26: 6 | AJ26: ITU | AQ26: ITB | AV26: NAC
A27: 23 | B27: Piperacilina +Tazobactam | C27: 5 | D27: 0 | E27: 5 | F27: mg | G27: 1 | H27: kg | I27: 0 | J27: 12 | K27: 0 | L27: 0 | M27: TPMs | N27: 10 | O27: 0 | R27: TRIMEtoprim 160 mg SULFAmetoxazol 800 mg TABleta | S27: ITB | T27: Oral/IV | U27: 5 | V27: 0 | W27: =U27 -> 5 | X27: 24 | Z27: Ampicilina/sulbactam | AA27: IV | AB27: 200 | AC27: 6 | AQ27: Medicamento | AR27: Ruta | AS27: Dosis | AT27: Intervalo | AV27: Medicamento | AW27: Ruta | AX27: Dosis (mg/kg/dia) | AY27: Intervalo (horas)
A28: 24 | B28: TRIMEtoprim 160 mg SULFAmetoxazol 800 mg TABleta | C28: 6 | D28: 10 | E28: =+(C28+D28)/2 -> 8 | F28: mg | G28: 1 | H28: kg | I28: 6 | J28: 8 | K28: 160 | L28: 800 | N28: 24 | O28: 30 | R28: TRIMEtoprim-SULFAmetoxazol (40-200)mg/5 ml SUSP | S28: ITB | T28: Oral/IV | U28: 5 | V28: 0 | W28: =U28 -> 5 | X28: 24 | Z28: Penicilina G | AA28: IV | AB28: 100.000 - 250.000 UI | AC28: 4 – 6 | AS28: (mg/kg/dosis) | AT28: (horas)
A29: 25 | B29: Vancomicina (Clorhidrato) 500 mg Polvo para Inyeccion | C29: 15 | D29: 0 | E29: =+C29 -> 15 | F29: mg | G29: 1 | H29: kg | I29: 0 | J29: 6 | K29: 500 | L29: 0 | N29: 45 | O29: 0 | R29: Trimetoprim - Sulfametoxazol (80 - 400) mg/5ml Sol Iny | S29: ITB | T29: Oral/IV | U29: 5 | V29: 0 | W29: =U29 -> 5 | X29: 24 | Z29: Ceftriaxona | AA29: IV | AB29: 75 | AC29: 24
A30: 26 | B30: Ciprofloxacina (Clorhidrato) 100 mg/10 ml Sln Inyectable | C30: 20 | D30: 30 | E30: =+C30 -> 20 | F30: mg | G30: 1 | H30: kg | I30: 0 | J30: 12 | K30: 100 | L30: 0 | N30: 40 | O30: 60 | R30: Oxacilina (Sal Sodica) 1000 mg Polvo para Inyeccion | S30: ITB | T30: IV | U30: 200 | V30: 0 | W30: =U30 -> 200 | X30: 24 | Z30: Cefotaxima | AA30: IV | AB30: 150 | AC30: 8
B31: Medicamento | C31: Dosis (mg/kg/día) | I31: Intervalo (horas) | R31: Piperacilina - Tazobactam 4500 mg Polvo para Inyeccion | S31: ITB | T31: IV | U31: 300 | V31: 400 | W31: =+(U31+V31)/2 -> 350 | X31: 24 | Z31: Clindamicina | AA31: IV/oral | AB31: 30 – 40 | AC31: 6 – 8
R32: Vancomicina (Clorhidrato) 500 mg Polvo para Inyeccion | S32: ITB | T32: IV | U32: 60 | V32: 0 | W32: =U32 -> 60 | X32: 24 | Z32: Vancomicina | AA32: IV | AB32: 60 | AC32: 6 – 8
R33: Linezolid 600 mg Tableta (REG) | S33: ITB | T33: VO | U33: 20 | V33: 30 | W33: =+(U33+V33)/2 -> 25 | X33: 24 | Z33: Oseltamivir | AA33: Oral | AB33: Ver nota | AC33: 12
R34: Linezolid 2 mg/ml Sln Inyectable x 300 ml (REG) | S34: ITB | T34: IV/VO | U34: 20 | V34: 30 | W34: =+(U34+V34)/2 -> 25 | X34: 24 | Z34: Amikacina | AB34: 15 – 20 | AC34: 24
R35: Daptomicina 350mg solucion inyectable (REG) | S35: ITB | T35: IV | U35: 5 | V35: 10 | W35: =+(U35+V35)/2 -> 7.5 | X35: 24 | Z35: Ampicilina | AB35: 200 – 300 | AC35: 6
R36: Ceftarolina* | S36: ITB | T36: IV | U36: 18 | V36: 36 | W36: =+(U36+V36)/2 -> 27 | X36: 24 | Z36: Cefepima | AB36: 150 | AC36: 8
R37: AMOXicilina 500 mg Capsula | S37: NAC | T37: Vía oral | U37: 90 | V37: 0 | W37: =U37 -> 90 | X37: 24 | Z37: Cefotaxima | AB37: 200 – 300 | AC37: 6 – 8
R38: AMOXicilina 250 mg/5 ml (5%) Suspension Oral Frasco x 45 ml | S38: NAC | T38: Vía oral | U38: 90 | V38: 0 | W38: =U38 -> 90 | X38: 24 | Z38: Ceftazidima | AB38: 150 | AC38: 8
R39: AZITromicina 500 mg Tableta | S39: NAC | T39: Vía oral | U39: 5 | V39: 10 | W39: =+(U39+V39)/2 -> 7.5 | X39: 24 | Z39: Ceftriaxona | AB39: 100 | AC39: 12
R40: AZITromicina200mg/5 ml (4%)Polvo para reconstituirx15ml | S40: NAC | T40: Vía oral | U40: 5 | V40: 10 | W40: =+(U40+V40)/2 -> 7.5 | X40: 24 | Z40: Gentamicina como terapia adyuvante | AB40: 5 – 7,5 | AC40: 24
R41: AMPIcilina (Sal Sodica) x 1000 mg Polvo para Inyeccion | S41: NAC | T41: Via endovenosa | U41: 200 | V41: 0 | W41: =U41 -> 200 | X41: 24 | Z41: Meropenem | AB41: 120 | AC41: 8
R42: AMPIcilina 250 mg/5 mL (5%) Polvo para Suspension Oral 60 ml | S42: NAC | T42: Via endovenosa | U42: 200 | V42: 0 | W42: =U42 -> 200 | X42: 24 | Z42: Oxacilina | AB42: 200 | AC42: 6
R43: AMPIcilina 500 mg Polvo para Inyeccion | S43: NAC | T43: Via endovenosa | U43: 200 | V43: 0 | W43: =U43 -> 200 | X43: 24 | Z43: Penicilina G | AB43: 300000 U | AC43: 4 – 6
R44: AMPIcilina Anhidra o Trihidrato 500 mg Tableta | S44: NAC | T44: Via endovenosa | U44: 200 | V44: 0 | W44: =U44 -> 200 | X44: 24 | Z44: Rifampicina | AB44: 10 – 20 | AC44: 12
R45: AMPIcilina Sodica/SULBactam Sodico 1000/500mg Polvo para iny (Ped) | S45: NAC | T45: Via endovenosa | U45: 200 | V45: 0 | W45: =U45 -> 200 | X45: 24 | Z45: Trimetoprim-sulfametoxazol | AB45: 10 – 20 | AC45: 12
R46: Ampicilina Sodica/Sulbactam Sodico 1,5 g Polvo para iny (adulto) | S46: NAC | T46: Via endovenosa | U46: 200 | V46: 0 | W46: =U46 -> 200 | X46: 24 | Z46: Vancomicina | AB46: 60 | AC46: 6
R47: PENIcilina G BENZAtinica 1.200.000 U Polvo para INYeccion | S47: NAC | T47: Via endovenosa | U47: 100000 | V47: 250000 | W47: =+(U47+V47)/2 -> 175000 | X47: 24
R48: PENIcilina G PROCAinica 400.000 U Polvo para INYeccion | S48: NAC | T48: Via endovenosa | U48: 100000 | V48: 250000 | W48: =+(U48+V48)/2 -> 175000 | X48: 24
R49: PENIcilina G SODica 1.000.000 U Polvo para INYeccion | S49: NAC | T49: Via endovenosa | U49: 100000 | V49: 250000 | W49: =+(U49+V49)/2 -> 175000 | X49: 24
R50: Ceftriaxona (Sal Sodica) 1000 mg Polvo para Inyeccion | S50: NAC | T50: Via endovenosa | U50: 75 | V50: 0 | W50: =U50 -> 75 | X50: 24
R51: Cefotaxime 1000 mg Polvo para inyeccion | S51: NAC | T51: Via endovenosa | U51: 150 | V51: 0 | W51: =U51 -> 150 | X51: 24
R52: Clindamicina (Fosfato) 600 mg /4ml Solucion Inyectable | S52: NAC | T52: Via endovenosa | U52: 30 | V52: 40 | W52: =+(U52+V52)/2 -> 35 | X52: 24
R53: Vancomicina (Clorhidrato) 500 mg Polvo para Inyeccion | S53: NAC | T53: Via endovenosa | U53: 60 | V53: 0 | W53: =U53 -> 60 | X53: 24
R54: Oseltamivir 75 mg Capsula (REG) (SP) | S54: NAC | T54: Vía oral | U54: 8 | V54: 0 | W54: 0 | X54: 24
R55: AMIKacina (Sulfato) 500 mg/2 ml Solucion Inyectable | S55: Meningitis | U55: 15 | V55: 20 | W55: =+(U55+V55)/2 -> 17.5 | X55: 24
R56: AMIKacina (Sulfato) 100 mg/2 ml Solucion Inyectable | S56: Meningitis | U56: 15 | V56: 20 | W56: =+(U56+V56)/2 -> 17.5 | X56: 24
R57: AMPIcilina (Sal Sodica) x 1000 mg Polvo para Inyeccion | S57: Meningitis | U57: 200 | V57: 300 | W57: =+(U57+V57)/2 -> 250 | X57: 24
A58: 1 | B58: 2 | C58: 3 | D58: 4 | E58: 5 | F58: 6 | G58: 7 | H58: 8 | I58: 9 | J58: 10 | K58: 11 | L58: 12 | M58: 13 | N58: 14 | O58: 15 | P58: 16 | R58: AMPIcilina 250 mg/5 mL (5%) Polvo para Suspension Oral 60 ml | S58: Meningitis | U58: 200 | V58: 300 | W58: =+(U58+V58)/2 -> 250 | X58: 24
R59: AMPIcilina 500 mg Polvo para Inyeccion | S59: Meningitis | U59: 200 | V59: 300 | W59: =+(U59+V59)/2 -> 250 | X59: 24
R60: AMPIcilina Anhidra o Trihidrato 500 mg Tableta | S60: Meningitis | U60: 200 | V60: 300 | W60: =+(U60+V60)/2 -> 250 | X60: 24
R61: Cefepime 1000 mg Polvo para inyeccion | S61: Meningitis | U61: 150 | V61: 0 | W61: =U61 -> 150 | X61: 24
R62: Cefotaxime 1000 mg Polvo para inyeccion | S62: Meningitis | U62: 200 | V62: 300 | W62: =+(U62+V62)/2 -> 250 | X62: 24
R63: Ceftazidima 1000 mg polvo para inyeccion | S63: Meningitis | U63: 150 | V63: 0 | W63: =U63 -> 150 | X63: 24
R64: Ceftriaxona (Sal Sodica) 1000 mg Polvo para Inyeccion | S64: Meningitis | U64: 100 | V64: 0 | W64: =U64 -> 100 | X64: 24
R65: Gentamicina 20 mg/2 ml Solucion Inyectable | S65: Meningitis | U65: 5 | V65: 7.5 | W65: =+(U65+V65)/2 -> 6.25 | X65: 24
R66: Gentamicina 40 mg/1 ml Solucion Inyectable | S66: Meningitis | U66: 5 | V66: 7.5 | W66: =+(U66+V66)/2 -> 6.25 | X66: 24
R67: Gentamicina 80 mg/2 ml Solucion Inyectable | S67: Meningitis | U67: 5 | V67: 7.5 | W67: =+(U67+V67)/2 -> 6.25 | X67: 24
R68: Meropenem (REG) 1000 mg Polvo para Inyeccion | S68: Meningitis | U68: 120 | V68: 0 | W68: =U68 -> 120 | X68: 24
R69: Meropenem 500 mg Polvo para Inyeccion (REG) | S69: Meningitis | U69: 120 | V69: 0 | W69: =U69 -> 120 | X69: 24
R70: Oxacilina (Sal Sodica) 1000 mg Polvo para Inyeccion | S70: Meningitis | U70: 200 | V70: 0 | W70: =U70 -> 200 | X70: 24
